Workbook
Name Срез_Контрагент: #N/A
Name Срез_Культура: #N/A
Name Срез_Культура1: #N/A
Name Срез_Орошение: #N/A
Name Срез_Орошение1: #N/A
Name Срез_Полив: #N/A

Sheet ОТЧЕТ 2026
B2: ОПЕРАТИВНАЯ ИНФОРМАЦИЯ ПО СБОРУ ГОРОШКА (СЕЗОН 2026 г.)
B19: ИЮНЬ
B20: Пн | C20: Вт | D20: Ср | E20: Чт | F20: Пт | G20: Сб | H20: Вс
B21: 1 | C21: =B21+1 -> 2 | D21: =C21+1 -> 3 | E21: =D21+1 -> 4 | F21: =E21+1 -> 5 | G21: =F21+1 -> 6 | H21: =G21+1 -> 7
B22: =H21+1 -> 8 | C22: =B22+1 -> 9 | D22: =C22+1 -> 10 | E22: =D22+1 -> 11 | F22: =E22+1 -> 12 | G22: =F22+1 -> 13 | H22: =G22+1 -> 14
B23: =H22+1 -> 15 | C23: =B23+1 -> 16 | D23: =C23+1 -> 17 | E23: =D23+1 -> 18 | F23: =E23+1 -> 19 | G23: =F23+1 -> 20 | H23: =G23+1 -> 21
B24: =H23+1 -> 22 | C24: =B24+1 -> 23 | D24: =C24+1 -> 24 | E24: =D24+1 -> 25 | F24: =E24+1 -> 26 | G24: =F24+1 -> 27 | H24: =G24+1 -> 28
B25: =H24+1 -> 29 | C25: =B25+1 -> 30
B26: ИЮЛЬ
D27: =1 -> 1 | E27: =D27+1 -> 2 | F27: =E27+1 -> 3 | G27: =F27+1 -> 4 | H27: =G27+1 -> 5
B28: =H27+1 -> 6 | C28: =B28+1 -> 7 | D28: =C28+1 -> 8 | E28: =D28+1 -> 9 | F28: =E28+1 -> 10 | G28: =F28+1 -> 11 | H28: =G28+1 -> 12
B29: =H28+1 -> 13 | C29: =B29+1 -> 14 | D29: =C29+1 -> 15 | E29: =D29+1 -> 16 | F29: =E29+1 -> 17 | G29: =F29+1 -> 18 | H29: =G29+1 -> 19
B31: День уборки - | E31: 34

Sheet Свод 2026
A1: Уборка гороха овощного в 2026 году на | C1: 46209
D3: Значения
A4: Культура | B4: Дата отчета | C4: Поле | D4: Площадь уборки, га | E4: Физический вес, кг | F4: в т.ч. Продажа, кг | G4: Зачетный вес, кг | H4: Урожайность физ.вес, т/га | I4: Урожайность зач. вес, т/га | J4: Степень зрелости, %
A5: ГРК (богара) | D5: 670.96029 | E5: 3918200 | F5: 332070 | G5: 3351407.6 | H5: 5.8396899 | I5: 4.9949418 | J5: 56.257396
A6: ГРК (полив) | D6: 350.03971 | E6: 1284550 | F6: 148150 | G6: 1125748.3 | H6: 3.6697265 | I6: 3.2160588 | J6: 57.22963
A7: Агролидер (полив) | D7: 269.1 | E7: 1397320 | F7: 399320 | G7: 1257990.1 | H7: 5.1925678 | I7: 4.6748053 | J7: 60.064815
A8: Колос (полив) | D8: 373.2 | E8: 1634840 | F8: 277580 | G8: 1468262.5 | H8: 4.3806002 | I8: 3.9342511 | J8: 57.579365
A9: Общий итог | D9: 1663.3 | E9: 8234910 | F9: 1157120 | G9: 7203408.5 | H9: 4.9509469 | I9: 4.3307933 | J9: 57.260255

Sheet Структура 2026 
A2: Структура посевных площадей
A4: Отбор: | B4: Год урожая Равно "2026 г." И Участок не используется Равно "Нет"
A6: Год урожая | D6: Площадь общая | E6: Площадь сева
A7: Подразделение
A8: Культура
A9: Поле
A10: 2026 г. | D10: 8282.66 | E10: 8282.66
A11: 2. Растениеводство (20) | D11: 5345 | E11: 5345
A12: Кукуруза на зерно | D12: 237 | E12: 237
A13: А-102/1 | D13: 5 | E13: 5
A14: А-103/1 | D14: 35 | E14: 35
A15: А-108/3 | D15: 9 | E15: 9
A16: А-109/1 | D16: 18 | E16: 18
A17: А-11 | D17: 17 | E17: 17
A18: А-110/1 | D18: 7 | E18: 7
A19: А-68/1 | D19: 77 | E19: 77
A20: А-84/1 | D20: 69 | E20: 69
A21: Подсолнечник | D21: 910 | E21: 910
... A165: Итого | D165: 8282.66 | E165: 8282.66

Sheet Подробности1
A1: Сведения о уборка - Поле: А-108/7, Культура: ГРК (полив)
A3: Культура | B3: Поле | C3: Сорт | D3: Площадь поля | E3: Площадь внесения | F3: Площадь уборки
A4: ГРК (полив) | B4: А-108/7 | C4: Патриот | D4: 102 | E4: 102 | F4: 3.1307448

Sheet Подробности2
A1: Сведения о уборка - Культура: ГРК (полив)
A3: Культура | B3: Поле | C3: Сорт | D3: Площадь поля | E3: Площадь внесения | F3: Площадь уборки
A4: ГРК (полив) | B4: А-54 | C4: Женева | D4: 55 | E4: 54 | F4: 46
A5: ГРК (полив) | B5: А-82/1 | C5: Женева | D5: 20 | E5: 8 | F5: 6
A6: ГРК (полив) | B6: А-104/1 | C6: Патриот | D6: 49 | E6: 33 | F6: 0
A7: ГРК (полив) | B7: А-108/7 | C7: Патриот | D7: 102 | E7: 102 | F7: 0
A8: ГРК (полив) | B8: А-112/2 | C8: Тристар | D8: 20 | E8: 20 | F8: 20
A9: ГРК (полив) | B9: А-54 | C9: Тристар | D9: 55 | E9: 1 | F9: 9
A10: ГРК (полив) | B10: А-54/4 | C10: Тристар | D10: 39 | E10: 39 | F10: 39
A11: ГРК (полив) | B11: А-81/1 | C11: Тристар | D11: 19 | E11: 19 | F11: 19
A12: ГРК (полив) | B12: А-82/1 | C12: Тристар | D12: 20 | E12: 12 | F12: 0
A13: ГРК (полив) | B13: А-79 | C13: Увертюра | D13: 54 | E13: 54 | F13: 33
A14: ГРК (полив) | B14: А-104/1 | C14: Фаворит | D14: 49 | E14: 16 | F14: 43.994136
A15: ГРК (полив) | B15: А-113/1 | C15: Фаворит | D15: 62 | E15: 62 | F15: 16.801585

Sheet Уборка по полям 2026
B1: Культура | C1: Поле | D1: Сорт | E1: Площадь поля | F1: Площадь внесения | G1: Площадь уборки
B2: ГРК (богара) | C2: А-104/1 | D2: Женева | E2: 11 | F2: 1.5 | G2: =SUMIFS('Реестр уборки 2026'!V:V,'Реестр уборки 2026'!W:W,Таблица13[[#This Row],[Культура]],'Реестр уборки 2026'!T:T,Таблица13[[#This Row],[Поле]],'Реестр уборки 2026'!U:U,Таблица13[[#This Row],[Сорт]]) -> 0 | L2: Площадь, га
B3: ГРК (богара) | C3: А-104/1 | D3: Патриот | E3: 11 | F3: 8 | G3: =SUMIFS('Реестр уборки 2026'!V:V,'Реестр уборки 2026'!W:W,Таблица13[[#This Row],[Культура]],'Реестр уборки 2026'!T:T,Таблица13[[#This Row],[Поле]],'Реестр уборки 2026'!U:U,Таблица13[[#This Row],[Сорт]]) -> 11 | I3: Культура | J3: Поле | K3: Сорт | L3: сев | M3: уборка | N3: остаток
B4: ГРК (богара) | C4: А-104/1 | D4: Тристар | E4: 11 | F4: 1.5 | G4: =SUMIFS('Реестр уборки 2026'!V:V,'Реестр уборки 2026'!W:W,Таблица13[[#This Row],[Культура]],'Реестр уборки 2026'!T:T,Таблица13[[#This Row],[Поле]],'Реестр уборки 2026'!U:U,Таблица13[[#This Row],[Сорт]]) -> 0 | I4: ГРК (богара) | J4: А-104/1 | L4: 11 | M4: 11 | N4: =M4-L4 -> 0
B5: ГРК (богара) | C5: А-105/1 | D5: Авола | E5: 56 | F5: 54.5 | G5: =SUMIFS('Реестр уборки 2026'!V:V,'Реестр уборки 2026'!W:W,Таблица13[[#This Row],[Культура]],'Реестр уборки 2026'!T:T,Таблица13[[#This Row],[Поле]],'Реестр уборки 2026'!U:U,Таблица13[[#This Row],[Сорт]]) -> 54.5 | J5: А-105/1 | L5: 56 | M5: 56 | N5: =M5-L5 -> 0
B6: ГРК (богара) | C6: А-105/1 | D6: Женева | E6: 56 | F6: 1.5 | G6: =SUMIFS('Реестр уборки 2026'!V:V,'Реестр уборки 2026'!W:W,Таблица13[[#This Row],[Культура]],'Реестр уборки 2026'!T:T,Таблица13[[#This Row],[Поле]],'Реестр уборки 2026'!U:U,Таблица13[[#This Row],[Сорт]]) -> 1.5 | J6: А-111/1 | L6: 14 | M6: 2 | N6: =M6-L6 -> -12 | O6: убрали на зерно
B7: ГРК (богара) | C7: А-111/1 | D7: Авола | E7: 14 | F7: 14 | G7: =SUMIFS('Реестр уборки 2026'!V:V,'Реестр уборки 2026'!W:W,Таблица13[[#This Row],[Культура]],'Реестр уборки 2026'!T:T,Таблица13[[#This Row],[Поле]],'Реестр уборки 2026'!U:U,Таблица13[[#This Row],[Сорт]]) -> 2 | J7: А-112/1 | L7: 40 | M7: 40 | N7: =M7-L7 -> 0
B8: ГРК (богара) | C8: А-112/1 | D8: Авола | E8: 40 | F8: 10 | G8: =SUMIFS('Реестр уборки 2026'!V:V,'Реестр уборки 2026'!W:W,Таблица13[[#This Row],[Культура]],'Реестр уборки 2026'!T:T,Таблица13[[#This Row],[Поле]],'Реестр уборки 2026'!U:U,Таблица13[[#This Row],[Сорт]]) -> 1 | J8: А-114 | L8: 4 | M8: 4 | N8: =M8-L8 -> 0
B9: ГРК (богара) | C9: А-112/1 | D9: Тристар | E9: 40 | F9: 30 | G9: =SUMIFS('Реестр уборки 2026'!V:V,'Реестр уборки 2026'!W:W,Таблица13[[#This Row],[Культура]],'Реестр уборки 2026'!T:T,Таблица13[[#This Row],[Поле]],'Реестр уборки 2026'!U:U,Таблица13[[#This Row],[Сорт]]) -> 39 | J9: А-115/1 | L9: 63 | M9: 63 | N9: =M9-L9 -> 0
B10: ГРК (богара) | C10: А-114 | D10: Женева | E10: 4 | F10: 4 | G10: =SUMIFS('Реестр уборки 2026'!V:V,'Реестр уборки 2026'!W:W,Таблица13[[#This Row],[Культура]],'Реестр уборки 2026'!T:T,Таблица13[[#This Row],[Поле]],'Реестр уборки 2026'!U:U,Таблица13[[#This Row],[Сорт]]) -> 4 | J10: А-116/1 | L10: 47 | M10: 32 | N10: =M10-L10 -> -15 | O10: уберем на зерно
B11: ГРК (богара) | C11: А-115/1 | D11: Тристар | E11: 63 | F11: 63 | G11: =SUMIFS('Реестр уборки 2026'!V:V,'Реестр уборки 2026'!W:W,Таблица13[[#This Row],[Культура]],'Реестр уборки 2026'!T:T,Таблица13[[#This Row],[Поле]],'Реестр уборки 2026'!U:U,Таблица13[[#This Row],[Сорт]]) -> 63 | J11: А-22/1 | L11: 36 | M11: 36 | N11: =M11-L11 -> 0
B12: ГРК (богара) | C12: А-116/1 | D12: Фаворит | E12: 47 | F12: 47 | G12: =SUMIFS('Реестр уборки 2026'!V:V,'Реестр уборки 2026'!W:W,Таблица13[[#This Row],[Культура]],'Реестр уборки 2026'!T:T,Таблица13[[#This Row],[Поле]],'Реестр уборки 2026'!U:U,Таблица13[[#This Row],[Сорт]]) -> 32 | J12: А-23 | L12: 41 | M12: 20 | N12: =M12-L12 -> -21 | O12: убрали на зерно
B13: ГРК (богара) | C13: А-22/1 | D13: Тиара | E13: 36 | F13: 5 | G13: =SUMIFS('Реестр уборки 2026'!V:V,'Реестр уборки 2026'!W:W,Таблица13[[#This Row],[Культура]],'Реестр уборки 2026'!T:T,Таблица13[[#This Row],[Поле]],'Реестр уборки 2026'!U:U,Таблица13[[#This Row],[Сорт]]) -> 5 | J13: А-24/1 | L13: 39 | M13: 39 | N13: =M13-L13 -> 0
B14: ГРК (богара) | C14: А-22/1 | D14: Увертюра | E14: 36 | F14: 31 | G14: =SUMIFS('Реестр уборки 2026'!V:V,'Реестр уборки 2026'!W:W,Таблица13[[#This Row],[Культура]],'Реестр уборки 2026'!T:T,Таблица13[[#This Row],[Поле]],'Реестр уборки 2026'!U:U,Таблица13[[#This Row],[Сорт]]) -> 31 | J14: А-3 | L14: 79 | M14: 79 | N14: =M14-L14 -> 0
B15: ГРК (богара) | C15: А-23 | D15: Увертюра | E15: 41 | F15: 20 | G15: =SUMIFS('Реестр уборки 2026'!V:V,'Реестр уборки 2026'!W:W,Таблица13[[#This Row],[Культура]],'Реестр уборки 2026'!T:T,Таблица13[[#This Row],[Поле]],'Реестр уборки 2026'!U:U,Таблица13[[#This Row],[Сорт]]) -> 20 | J15: А-38 | L15: 38 | M15: 38 | N15: =M15-L15 -> 0
B16: ГРК (богара) | C16: А-23 | D16: Фаворит | E16: 41 | F16: 21 | G16: =SUMIFS('Реестр уборки 2026'!V:V,'Реестр уборки 2026'!W:W,Таблица13[[#This Row],[Культура]],'Реестр уборки 2026'!T:T,Таблица13[[#This Row],[Поле]],'Реестр уборки 2026'!U:U,Таблица13[[#This Row],[Сорт]]) -> 0 | J16: А-4/1 | L16: 111 | M16: 111 | N16: =M16-L16 -> 0
B17: ГРК (богара) | C17: А-24/1 | D17: Фаворит | E17: 39 | F17: 39 | G17: =SUMIFS('Реестр уборки 2026'!V:V,'Реестр уборки 2026'!W:W,Таблица13[[#This Row],[Культура]],'Реестр уборки 2026'!T:T,Таблица13[[#This Row],[Поле]],'Реестр уборки 2026'!U:U,Таблица13[[#This Row],[Сорт]]) -> 39 | J17: А-5/1 | L17: 63 | M17: 26 | N17: =M17-L17 -> -37 | O17: убрали на зерно
B18: ГРК (богара) | C18: А-3 | D18: Авола | E18: 79 | F18: 79 | G18: =SUMIFS('Реестр уборки 2026'!V:V,'Реестр уборки 2026'!W:W,Таблица13[[#This Row],[Культура]],'Реестр уборки 2026'!T:T,Таблица13[[#This Row],[Поле]],'Реестр уборки 2026'!U:U,Таблица13[[#This Row],[Сорт]]) -> 79 | J18: А-76/3 | L18: 41 | M18: 41 | N18: =M18-L18 -> 0
B19: ГРК (богара) | C19: А-38 | D19: Авола | E19: 38 | F19: 38 | G19: =SUMIFS('Реестр уборки 2026'!V:V,'Реестр уборки 2026'!W:W,Таблица13[[#This Row],[Культура]],'Реестр уборки 2026'!T:T,Таблица13[[#This Row],[Поле]],'Реестр уборки 2026'!U:U,Таблица13[[#This Row],[Сорт]]) -> 38 | J19: А-76/5 | L19: 14 | M19: 14 | N19: =M19-L19 -> 0
B20: ГРК (богара) | C20: А-4/1 | D20: Тиара | E20: 111 | F20: 111 | G20: =SUMIFS('Реестр уборки 2026'!V:V,'Реестр уборки 2026'!W:W,Таблица13[[#This Row],[Культура]],'Реестр уборки 2026'!T:T,Таблица13[[#This Row],[Поле]],'Реестр уборки 2026'!U:U,Таблица13[[#This Row],[Сорт]]) -> 111 | J20: А-83/1 | L20: 24 | M20: 3 | N20: =M20-L20 -> -21 | O20: убрали на зерно
B21: ГРК (богара) | C21: А-5/1 | D21: Авола | E21: 63 | F21: 63 | G21: =SUMIFS('Реестр уборки 2026'!V:V,'Реестр уборки 2026'!W:W,Таблица13[[#This Row],[Культура]],'Реестр уборки 2026'!T:T,Таблица13[[#This Row],[Поле]],'Реестр уборки 2026'!U:U,Таблица13[[#This Row],[Сорт]]) -> 26 | J21: А-83/2 | L21: 57 | M21: 57 | N21: =M21-L21 -> 0
B22: ГРК (богара) | C22: А-76/3 | D22: Авола | E22: 41 | F22: 41 | G22: =SUMIFS('Реестр уборки 2026'!V:V,'Реестр уборки 2026'!W:W,Таблица13[[#This Row],[Культура]],'Реестр уборки 2026'!T:T,Таблица13[[#This Row],[Поле]],'Реестр уборки 2026'!U:U,Таблица13[[#This Row],[Сорт]]) -> 41 | I22: ГРК (богара) Итог | L22: 778 | M22: 672 | N22: =M22-L22 -> -106
B23: ГРК (богара) | C23: А-76/5 | D23: Авола | E23: 14 | F23: 14 | G23: =SUMIFS('Реестр уборки 2026'!V:V,'Реестр уборки 2026'!W:W,Таблица13[[#This Row],[Культура]],'Реестр уборки 2026'!T:T,Таблица13[[#This Row],[Поле]],'Реестр уборки 2026'!U:U,Таблица13[[#This Row],[Сорт]]) -> 14 | I23: ГРК (полив) | J23: А-104/1 | L23: 49 | M23: 49 | N23: =M23-L23 -> 0
B24: ГРК (богара) | C24: А-83/1 | D24: Фаворит | E24: 24 | F24: 24 | G24: =SUMIFS('Реестр уборки 2026'!V:V,'Реестр уборки 2026'!W:W,Таблица13[[#This Row],[Культура]],'Реестр уборки 2026'!T:T,Таблица13[[#This Row],[Поле]],'Реестр уборки 2026'!U:U,Таблица13[[#This Row],[Сорт]]) -> 3 | J24: А-108/7 | L24: 102 | M24: 77 | N24: =M24-L24 -> -25
B25: ГРК (богара) | C25: А-83/2 | D25: Авола | E25: 57 | F25: 52 | G25: =SUMIFS('Реестр уборки 2026'!V:V,'Реестр уборки 2026'!W:W,Таблица13[[#This Row],[Культура]],'Реестр уборки 2026'!T:T,Таблица13[[#This Row],[Поле]],'Реестр уборки 2026'!U:U,Таблица13[[#This Row],[Сорт]]) -> 52 | J25: А-112/2 | L25: 20 | M25: 20 | N25: =M25-L25 -> 0
B26: ГРК (богара) | C26: А-83/2 | D26: Фаворит | E26: 57 | F26: 5 | G26: =SUMIFS('Реестр уборки 2026'!V:V,'Реестр уборки 2026'!W:W,Таблица13[[#This Row],[Культура]],'Реестр уборки 2026'!T:T,Таблица13[[#This Row],[Поле]],'Реестр уборки 2026'!U:U,Таблица13[[#This Row],[Сорт]]) -> 5 | J26: А-113/1 | L26: 62 | M26: 62 | N26: =M26-L26 -> 0
B27: ГРК (полив) | C27: А-104/1 | D27: Патриот | E27: 49 | F27: 33 | G27: =SUMIFS('Реестр уборки 2026'!V:V,'Реестр уборки 2026'!W:W,Таблица13[[#This Row],[Культура]],'Реестр уборки 2026'!T:T,Таблица13[[#This Row],[Поле]],'Реестр уборки 2026'!U:U,Таблица13[[#This Row],[Сорт]]) -> 0 | J27: А-54 | L27: 55 | M27: 55 | N27: =M27-L27 -> 0
B28: ГРК (полив) | C28: А-104/1 | D28: Фаворит | E28: 49 | F28: 16 | G28: =SUMIFS('Реестр уборки 2026'!V:V,'Реестр уборки 2026'!W:W,Таблица13[[#This Row],[Культура]],'Реестр уборки 2026'!T:T,Таблица13[[#This Row],[Поле]],'Реестр уборки 2026'!U:U,Таблица13[[#This Row],[Сорт]]) -> 49 | J28: А-54/4 | L28: 39 | M28: 39 | N28: =M28-L28 -> 0
B29: ГРК (полив) | C29: А-108/7 | D29: Патриот | E29: 102 | F29: 102 | G29: =SUMIFS('Реестр уборки 2026'!V:V,'Реестр уборки 2026'!W:W,Таблица13[[#This Row],[Культура]],'Реестр уборки 2026'!T:T,Таблица13[[#This Row],[Поле]],'Реестр уборки 2026'!U:U,Таблица13[[#This Row],[Сорт]]) -> 77 | J29: А-79 | L29: 54 | M29: 33 | N29: =M29-L29 -> -21 | O29: оставили на зерно
B30: ГРК (полив) | C30: А-112/2 | D30: Тристар | E30: 20 | F30: 20 | G30: =SUMIFS('Реестр уборки 2026'!V:V,'Реестр уборки 2026'!W:W,Таблица13[[#This Row],[Культура]],'Реестр уборки 2026'!T:T,Таблица13[[#This Row],[Поле]],'Реестр уборки 2026'!U:U,Таблица13[[#This Row],[Сорт]]) -> 20 | J30: А-81/1 | L30: 19 | M30: 19 | N30: =M30-L30 -> 0
B31: ГРК (полив) | C31: А-113/1 | D31: Фаворит | E31: 62 | F31: 62 | G31: =SUMIFS('Реестр уборки 2026'!V:V,'Реестр уборки 2026'!W:W,Таблица13[[#This Row],[Культура]],'Реестр уборки 2026'!T:T,Таблица13[[#This Row],[Поле]],'Реестр уборки 2026'!U:U,Таблица13[[#This Row],[Сорт]]) -> 62 | J31: А-82/1 | L31: 20 | M31: 6 | N31: =M31-L31 -> -14
B32: ГРК (полив) | C32: А-54 | D32: Женева | E32: 55 | F32: 54 | G32: =SUMIFS('Реестр уборки 2026'!V:V,'Реестр уборки 2026'!W:W,Таблица13[[#This Row],[Культура]],'Реестр уборки 2026'!T:T,Таблица13[[#This Row],[Поле]],'Реестр уборки 2026'!U:U,Таблица13[[#This Row],[Сорт]]) -> 46.2 | I32: ГРК (полив) Итог | L32: 420 | M32: 360 | N32: =M32-L32 -> -60
B33: ГРК (полив) | C33: А-54 | D33: Тристар | E33: 55 | F33: 1 | G33: =SUMIFS('Реестр уборки 2026'!V:V,'Реестр уборки 2026'!W:W,Таблица13[[#This Row],[Культура]],'Реестр уборки 2026'!T:T,Таблица13[[#This Row],[Поле]],'Реестр уборки 2026'!U:U,Таблица13[[#This Row],[Сорт]]) -> 8.8 | I33: Агролидер (полив) | J33: 12 Агролидер | L33: 76.64 | M33: 76.7 | N33: =M33-L33 -> 0.06
B34: ГРК (полив) | C34: А-54/4 | D34: Тристар | E34: 39 | F34: 39 | G34: =SUMIFS('Реестр уборки 2026'!V:V,'Реестр уборки 2026'!W:W,Таблица13[[#This Row],[Культура]],'Реестр уборки 2026'!T:T,Таблица13[[#This Row],[Поле]],'Реестр уборки 2026'!U:U,Таблица13[[#This Row],[Сорт]]) -> 39 | J34: 17 Агролидер | L34: 63.51 | M34: 63.5 | N34: =M34-L34 -> -0.01
B35: ГРК (полив) | C35: А-79 | D35: Увертюра | E35: 54 | F35: 54 | G35: =SUMIFS('Реестр уборки 2026'!V:V,'Реестр уборки 2026'!W:W,Таблица13[[#This Row],[Культура]],'Реестр уборки 2026'!T:T,Таблица13[[#This Row],[Поле]],'Реестр уборки 2026'!U:U,Таблица13[[#This Row],[Сорт]]) -> 33 | J35: 18 Агролидер | L35: 128.85 | M35: 128.9 | N35: =M35-L35 -> 0.05
B36: ГРК (полив) | C36: А-81/1 | D36: Тристар | E36: 19 | F36: 19 | G36: =SUMIFS('Реестр уборки 2026'!V:V,'Реестр уборки 2026'!W:W,Таблица13[[#This Row],[Культура]],'Реестр уборки 2026'!T:T,Таблица13[[#This Row],[Поле]],'Реестр уборки 2026'!U:U,Таблица13[[#This Row],[Сорт]]) -> 19 | I36: Агролидер (полив) Итог | L36: 269 | M36: 269.1 | N36: =M36-L36 -> 0.1
B37: ГРК (полив) | C37: А-82/1 | D37: Женева | E37: 20 | F37: 8 | G37: =SUMIFS('Реестр уборки 2026'!V:V,'Реестр уборки 2026'!W:W,Таблица13[[#This Row],[Культура]],'Реестр уборки 2026'!T:T,Таблица13[[#This Row],[Поле]],'Реестр уборки 2026'!U:U,Таблица13[[#This Row],[Сорт]]) -> 6 | I37: Колос (полив) | J37: 1.6 Колос | L37: 38.6 | M37: 38.6 | N37: =M37-L37 -> 0
B38: ГРК (полив) | C38: А-82/1 | D38: Тристар | E38: 20 | F38: 12 | G38: =SUMIFS('Реестр уборки 2026'!V:V,'Реестр уборки 2026'!W:W,Таблица13[[#This Row],[Культура]],'Реестр уборки 2026'!T:T,Таблица13[[#This Row],[Поле]],'Реестр уборки 2026'!U:U,Таблица13[[#This Row],[Сорт]]) -> 0 | J38: 1.7 Колос | L38: 55 | M38: 55 | N38: =M38-L38 -> 0
B39: Агролидер (полив) | C39: 12 Агролидер | D39: Женева | E39: 76.64 | F39: 46 | G39: =SUMIFS('Реестр уборки 2026'!V:V,'Реестр уборки 2026'!W:W,Таблица13[[#This Row],[Культура]],'Реестр уборки 2026'!T:T,Таблица13[[#This Row],[Поле]],'Реестр уборки 2026'!U:U,Таблица13[[#This Row],[Сорт]]) -> 46.1 | J39: 2.2 Колос | L39: 94.1 | M39: 79.1 | N39: =M39-L39 -> -15 | O39: 15 га оставлено (вымочки)
B40: Агролидер (полив) | C40: 12 Агролидер | D40: Тристар | E40: 76.64 | F40: 30.64 | G40: =SUMIFS('Реестр уборки 2026'!V:V,'Реестр уборки 2026'!W:W,Таблица13[[#This Row],[Культура]],'Реестр уборки 2026'!T:T,Таблица13[[#This Row],[Поле]],'Реестр уборки 2026'!U:U,Таблица13[[#This Row],[Сорт]]) -> 30.6 | J40: 3.1 Колос | L40: 93.9 | M40: 42 | N40: =M40-L40 -> -51.9 | O40: 7 га оставлено (вымочки)
B41: Агролидер (полив) | C41: 17 Агролидер | D41: Тристар | E41: 63.51 | F41: 63.51 | G41: =SUMIFS('Реестр уборки 2026'!V:V,'Реестр уборки 2026'!W:W,Таблица13[[#This Row],[Культура]],'Реестр уборки 2026'!T:T,Таблица13[[#This Row],[Поле]],'Реестр уборки 2026'!U:U,Таблица13[[#This Row],[Сорт]]) -> 63.5 | J41: 3.3 Колос | L41: 102.44 | M41: 102.4 | N41: =M41-L41 -> -0.04
B42: Агролидер (полив) | C42: 18 Агролидер | D42: Тристар | E42: 128.85 | F42: 128.85 | G42: =SUMIFS('Реестр уборки 2026'!V:V,'Реестр уборки 2026'!W:W,Таблица13[[#This Row],[Культура]],'Реестр уборки 2026'!T:T,Таблица13[[#This Row],[Поле]],'Реестр уборки 2026'!U:U,Таблица13[[#This Row],[Сорт]]) -> 128.9 | J42: 3.6 Колос | L42: 56.12 | M42: 56.1 | N42: =M42-L42 -> -0.02
B43: Колос (полив) | C43: 1.6 Колос | D43: Фаворит | E43: 38.6 | F43: 38.6 | G43: =SUMIFS('Реестр уборки 2026'!V:V,'Реестр уборки 2026'!W:W,Таблица13[[#This Row],[Культура]],'Реестр уборки 2026'!T:T,Таблица13[[#This Row],[Поле]],'Реестр уборки 2026'!U:U,Таблица13[[#This Row],[Сорт]]) -> 38.6 | I43: Колос (полив) Итог | L43: 440.16 | M43: 373.2 | N43: =M43-L43 -> -66.96
B44: Колос (полив) | C44: 1.7 Колос | D44: Фаворит | E44: 55 | F44: 55 | G44: =SUMIFS('Реестр уборки 2026'!V:V,'Реестр уборки 2026'!W:W,Таблица13[[#This Row],[Культура]],'Реестр уборки 2026'!T:T,Таблица13[[#This Row],[Поле]],'Реестр уборки 2026'!U:U,Таблица13[[#This Row],[Сорт]]) -> 55 | I44: Общий итог | L44: 1907.16 | M44: 1674.3 | N44: =M44-L44 -> -232.86
B45: Колос (полив) | C45: 2.2 Колос | D45: Тристар | E45: 94.1 | F45: 81.7 | G45: =SUMIFS('Реестр уборки 2026'!V:V,'Реестр уборки 2026'!W:W,Таблица13[[#This Row],[Культура]],'Реестр уборки 2026'!T:T,Таблица13[[#This Row],[Поле]],'Реестр уборки 2026'!U:U,Таблица13[[#This Row],[Сорт]]) -> 0
B46: Колос (полив) | C46: 2.2 Колос | D46: Фаворит | E46: 94.1 | F46: 12.4 | G46: =SUMIFS('Реестр уборки 2026'!V:V,'Реестр уборки 2026'!W:W,Таблица13[[#This Row],[Культура]],'Реестр уборки 2026'!T:T,Таблица13[[#This Row],[Поле]],'Реестр уборки 2026'!U:U,Таблица13[[#This Row],[Сорт]]) -> 79.1
B47: Колос (полив) | C47: 3.1 Колос | D47: Беркут | E47: 93.9 | F47: 46.6 | G47: =SUMIFS('Реестр уборки 2026'!V:V,'Реестр уборки 2026'!W:W,Таблица13[[#This Row],[Культура]],'Реестр уборки 2026'!T:T,Таблица13[[#This Row],[Поле]],'Реестр уборки 2026'!U:U,Таблица13[[#This Row],[Сорт]]) -> 14.9
B48: Колос (полив) | C48: 3.1 Колос | D48: Тристар | E48: 93.9 | F48: 3.3 | G48: =SUMIFS('Реестр уборки 2026'!V:V,'Реестр уборки 2026'!W:W,Таблица13[[#This Row],[Культура]],'Реестр уборки 2026'!T:T,Таблица13[[#This Row],[Поле]],'Реестр уборки 2026'!U:U,Таблица13[[#This Row],[Сорт]]) -> 0
B49: Колос (полив) | C49: 3.1 Колос | D49: Фаворит | E49: 93.9 | F49: 44 | G49: =SUMIFS('Реестр уборки 2026'!V:V,'Реестр уборки 2026'!W:W,Таблица13[[#This Row],[Культура]],'Реестр уборки 2026'!T:T,Таблица13[[#This Row],[Поле]],'Реестр уборки 2026'!U:U,Таблица13[[#This Row],[Сорт]]) -> 27.1
B50: Колос (полив) | C50: 3.3 Колос | D50: Беркут | E50: 102.44 | F50: 70.4 | G50: =SUMIFS('Реестр уборки 2026'!V:V,'Реестр уборки 2026'!W:W,Таблица13[[#This Row],[Культура]],'Реестр уборки 2026'!T:T,Таблица13[[#This Row],[Поле]],'Реестр уборки 2026'!U:U,Таблица13[[#This Row],[Сорт]]) -> 67.4
B51: Колос (полив) | C51: 3.3 Колос | D51: Фаворит | E51: 102.44 | F51: 32.04 | G51: =SUMIFS('Реестр уборки 2026'!V:V,'Реестр уборки 2026'!W:W,Таблица13[[#This Row],[Культура]],'Реестр уборки 2026'!T:T,Таблица13[[#This Row],[Поле]],'Реестр уборки 2026'!U:U,Таблица13[[#This Row],[Сорт]]) -> 35
B52: Колос (полив) | C52: 3.6 Колос | D52: Фаворит | E52: 56.12 | F52: 56.12 | G52: =SUMIFS('Реестр уборки 2026'!V:V,'Реестр уборки 2026'!W:W,Таблица13[[#This Row],[Культура]],'Реестр уборки 2026'!T:T,Таблица13[[#This Row],[Поле]],'Реестр уборки 2026'!U:U,Таблица13[[#This Row],[Сорт]]) -> 56.1

Sheet Данные 2026
K1: протянуть формулу на след день
A2: 1.1 | B2: Выборка по КА, орошению | D2: 5 | I2: 8
A3: Валовый сбор | D3: Выполнение плана по сбору | E3: ПЛАН, т | F3: ФАКТ, т | G3: Исполнение плана, % | I3: Ежедневные показатели | K3: Сбор, т | L3: Значение спелости | M3: Финометр
A4: ПЛАН, т | B4: =C59 -> 9535.8 | D4: ГРК (богара) | E4: =C55 -> 3890 | F4: =D55 -> 3918.2 | G4: =IFERROR(F4/E4, ) -> 1.0072494 | I4: 1 | J4: 46176 | K4: =IFERROR(SUMIF('Реестр уборки 2026'!Z:Z,J4,'Реестр уборки 2026'!G:G)/1000, ) -> 191.51 | L4: =IFERROR(AVERAGEIF('Реестр уборки 2026'!Z:Z,'Данные 2026'!J4,'Реестр уборки 2026'!C:C),) -> 52.285714 | M4: нет данных
A5: ФАКТ, т | B5: =D59 -> 8234.91 | D5: ГРК (полив) | E5: =C56 -> 2100 | F5: =D56 -> 1284.55 | G5: =IFERROR(F5/E5, ) -> 0.61169048 | I5: 2 | J5: =J4+1 -> 46177 | K5: =IFERROR(SUMIF('Реестр уборки 2026'!Z:Z,J5,'Реестр уборки 2026'!G:G)/1000, ) -> 117.37 | L5: =IFERROR(AVERAGEIF('Реестр уборки 2026'!Z:Z,'Данные 2026'!J5,'Реестр уборки 2026'!C:C),) -> 52 | M5: нет данных
A6: Исполнение плана, % | B6: =E59 -> 0.8635783 | D6: Агролидер (полив) | E6: =C57 -> 1345 | F6: =D57 -> 1397.32 | G6: =IFERROR(F6/E6, ) -> 1.0388996 | I6: 3 | J6: =J5+1 -> 46178 | M6: нет данных
D7: Колос (полив) | E7: =C58 -> 2200.8 | F7: =D58 -> 1634.84 | G7: =IFERROR(F7/E7, ) -> 0.74283897 | I7: 4 | J7: =J6+1 -> 46179 | K7: =IFERROR(SUMIF('Реестр уборки 2026'!Z:Z,J7,'Реестр уборки 2026'!G:G)/1000, ) -> 268.92 | L7: =IFERROR(AVERAGEIF('Реестр уборки 2026'!Z:Z,'Данные 2026'!J7,'Реестр уборки 2026'!C:C),) -> 47.826087 | M7: нет данных
A8: 1.2 | I8: 5 | J8: =J7+1 -> 46180 | K8: =IFERROR(SUMIF('Реестр уборки 2026'!Z:Z,J8,'Реестр уборки 2026'!G:G)/1000, ) -> 222.31 | L8: =IFERROR(AVERAGEIF('Реестр уборки 2026'!Z:Z,'Данные 2026'!J8,'Реестр уборки 2026'!C:C),) -> 51.2 | M8: нет данных
A9: Зачетный вес | I9: 6 | J9: =J8+1 -> 46181 | K9: =IFERROR(SUMIF('Реестр уборки 2026'!Z:Z,J9,'Реестр уборки 2026'!G:G)/1000, ) -> 246.5 | L9: =IFERROR(AVERAGEIF('Реестр уборки 2026'!Z:Z,'Данные 2026'!J9,'Реестр уборки 2026'!C:C),) -> 49.55 | M9: нет данных
A10: ПЛАН, т | I10: 7 | J10: =J9+1 -> 46182 | K10: =IFERROR(SUMIF('Реестр уборки 2026'!Z:Z,J10,'Реестр уборки 2026'!G:G)/1000, ) -> 309.81 | L10: =IFERROR(AVERAGEIF('Реестр уборки 2026'!Z:Z,'Данные 2026'!J10,'Реестр уборки 2026'!C:C),) -> 53.269231 | M10: нет данных
A11: ФАКТ, т | I11: 8 | J11: =J10+1 -> 46183 | K11: =IFERROR(SUMIF('Реестр уборки 2026'!Z:Z,J11,'Реестр уборки 2026'!G:G)/1000, ) -> 373.68 | L11: =IFERROR(AVERAGEIF('Реестр уборки 2026'!Z:Z,'Данные 2026'!J11,'Реестр уборки 2026'!C:C),) -> 55.580645 | M11: нет данных
E12: =SUM(E4:E11) -> 9535.8 | F12: =SUM(F4:F11) -> 8234.91 | G12: =IFERROR(F12/E12, ) -> 0.8635783 | I12: 9 | J12: =J11+1 -> 46184 | K12: =IFERROR(SUMIF('Реестр уборки 2026'!Z:Z,J12,'Реестр уборки 2026'!G:G)/1000, ) -> 314.53 | L12: =IFERROR(AVERAGEIF('Реестр уборки 2026'!Z:Z,'Данные 2026'!J12,'Реестр уборки 2026'!C:C),) -> 61.192308 | M12: нет данных
A13: 2 | D13: 6 | I13: 10 | J13: =J12+1 -> 46185 | K13: =IFERROR(SUMIF('Реестр уборки 2026'!Z:Z,J13,'Реестр уборки 2026'!G:G)/1000, ) -> 275.87 | L13: =IFERROR(AVERAGEIF('Реестр уборки 2026'!Z:Z,'Данные 2026'!J13,'Реестр уборки 2026'!C:C),) -> 63.083333 | M13: нет данных
A14: Площадь уборки | D14: Выполнение плана по сбору | F14: Урожайность, т/га | G14: Вал, т | I14: 11 | J14: =J13+1 -> 46186 | K14: =IFERROR(SUMIF('Реестр уборки 2026'!Z:Z,J14,'Реестр уборки 2026'!G:G)/1000, ) -> 210.12 | L14: =IFERROR(AVERAGEIF('Реестр уборки 2026'!Z:Z,'Данные 2026'!J14,'Реестр уборки 2026'!C:C),) -> 60.833333 | M14: нет данных
A15: ПЛАН, га | B15: =F59 -> 1907.16 | D15: 2019 | F15: 3.3 | G15: 6813 | I15: 12 | J15: =J14+1 -> 46187 | K15: =IFERROR(SUMIF('Реестр уборки 2026'!Z:Z,J15,'Реестр уборки 2026'!G:G)/1000, ) -> 283.77 | L15: =IFERROR(AVERAGEIF('Реестр уборки 2026'!Z:Z,'Данные 2026'!J15,'Реестр уборки 2026'!C:C),) -> 62.375 | M15: нет данных
A16: ФАКТ, га | B16: =G59 -> 1674.3 | D16: 2020 | F16: 4.6 | G16: 12761 | I16: 13 | J16: =J15+1 -> 46188 | K16: =IFERROR(SUMIF('Реестр уборки 2026'!Z:Z,J16,'Реестр уборки 2026'!G:G)/1000, ) -> 274.72 | L16: =IFERROR(AVERAGEIF('Реестр уборки 2026'!Z:Z,'Данные 2026'!J16,'Реестр уборки 2026'!C:C),) -> 61.826087 | M16: нет данных
A17: Остаток, га | B17: =B15-B16 -> 232.86 | D17: 2021 | F17: 4.2 | G17: 10161 | I17: 14 | J17: =J16+1 -> 46189 | K17: =IFERROR(SUMIF('Реестр уборки 2026'!Z:Z,J17,'Реестр уборки 2026'!G:G)/1000, ) -> 224.44 | L17: =IFERROR(AVERAGEIF('Реестр уборки 2026'!Z:Z,'Данные 2026'!J17,'Реестр уборки 2026'!C:C),) -> 61.619048 | M17: нет данных
A18: Исполнение плана, % | B18: =B16/B15 -> 0.87790222 | D18: 2022 | F18: 3 | G18: 6505 | I18: 15 | J18: =J17+1 -> 46190 | K18: =IFERROR(SUMIF('Реестр уборки 2026'!Z:Z,J18,'Реестр уборки 2026'!G:G)/1000, ) -> 260.14 | L18: =IFERROR(AVERAGEIF('Реестр уборки 2026'!Z:Z,'Данные 2026'!J18,'Реестр уборки 2026'!C:C),) -> 56.391304 | M18: нет данных
A19: Убрали на зерно | D19: 2023 | F19: 5.6 | G19: 6656 | I19: 16 | J19: =J18+1 -> 46191 | K19: =IFERROR(SUMIF('Реестр уборки 2026'!Z:Z,J19,'Реестр уборки 2026'!G:G)/1000, ) -> 276.54 | L19: =IFERROR(AVERAGEIF('Реестр уборки 2026'!Z:Z,'Данные 2026'!J19,'Реестр уборки 2026'!C:C),) -> 52.84 | M19: нет данных
A20: ОСТАВИЛИ | D20: 2024 | F20: 2.7 | G20: 4371.9 | I20: 17 | J20: =J19+1 -> 46192 | K20: =IFERROR(SUMIF('Реестр уборки 2026'!Z:Z,J20,'Реестр уборки 2026'!G:G)/1000, ) -> 48.93 | L20: =IFERROR(AVERAGEIF('Реестр уборки 2026'!Z:Z,'Данные 2026'!J20,'Реестр уборки 2026'!C:C),) -> 47.333333 | M20: нет данных
A21: 3.1 | D21: 2025 | F21: 4.7835642 | G21: 7098.14 | I21: 18 | J21: =J20+1 -> 46193 | K21: =IFERROR(SUMIF('Реестр уборки 2026'!Z:Z,J21,'Реестр уборки 2026'!G:G)/1000, ) -> 53.81 | L21: =IFERROR(AVERAGEIF('Реестр уборки 2026'!Z:Z,'Данные 2026'!J21,'Реестр уборки 2026'!C:C),) -> 51.428571 | M21: нет данных
A22: Урожайность физ. вес. | D22: 2026 | F22: =B24 -> 4.9184196 | G22: =F12 -> 8234.91 | I22: 19 | J22: =J21+1 -> 46194 | K22: =IFERROR(SUMIF('Реестр уборки 2026'!Z:Z,J22,'Реестр уборки 2026'!G:G)/1000, ) -> 305.45 | L22: =IFERROR(AVERAGEIF('Реестр уборки 2026'!Z:Z,'Данные 2026'!J22,'Реестр уборки 2026'!C:C),) -> 55.933333 | M22: нет данных
A23: ПЛАН, т/га | B23: =IFERROR(B4/B15, ) -> 5 | I23: 20 | J23: =J22+1 -> 46195 | K23: =IFERROR(SUMIF('Реестр уборки 2026'!Z:Z,J23,'Реестр уборки 2026'!G:G)/1000, ) -> 278.12 | L23: =IFERROR(AVERAGEIF('Реестр уборки 2026'!Z:Z,'Данные 2026'!J23,'Реестр уборки 2026'!C:C),) -> 58.8 | M23: нет данных
A24: ФАКТ, т/га | B24: =IFERROR(B5/B16, ) -> 4.9184196 | I24: 21 | J24: =J23+1 -> 46196 | K24: =IFERROR(SUMIF('Реестр уборки 2026'!Z:Z,J24,'Реестр уборки 2026'!G:G)/1000, ) -> 283.39 | L24: =IFERROR(AVERAGEIF('Реестр уборки 2026'!Z:Z,'Данные 2026'!J24,'Реестр уборки 2026'!C:C),) -> 59.230769 | M24: нет данных
D25: 7 | I25: 22 | J25: =J24+1 -> 46197 | K25: =IFERROR(SUMIF('Реестр уборки 2026'!Z:Z,J25,'Реестр уборки 2026'!G:G)/1000, ) -> 228.04 | L25: =IFERROR(AVERAGEIF('Реестр уборки 2026'!Z:Z,'Данные 2026'!J25,'Реестр уборки 2026'!C:C),) -> 61.217391 | M25: нет данных
A26: 3.2 | D26: Распределение сырья по финометру | F26: Вес, т | G26: Доля, % | I26: 23 | J26: =J25+1 -> 46198 | K26: =IFERROR(SUMIF('Реестр уборки 2026'!Z:Z,J26,'Реестр уборки 2026'!G:G)/1000, ) -> 399.44 | L26: =IFERROR(AVERAGEIF('Реестр уборки 2026'!Z:Z,'Данные 2026'!J26,'Реестр уборки 2026'!C:C),) -> 59.529412 | M26: нет данных
A27: Урожайность зач. вес. | C27: до 40 | D27: до 40 | F27: =SUMIF('Реестр уборки 2026'!AC:AC,Таблица111[[#This Row],[Распределение сырья по финометру]],'Реестр уборки 2026'!G:G)/1000 -> 0 | G27: =IFERROR(F27/$F$33, ) -> 0 | I27: 24 | J27: =J26+1 -> 46199 | K27: =IFERROR(SUMIF('Реестр уборки 2026'!Z:Z,J27,'Реестр уборки 2026'!G:G)/1000, ) -> 245.87 | L27: =IFERROR(AVERAGEIF('Реестр уборки 2026'!Z:Z,'Данные 2026'!J27,'Реестр уборки 2026'!C:C),) -> 64.681818 | M27: нет данных
A28: ПЛАН, т/га | B28: =IFERROR(B10/B15, 0) -> 0 | C28: 40-62 | D28: 40-52 | F28: =SUMIF('Реестр уборки 2026'!AC:AC,Таблица111[[#This Row],[Распределение сырья по финометру]],'Реестр уборки 2026'!G:G)/1000 -> 1549.04 | G28: =IFERROR(F28/$F$33, ) -> 0.18810649 | I28: 25 | J28: =J27+1 -> 46200 | K28: =IFERROR(SUMIF('Реестр уборки 2026'!Z:Z,J28,'Реестр уборки 2026'!G:G)/1000, ) -> 277.62 | L28: =IFERROR(AVERAGEIF('Реестр уборки 2026'!Z:Z,'Данные 2026'!J28,'Реестр уборки 2026'!C:C),) -> 63.263158 | M28: нет данных
A29: ФАКТ, т/га | B29: =IFERROR(B11/B16, 0) -> 0 | C29: 63-66 | D29: 53-63 | F29: =SUMIF('Реестр уборки 2026'!AC:AC,Таблица111[[#This Row],[Распределение сырья по финометру]],'Реестр уборки 2026'!G:G)/1000 -> 4786.51 | G29: =IFERROR(F29/$F$33, ) -> 0.58124618 | I29: 26 | J29: =J28+1 -> 46201 | K29: =IFERROR(SUMIF('Реестр уборки 2026'!Z:Z,J29,'Реестр уборки 2026'!G:G)/1000, ) -> 344.28 | L29: =IFERROR(AVERAGEIF('Реестр уборки 2026'!Z:Z,'Данные 2026'!J29,'Реестр уборки 2026'!C:C),) -> 59.72 | M29: нет данных
C30: 67-85 | D30: 64-66 | F30: =SUMIF('Реестр уборки 2026'!AC:AC,Таблица111[[#This Row],[Распределение сырья по финометру]],'Реестр уборки 2026'!G:G)/1000 -> 1097.02 | G30: =IFERROR(F30/$F$33, ) -> 0.13321578 | I30: 27 | J30: =J29+1 -> 46202 | K30: =IFERROR(SUMIF('Реестр уборки 2026'!Z:Z,J30,'Реестр уборки 2026'!G:G)/1000, ) -> 262.1 | L30: =IFERROR(AVERAGEIF('Реестр уборки 2026'!Z:Z,'Данные 2026'!J30,'Реестр уборки 2026'!C:C),) -> 56.25 | M30: нет данных
D31: 67-85 | F31: =SUMIF('Реестр уборки 2026'!AC:AC,Таблица111[[#This Row],[Распределение сырья по финометру]],'Реестр уборки 2026'!G:G)/1000 -> 802.34 | G31: =IFERROR(F31/$F$33, ) -> 0.097431544 | I31: 28 | J31: =J30+1 -> 46203 | K31: =IFERROR(SUMIF('Реестр уборки 2026'!Z:Z,J31,'Реестр уборки 2026'!G:G)/1000, ) -> 185.66 | L31: =IFERROR(AVERAGEIF('Реестр уборки 2026'!Z:Z,'Данные 2026'!J31,'Реестр уборки 2026'!C:C),) -> 55.157895 | M31: нет данных
A32: 4 | D32: нет данных | F32: =SUMIF('Реестр уборки 2026'!AC:AC,Таблица111[[#This Row],[Распределение сырья по финометру]],'Реестр уборки 2026'!G:G)/1000 -> 0 | G32: =IFERROR(F32/$F$33, ) -> 0 | I32: 29 | J32: =J31+1 -> 46204 | K32: =IFERROR(SUMIF('Реестр уборки 2026'!Z:Z,J32,'Реестр уборки 2026'!G:G)/1000, ) -> 254.57 | L32: =IFERROR(AVERAGEIF('Реестр уборки 2026'!Z:Z,'Данные 2026'!J32,'Реестр уборки 2026'!C:C),) -> 54.619048 | M32: нет данных
A33: Информация по сырью | F33: =SUM(F27:F32) -> 8234.91 | G33: =SUM(G27:G32) -> 1 | I33: 30 | J33: =J32+1 -> 46205 | K33: =IFERROR(SUMIF('Реестр уборки 2026'!Z:Z,J33,'Реестр уборки 2026'!G:G)/1000, ) -> 283.03 | L33: =IFERROR(AVERAGEIF('Реестр уборки 2026'!Z:Z,'Данные 2026'!J33,'Реестр уборки 2026'!C:C),) -> 54.043478 | M33: нет данных
A34: Переработка | B34: =B37-B35-B36 -> 7424.59 | I34: 31 | J34: =J33+1 -> 46206 | K34: =IFERROR(SUMIF('Реестр уборки 2026'!Z:Z,J34,'Реестр уборки 2026'!G:G)/1000, ) -> 221.76 | L34: =IFERROR(AVERAGEIF('Реестр уборки 2026'!Z:Z,'Данные 2026'!J34,'Реестр уборки 2026'!C:C),) -> 59.052632 | M34: нет данных
A35: Утилизация | B35: 0 | I35: 32 | J35: =J34+1 -> 46207 | K35: =IFERROR(SUMIF('Реестр уборки 2026'!Z:Z,J35,'Реестр уборки 2026'!G:G)/1000, ) -> 255.78 | L35: =IFERROR(AVERAGEIF('Реестр уборки 2026'!Z:Z,'Данные 2026'!J35,'Реестр уборки 2026'!C:C),) -> 60.5 | M35: нет данных
A36: Реализация | B36: =810320/1000 -> 810.32 | C36: 0 | D36: - реализовано по документам отгрузки (зач вес) | I36: 33 | J36: =J35+1 -> 46208 | K36: =IFERROR(SUMIF('Реестр уборки 2026'!Z:Z,J36,'Реестр уборки 2026'!G:G)/1000, ) -> 241.54 | L36: =IFERROR(AVERAGEIF('Реестр уборки 2026'!Z:Z,'Данные 2026'!J36,'Реестр уборки 2026'!C:C),) -> 60.75 | M36: нет данных
A37: Собственное сырье | B37: =F12 -> 8234.91 | I37: 34 | J37: =J36+1 -> 46209 | K37: =IFERROR(SUMIF('Реестр уборки 2026'!Z:Z,J37,'Реестр уборки 2026'!G:G)/1000, ) -> 215.29 | L37: =IFERROR(AVERAGEIF('Реестр уборки 2026'!Z:Z,'Данные 2026'!J37,'Реестр уборки 2026'!C:C),) -> 67.470588 | M37: нет данных
A38: Закупка | B38: 0 | I38: 35 | J38: =J37+1 -> 46210 | M38: нет данных
I39: 36 | J39: =J38+1 -> 46211 | M39: нет данных
I40: 37 | J40: =J39+1 -> 46212 | M40: нет данных
I41: 38 | J41: =J40+1 -> 46213 | M41: нет данных
I42: 39 | J42: =J41+1 -> 46214 | M42: нет данных
I43: 40 | J43: =J42+1 -> 46215 | M43: нет данных
I44: 41 | J44: =J43+1 -> 46216 | M44: нет данных
I45: 42 | J45: =J44+1 -> 46217 | M45: нет данных
I46: 43 | J46: =J45+1 -> 46218 | M46: нет данных
I47: 44 | J47: =J46+1 -> 46219 | M47: нет данных
I48: 45 | J48: =J47+1 -> 46220 | M48: нет данных
K49: =SUM(K4:K48) -> 8234.91
A54: Культура | B54: Орошение | C54: ПЛАН, т | D54: ФАКТ, т | E54: Исполнение плана по валу, % | F54: ПЛАН, га | G54: ФАКТ, га | H54: Исполнение плана по площади, % | I54: Урожайность, т/га
A55: ГРК (богара) | B55: богара | C55: =Таблица413[[#This Row],[ПЛАН, га]]*5 -> 3890 | D55: =SUMIF('Реестр уборки 2026'!W:W,Таблица413[[#This Row],[Культура]],'Реестр уборки 2026'!G:G)/1000 -> 3918.2 | E55: =IFERROR(D55/C55, ) -> 1.0072494 | F55: 778 | G55: =SUMIF('Реестр уборки 2026'!W:W,Таблица413[[#This Row],[Культура]],'Реестр уборки 2026'!V:V) -> 672 | H55: =IFERROR(G55/F55, ) -> 0.86375321 | I55: =IFERROR(Таблица413[[#This Row],[ФАКТ, т]]/Таблица413[[#This Row],[ФАКТ, га]],) -> 5.8306548
A56: ГРК (полив) | B56: полив | C56: 2100 | D56: =SUMIF('Реестр уборки 2026'!W:W,Таблица413[[#This Row],[Культура]],'Реестр уборки 2026'!G:G)/1000 -> 1284.55 | E56: =IFERROR(D56/C56, ) -> 0.61169048 | F56: 420 | G56: =SUMIF('Реестр уборки 2026'!W:W,Таблица413[[#This Row],[Культура]],'Реестр уборки 2026'!V:V) -> 360 | H56: =IFERROR(G56/F56, ) -> 0.85714286 | I56: =IFERROR(Таблица413[[#This Row],[ФАКТ, т]]/Таблица413[[#This Row],[ФАКТ, га]],) -> 3.5681944
A57: Агролидер (полив) | B57: полив | C57: 1345 | D57: =SUMIF('Реестр уборки 2026'!W:W,Таблица413[[#This Row],[Культура]],'Реестр уборки 2026'!G:G)/1000 -> 1397.32 | E57: =IFERROR(D57/C57, ) -> 1.0388996 | F57: 269 | G57: =SUMIF('Реестр уборки 2026'!W:W,Таблица413[[#This Row],[Культура]],'Реестр уборки 2026'!V:V) -> 269.1 | H57: =IFERROR(G57/F57, ) -> 1.0003717 | I57: =IFERROR(Таблица413[[#This Row],[ФАКТ, т]]/Таблица413[[#This Row],[ФАКТ, га]],) -> 5.1925678
A58: Колос (полив) | B58: полив | C58: 2200.8 | D58: =SUMIF('Реестр уборки 2026'!W:W,Таблица413[[#This Row],[Культура]],'Реестр уборки 2026'!G:G)/1000 -> 1634.84 | E58: =IFERROR(D58/C58, ) -> 0.74283897 | F58: 440.16 | G58: =SUMIF('Реестр уборки 2026'!W:W,Таблица413[[#This Row],[Культура]],'Реестр уборки 2026'!V:V) -> 373.2 | H58: =IFERROR(G58/F58, ) -> 0.8478735 | I58: =IFERROR(Таблица413[[#This Row],[ФАКТ, т]]/Таблица413[[#This Row],[ФАКТ, га]],) -> 4.3806002
C59: =SUBTOTAL(109,C55:C58) -> 9535.8 | D59: =SUBTOTAL(109,D55:D58) -> 8234.91 | E59: =D59/C59 -> 0.8635783 | F59: =SUBTOTAL(109,F55:F58) -> 1907.16 | G59: =SUBTOTAL(109,G55:G58) -> 1674.3 | H59: =IFERROR(G59/F59, ) -> 0.87790222 | I59: =D59/G59 -> 4.9184196
A63: Названия строк | B63: ПЛАН, т | C63: ФАКТ, т | D63: Исполнение плана по валу, % | E63: ПЛАН, га | F63: ФАКТ, га
A64: Агролидер (полив) | B64: 1345 | C64: 1384.14 | D64: 1.0291004 | E64: 269 | F64: 269.00406
A65: ГРК (богара) | B65: 3890 | C65: 3765.1 | D65: 0.96789203 | E65: 778 | F65: 637.9
A66: ГРК (полив) | B66: 2100 | C66: 719.04 | D66: 0.3424 | E66: 420 | F66: 167
A67: Колос (полив) | B67: 2200.8 | C67: 886.23 | D67: 0.40268539 | E67: 440.16 | F67: 188.12
A68: Общий итог | B68: 9535.8 | C68: 6754.51 | D68: 0.70833176 | E68: 1907.16 | F68: 1262.0241

Sheet ОТЧЕТ 2025
B2: ОПЕРАТИВНАЯ ИНФОРМАЦИЯ ПО СБОРУ ГОРОШКА (СЕЗОН 2025 г.)
B24: МАЙ
B25: Пн | C25: Вт | D25: Ср | E25: Чт | F25: Пт | G25: Сб | H25: Вс
C26: 45804 | D26: =C26+1 -> 45805 | E26: =D26+1 -> 45806 | F26: =E26+1 -> 45807 | G26: =F26+1 -> 45808
B27: ИЮНЬ
H28: =G26+1 -> 45809
B29: =H28+1 -> 45810 | C29: =B29+1 -> 45811 | D29: =C29+1 -> 45812 | E29: =D29+1 -> 45813 | F29: =E29+1 -> 45814 | G29: =F29+1 -> 45815 | H29: =G29+1 -> 45816
B30: =H29+1 -> 45817 | C30: =B30+1 -> 45818 | D30: =C30+1 -> 45819 | E30: =D30+1 -> 45820 | F30: =E30+1 -> 45821 | G30: =F30+1 -> 45822 | H30: =G30+1 -> 45823
B31: =H30+1 -> 45824 | C31: =B31+1 -> 45825 | D31: =C31+1 -> 45826 | E31: =D31+1 -> 45827 | F31: =E31+1 -> 45828 | G31: =F31+1 -> 45829 | H31: =G31+1 -> 45830
B32: =H31+1 -> 45831 | C32: =B32+1 -> 45832 | D32: =C32+1 -> 45833 | E32: =D32+1 -> 45834 | F32: =E32+1 -> 45835 | G32: =F32+1 -> 45836 | H32: =G32+1 -> 45837
B33: =H32+1 -> 45838
B34: ИЮЛЬ
C35: =B33+1 -> 45839 | D35: =C35+1 -> 45840 | E35: =D35+1 -> 45841 | F35: =E35+1 -> 45842 | G35: =F35+1 -> 45843 | H35: =G35+1 -> 45844
B36: =H35+1 -> 45845 | C36: =B36+1 -> 45846 | D36: =C36+1 -> 45847 | E36: =D36+1 -> 45848 | F36: =E36+1 -> 45849 | G36: =F36+1 -> 45850 | H36: =G36+1 -> 45851
B38: День уборки - | E38: 45

Sheet ОТЧЕТ 2024
B2: ОПЕРАТИВНАЯ ИНФОРМАЦИЯ ПО СБОРУ ГОРОШКА (СЕЗОН 2024 г.)
B21: МАЙ
B22: Пн | C22: Вт | D22: Ср | E22: Чт | F22: Пт | G22: Сб | H22: Вс
F23: 45429 | G23: 45430 | H23: 45431
B24: =H23+1 -> 45432 | C24: =B24+1 -> 45433 | D24: =C24+1 -> 45434 | E24: =D24+1 -> 45435 | F24: =E24+1 -> 45436 | G24: =F24+1 -> 45437 | H24: =G24+1 -> 45438
B25: =H24+1 -> 45439 | C25: =B25+1 -> 45440 | D25: =C25+1 -> 45441 | E25: =D25+1 -> 45442 | F25: =E25+1 -> 45443
B26: ИЮНЬ
G27: 45444 | H27: =G27+1 -> 45445
B28: =H27+1 -> 45446 | C28: =B28+1 -> 45447 | D28: =C28+1 -> 45448 | E28: =D28+1 -> 45449 | F28: =E28+1 -> 45450 | G28: =F28+1 -> 45451 | H28: =G28+1 -> 45452
B29: =H28+1 -> 45453 | C29: =B29+1 -> 45454 | D29: =C29+1 -> 45455 | E29: =D29+1 -> 45456 | F29: =E29+1 -> 45457 | G29: =F29+1 -> 45458 | H29: =G29+1 -> 45459
B30: =H29+1 -> 45460 | C30: =B30+1 -> 45461 | D30: =C30+1 -> 45462 | E30: =D30+1 -> 45463 | F30: =E30+1 -> 45464 | G30: =F30+1 -> 45465 | H30: =G30+1 -> 45466
B31: =H30+1 -> 45467 | C31: =B31+1 -> 45468 | D31: =C31+1 -> 45469 | E31: =D31+1 -> 45470 | F31: =E31+1 -> 45471 | G31: =F31+1 -> 45472 | H31: =G31+1 -> 45473
B32: ИЮЛЬ
B33: =H31+1 -> 45474 | C33: =B33+1 -> 45475 | D33: =C33+1 -> 45476 | E33: =D33+1 -> 45477 | F33: =E33+1 -> 45478 | G33: =F33+1 -> 45479 | H33: =G33+1 -> 45480
B34: =H33+1 -> 45481 | C34: =B34+1 -> 45482 | D34: =C34+1 -> 45483 | E34: =D34+1 -> 45484 | F34: =E34+1 -> 45485 | G34: =F34+1 -> 45486 | H34: =G34+1 -> 45487
B35: =H34+1 -> 45488 | C35: =B35+1 -> 45489 | D35: =C35+1 -> 45490 | E35: =D35+1 -> 45491 | F35: =E35+1 -> 45492 | G35: =F35+1 -> 45493 | H35: =G35+1 -> 45494
B36: =H35+1 -> 45495 | C36: =B36+1 -> 45496 | D36: =C36+1 -> 45497 | E36: =D36+1 -> 45498 | F36: =E36+1 -> 45499 | G36: =F36+1 -> 45500 | H36: =G36+1 -> 45501
B37: =H36+1 -> 45502 | C37: =B37+1 -> 45503 | D37: =C37+1 -> 45504

Sheet Данные 2025
A2: 1.1 | B2: Выборка по КА, орошению | D2: 5 | I2: 8
A3: Валовый сбор | D3: Выполнение плана по сбору | E3: ПЛАН, т | F3: ФАКТ, т | G3: Исполнение плана, % | I3: Ежедневные показатели | K3: Сбор, т | L3: Значение спелости | M3: Финометр
A4: ПЛАН, т | B4: =C63 -> 6798.045 | D4: Учхоз Кубань (богара) | E4: 1157.4 | F4: =D55 -> 1320.13 | G4: =IFERROR(F4/E4, ) -> 1.1405996 | I4: 1 | J4: 45804 | K4: =SUMIF('Реестр уборки 2025'!Z:Z,J4,'Реестр уборки 2025'!G:G)/1000 -> 71.35 | L4: =IFERROR(AVERAGEIF('Реестр уборки 2025'!Z:Z,'Данные 2025'!J4,'Реестр уборки 2025'!C:C),) -> 41.333333 | M4: 40-52
A5: ФАКТ, т | B5: =D63 -> 7098.14 | D5: ГРК собственные семена (богара) | E5: 910 | F5: =D56 -> 503.65 | G5: =IFERROR(F5/E5, ) -> 0.55346154 | I5: 2 | J5: 45805 | K5: =SUMIF('Реестр уборки 2025'!Z:Z,J5,'Реестр уборки 2025'!G:G)/1000 -> 98.78 | L5: =IFERROR(AVERAGEIF('Реестр уборки 2025'!Z:Z,'Данные 2025'!J5,'Реестр уборки 2025'!C:C),) -> 44 | M5: 40-52
A6: Исполнение плана, % | B6: =E63 -> 1.0441443 | D6: ГРК демо (богара) | E6: 136.5 | F6: =D57 -> 91.8 | G6: =IFERROR(F6/E6, ) -> 0.67252747 | I6: 3 | J6: 45806 | K6: =SUMIF('Реестр уборки 2025'!Z:Z,J6,'Реестр уборки 2025'!G:G)/1000 -> 10.74 | L6: =IFERROR(AVERAGEIF('Реестр уборки 2025'!Z:Z,'Данные 2025'!J6,'Реестр уборки 2025'!C:C),) -> 42.5 | M6: 40-52
D7: ГРК (богара) | E7: 936.2 | F7: =D58 -> 769.25 | G7: =IFERROR(F7/E7, ) -> 0.82167272 | I7: 4 | J7: 45807
A8: 1.2 | D8: Братковский (полив) | E8: 765 | F8: =D59 -> 842.08 | G8: =IFERROR(F8/E8, ) -> 1.1007582 | I8: 5 | J8: 45808 | K8: =SUMIF('Реестр уборки 2025'!Z:Z,J8,'Реестр уборки 2025'!G:G)/1000 -> 55.61 | L8: =IFERROR(AVERAGEIF('Реестр уборки 2025'!Z:Z,'Данные 2025'!J8,'Реестр уборки 2025'!C:C),) -> 45.625 | M8: 40-52
A9: Зачетный вес | D9: Братковский закупка (полив) | E9: 522.325 | F9: =D60 -> 561.3 | G9: =IFERROR(F9/E9, ) -> 1.0746183 | I9: 6 | J9: 45809 | K9: =SUMIF('Реестр уборки 2025'!Z:Z,J9,'Реестр уборки 2025'!G:G)/1000 -> 206.19 | L9: =IFERROR(AVERAGEIF('Реестр уборки 2025'!Z:Z,'Данные 2025'!J9,'Реестр уборки 2025'!C:C),) -> 51.588235 | M9: 40-52
A10: ПЛАН, т | D10: Агролидер (полив) | E10: 586.5 | F10: =D61 -> 1017.73 | G10: =IFERROR(F10/E10, ) -> 1.73526 | I10: 7 | J10: 45810 | K10: =SUMIF('Реестр уборки 2025'!Z:Z,J10,'Реестр уборки 2025'!G:G)/1000 -> 198.3 | L10: =IFERROR(AVERAGEIF('Реестр уборки 2025'!Z:Z,'Данные 2025'!J10,'Реестр уборки 2025'!C:C),) -> 52.9375 | M10: 53-63
A11: ФАКТ, т | D11: Колос (полив) | E11: 1784.12 | F11: =D62 -> 1992.2 | G11: =IFERROR(F11/E11, ) -> 1.1166289 | I11: 8 | J11: 45811 | K11: =SUMIF('Реестр уборки 2025'!Z:Z,J11,'Реестр уборки 2025'!G:G)/1000 -> 285.91 | L11: =IFERROR(AVERAGEIF('Реестр уборки 2025'!Z:Z,'Данные 2025'!J11,'Реестр уборки 2025'!C:C),) -> 54.666667 | M11: 53-63
E12: =SUM(E4:E11) -> 6798.045 | F12: =SUM(F4:F11) -> 7098.14 | G12: =IFERROR(F12/E12, ) -> 1.0441443 | I12: 9 | J12: 45812 | K12: =SUMIF('Реестр уборки 2025'!Z:Z,J12,'Реестр уборки 2025'!G:G)/1000 -> 339.79 | L12: =IFERROR(AVERAGEIF('Реестр уборки 2025'!Z:Z,'Данные 2025'!J12,'Реестр уборки 2025'!C:C),) -> 57.666667 | M12: 53-63
A13: 2 | D13: 6 | I13: 10 | J13: 45813 | K13: =SUMIF('Реестр уборки 2025'!Z:Z,J13,'Реестр уборки 2025'!G:G)/1000 -> 240.45 | L13: =IFERROR(AVERAGEIF('Реестр уборки 2025'!Z:Z,'Данные 2025'!J13,'Реестр уборки 2025'!C:C),) -> 53.473684 | M13: 53-63
A14: Площадь уборки | D14: Выполнение плана по сбору | F14: Урожайность, т/га | G14: Вал, т | I14: 11 | J14: 45814 | K14: =SUMIF('Реестр уборки 2025'!Z:Z,J14,'Реестр уборки 2025'!G:G)/1000 -> 417.43 | L14: =IFERROR(AVERAGEIF('Реестр уборки 2025'!Z:Z,'Данные 2025'!J14,'Реестр уборки 2025'!C:C),) -> 57.228571 | M14: 53-63
A15: ПЛАН, га | B15: =F63 -> 1675.8 | D15: 2019 | F15: 3.3 | G15: 6813 | I15: 12 | J15: 45815 | K15: =SUMIF('Реестр уборки 2025'!Z:Z,J15,'Реестр уборки 2025'!G:G)/1000 -> 163.35 | L15: =IFERROR(AVERAGEIF('Реестр уборки 2025'!Z:Z,'Данные 2025'!J15,'Реестр уборки 2025'!C:C),) -> 60.933333 | M15: 53-63
A16: ФАКТ, га | B16: =G63 -> 1483.8601 | D16: 2020 | F16: 4.6 | G16: 12761 | I16: 13 | J16: 45816 | K16: =SUMIF('Реестр уборки 2025'!Z:Z,J16,'Реестр уборки 2025'!G:G)/1000 -> 233.26 | L16: =IFERROR(AVERAGEIF('Реестр уборки 2025'!Z:Z,'Данные 2025'!J16,'Реестр уборки 2025'!C:C),) -> 60.869565 | M16: 53-63
A17: Остаток, га | B17: =B15-B16 -> 191.93991 | D17: 2021 | F17: 4.2 | G17: 10161 | I17: 14 | J17: 45817 | K17: =SUMIF('Реестр уборки 2025'!Z:Z,J17,'Реестр уборки 2025'!G:G)/1000 -> 100.73 | L17: =IFERROR(AVERAGEIF('Реестр уборки 2025'!Z:Z,'Данные 2025'!J17,'Реестр уборки 2025'!C:C),) -> 68.1 | M17: 67-85
A18: Исполнение плана, % | B18: =B16/B15 -> 0.88546371 | D18: 2022 | F18: 3 | G18: 6505 | I18: 15 | J18: 45818 | K18: =SUMIF('Реестр уборки 2025'!Z:Z,J18,'Реестр уборки 2025'!G:G)/1000 -> 243.58 | L18: =IFERROR(AVERAGEIF('Реестр уборки 2025'!Z:Z,'Данные 2025'!J18,'Реестр уборки 2025'!C:C),) -> 62.541667 | M18: 53-63
A19: Убрали на зерно | B19: 71 | D19: 2023 | F19: 5.6 | G19: 6656 | I19: 16 | J19: 45819 | K19: =SUMIF('Реестр уборки 2025'!Z:Z,J19,'Реестр уборки 2025'!G:G)/1000 -> 127.99 | L19: =IFERROR(AVERAGEIF('Реестр уборки 2025'!Z:Z,'Данные 2025'!J19,'Реестр уборки 2025'!C:C),) -> 65.090909 | M19: 64-66
A20: ОСТАВИЛИ | B20: 120.96957 | D20: 2024 | F20: 2.7 | G20: 4371.9 | I20: 17 | J20: 45820 | K20: =SUMIF('Реестр уборки 2025'!Z:Z,J20,'Реестр уборки 2025'!G:G)/1000 -> 302.41 | L20: =IFERROR(AVERAGEIF('Реестр уборки 2025'!Z:Z,'Данные 2025'!J20,'Реестр уборки 2025'!C:C),) -> 54.217391 | M20: 53-63
A21: 3.1 | D21: 2025 | F21: =B24 -> 4.7835642 | G21: =F12 -> 7098.14 | I21: 18 | J21: 45821 | K21: =SUMIF('Реестр уборки 2025'!Z:Z,J21,'Реестр уборки 2025'!G:G)/1000 -> 251.82 | L21: =IFERROR(AVERAGEIF('Реестр уборки 2025'!Z:Z,'Данные 2025'!J21,'Реестр уборки 2025'!C:C),) -> 53.583333 | M21: 53-63
A22: Урожайность физ. вес. | I22: 19 | J22: 45822 | K22: =SUMIF('Реестр уборки 2025'!Z:Z,J22,'Реестр уборки 2025'!G:G)/1000 -> 260.19 | L22: =IFERROR(AVERAGEIF('Реестр уборки 2025'!Z:Z,'Данные 2025'!J22,'Реестр уборки 2025'!C:C),) -> 63.15 | M22: 53-63
A23: ПЛАН, т/га | B23: =IFERROR(B4/B15, ) -> 4.0565968 | I23: 20 | J23: 45823 | K23: =SUMIF('Реестр уборки 2025'!Z:Z,J23,'Реестр уборки 2025'!G:G)/1000 -> 251.63 | L23: =IFERROR(AVERAGEIF('Реестр уборки 2025'!Z:Z,'Данные 2025'!J23,'Реестр уборки 2025'!C:C),) -> 67.095238 | M23: 67-85
A24: ФАКТ, т/га | B24: =IFERROR(B5/B16, ) -> 4.7835642 | I24: 21 | J24: 45824 | K24: =SUMIF('Реестр уборки 2025'!Z:Z,J24,'Реестр уборки 2025'!G:G)/1000 -> 182.08 | L24: =IFERROR(AVERAGEIF('Реестр уборки 2025'!Z:Z,'Данные 2025'!J24,'Реестр уборки 2025'!C:C),) -> 61.375 | M24: 53-63
D25: 7 | I25: 22 | J25: 45825 | K25: =SUMIF('Реестр уборки 2025'!Z:Z,J25,'Реестр уборки 2025'!G:G)/1000 -> 231.15 | L25: =IFERROR(AVERAGEIF('Реестр уборки 2025'!Z:Z,'Данные 2025'!J25,'Реестр уборки 2025'!C:C),) -> 58.117647 | M25: 53-63
A26: 3.2 | D26: Распределение сырья по финометру | F26: Вес, т | G26: Доля, % | I26: 23 | J26: 45826 | K26: =SUMIF('Реестр уборки 2025'!Z:Z,J26,'Реестр уборки 2025'!G:G)/1000 -> 157.45 | L26: =IFERROR(AVERAGEIF('Реестр уборки 2025'!Z:Z,'Данные 2025'!J26,'Реестр уборки 2025'!C:C),) -> 55.5 | M26: 53-63
A27: Урожайность зач. вес. | C27: до 40 | D27: до 40 | F27: =SUMIF('Реестр уборки 2025'!AC:AC,Таблица1[[#This Row],[Распределение сырья по финометру]],'Реестр уборки 2025'!G:G)/1000 -> 15.6 | G27: =IFERROR(F27/$F$33, ) -> 0.0021977588 | I27: 24 | J27: 45827 | K27: =SUMIF('Реестр уборки 2025'!Z:Z,J27,'Реестр уборки 2025'!G:G)/1000 -> 304.92 | L27: =IFERROR(AVERAGEIF('Реестр уборки 2025'!Z:Z,'Данные 2025'!J27,'Реестр уборки 2025'!C:C),) -> 62.826087 | M27: 53-63
A28: ПЛАН, т/га | B28: =IFERROR(B10/B15, 0) -> 0 | C28: 40-62 | D28: 40-52 | F28: =SUMIF('Реестр уборки 2025'!AC:AC,Таблица1[[#This Row],[Распределение сырья по финометру]],'Реестр уборки 2025'!G:G)/1000 -> 1875.175 | G28: =IFERROR(F28/$F$33, ) -> 0.26417836 | I28: 25 | J28: 45828 | K28: =SUMIF('Реестр уборки 2025'!Z:Z,J28,'Реестр уборки 2025'!G:G)/1000 -> 252.94 | L28: =IFERROR(AVERAGEIF('Реестр уборки 2025'!Z:Z,'Данные 2025'!J28,'Реестр уборки 2025'!C:C),) -> 64.526316 | M28: 64-66
A29: ФАКТ, т/га | B29: =IFERROR(B11/B16, 0) -> 0 | C29: 63-66 | D29: 53-63 | F29: =SUMIF('Реестр уборки 2025'!AC:AC,Таблица1[[#This Row],[Распределение сырья по финометру]],'Реестр уборки 2025'!G:G)/1000 -> 3153.785 | G29: =IFERROR(F29/$F$33, ) -> 0.44431147 | I29: 26 | J29: 45829 | K29: =SUMIF('Реестр уборки 2025'!Z:Z,J29,'Реестр уборки 2025'!G:G)/1000 -> 123.3 | L29: =IFERROR(AVERAGEIF('Реестр уборки 2025'!Z:Z,'Данные 2025'!J29,'Реестр уборки 2025'!C:C),) -> 60 | M29: 53-63
C30: 67-85 | D30: 64-66 | F30: =SUMIF('Реестр уборки 2025'!AC:AC,Таблица1[[#This Row],[Распределение сырья по финометру]],'Реестр уборки 2025'!G:G)/1000 -> 570.75 | G30: =IFERROR(F30/$F$33, ) -> 0.080408389 | I30: 27 | J30: 45830 | K30: =SUMIF('Реестр уборки 2025'!Z:Z,J30,'Реестр уборки 2025'!G:G)/1000 -> 272.42 | L30: =IFERROR(AVERAGEIF('Реестр уборки 2025'!Z:Z,'Данные 2025'!J30,'Реестр уборки 2025'!C:C),) -> 49.4 | M30: 40-52
D31: 67-85 | F31: =SUMIF('Реестр уборки 2025'!AC:AC,Таблица1[[#This Row],[Распределение сырья по финометру]],'Реестр уборки 2025'!G:G)/1000 -> 1443.44 | G31: =IFERROR(F31/$F$33, ) -> 0.20335468 | I31: 28 | J31: 45831 | K31: =SUMIF('Реестр уборки 2025'!Z:Z,J31,'Реестр уборки 2025'!G:G)/1000 -> 109.28 | L31: =IFERROR(AVERAGEIF('Реестр уборки 2025'!Z:Z,'Данные 2025'!J31,'Реестр уборки 2025'!C:C),) -> 52.875 | M31: 53-63
A32: 4 | D32: нет данных | F32: =SUMIF('Реестр уборки 2025'!AC:AC,Таблица1[[#This Row],[Распределение сырья по финометру]],'Реестр уборки 2025'!G:G)/1000 -> 39.39 | G32: =IFERROR(F32/$F$33, ) -> 0.0055493411 | I32: 29 | J32: 45832 | K32: =SUMIF('Реестр уборки 2025'!Z:Z,J32,'Реестр уборки 2025'!G:G)/1000 -> 200.28 | L32: =IFERROR(AVERAGEIF('Реестр уборки 2025'!Z:Z,'Данные 2025'!J32,'Реестр уборки 2025'!C:C),) -> 49.375 | M32: 40-52
A33: Информация по сырью | F33: =SUM(F27:F32) -> 7098.14 | G33: =SUM(G27:G32) -> 1 | I33: 30 | J33: 45833 | K33: =SUMIF('Реестр уборки 2025'!Z:Z,J33,'Реестр уборки 2025'!G:G)/1000 -> 19.23 | L33: =IFERROR(AVERAGEIF('Реестр уборки 2025'!Z:Z,'Данные 2025'!J33,'Реестр уборки 2025'!C:C),) -> 48.5 | M33: 40-52
A34: Переработка | B34: =B37-B35-B36 -> 6329.53 | I34: 31 | J34: 45834
A35: Утилизация | B35: =(108250+8280+39390)/1000 -> 155.92 | I35: 32 | J35: 45835 | K35: =SUMIF('Реестр уборки 2025'!Z:Z,J35,'Реестр уборки 2025'!G:G)/1000 -> 17.56 | L35: =IFERROR(AVERAGEIF('Реестр уборки 2025'!Z:Z,'Данные 2025'!J35,'Реестр уборки 2025'!C:C),) -> 46 | M35: 40-52
A36: Реализация | B36: 612.69 | C36: 542.3951 | D36: - реализовано по документам отгрузки (ранее было указано в отчете) | I36: 33 | J36: 45836 | K36: =SUMIF('Реестр уборки 2025'!Z:Z,J36,'Реестр уборки 2025'!G:G)/1000 -> 43.19 | L36: =IFERROR(AVERAGEIF('Реестр уборки 2025'!Z:Z,'Данные 2025'!J36,'Реестр уборки 2025'!C:C),) -> 48 | M36: 40-52
A37: Собственное сырье | B37: =F12 -> 7098.14 | I37: 34 | J37: 45837 | K37: =SUMIF('Реестр уборки 2025'!Z:Z,J37,'Реестр уборки 2025'!G:G)/1000 -> 71.97 | L37: =IFERROR(AVERAGEIF('Реестр уборки 2025'!Z:Z,'Данные 2025'!J37,'Реестр уборки 2025'!C:C),) -> 48.444444 | M37: 40-52
A38: Закупка | B38: 0 | C38: не указана закупка Брактовского, так как она была запланирована в конвейере | I38: 35 | J38: 45838 | K38: =SUMIF('Реестр уборки 2025'!Z:Z,J38,'Реестр уборки 2025'!G:G)/1000 -> 25.63 | L38: =IFERROR(AVERAGEIF('Реестр уборки 2025'!Z:Z,'Данные 2025'!J38,'Реестр уборки 2025'!C:C),) -> 52 | M38: 40-52
I39: 36 | J39: 45839 | K39: =SUMIF('Реестр уборки 2025'!Z:Z,J39,'Реестр уборки 2025'!G:G)/1000 -> 176.53 | L39: =IFERROR(AVERAGEIF('Реестр уборки 2025'!Z:Z,'Данные 2025'!J39,'Реестр уборки 2025'!C:C),) -> 54 | M39: 53-63
I40: 37 | J40: 45840 | K40: =SUMIF('Реестр уборки 2025'!Z:Z,J40,'Реестр уборки 2025'!G:G)/1000 -> 192.78 | L40: =IFERROR(AVERAGEIF('Реестр уборки 2025'!Z:Z,'Данные 2025'!J40,'Реестр уборки 2025'!C:C),) -> 52.357143 | M40: 40-52
I41: 38 | J41: 45841 | K41: =SUMIF('Реестр уборки 2025'!Z:Z,J41,'Реестр уборки 2025'!G:G)/1000 -> 204.08 | L41: =IFERROR(AVERAGEIF('Реестр уборки 2025'!Z:Z,'Данные 2025'!J41,'Реестр уборки 2025'!C:C),) -> 55.6875 | M41: 53-63
I42: 39 | J42: 45842 | K42: =SUMIF('Реестр уборки 2025'!Z:Z,J42,'Реестр уборки 2025'!G:G)/1000 -> 147.51 | L42: =IFERROR(AVERAGEIF('Реестр уборки 2025'!Z:Z,'Данные 2025'!J42,'Реестр уборки 2025'!C:C),) -> 61.363636 | M42: 53-63
I43: 40 | J43: 45843 | K43: =SUMIF('Реестр уборки 2025'!Z:Z,J43,'Реестр уборки 2025'!G:G)/1000 -> 163.17 | L43: =IFERROR(AVERAGEIF('Реестр уборки 2025'!Z:Z,'Данные 2025'!J43,'Реестр уборки 2025'!C:C),) -> 61.25 | M43: 53-63
I44: 41 | J44: 45844 | K44: =SUMIF('Реестр уборки 2025'!Z:Z,J44,'Реестр уборки 2025'!G:G)/1000 -> 120.94 | L44: =IFERROR(AVERAGEIF('Реестр уборки 2025'!Z:Z,'Данные 2025'!J44,'Реестр уборки 2025'!C:C),) -> 53.222222 | M44: 53-63
I45: 42 | J45: 45845
I46: 43 | J46: 45846 | K46: =SUMIF('Реестр уборки 2025'!Z:Z,J46,'Реестр уборки 2025'!G:G)/1000 -> 131.84 | L46: =IFERROR(AVERAGEIF('Реестр уборки 2025'!Z:Z,'Данные 2025'!J46,'Реестр уборки 2025'!C:C),) -> 67.1 | M46: 67-85
I47: 44 | J47: 45847 | K47: =SUMIF('Реестр уборки 2025'!Z:Z,J47,'Реестр уборки 2025'!G:G)/1000 -> 63.8 | L47: =IFERROR(AVERAGEIF('Реестр уборки 2025'!Z:Z,'Данные 2025'!J47,'Реестр уборки 2025'!C:C),) -> 71.4 | M47: 67-85
I48: 45 | J48: 45848 | K48: =SUMIF('Реестр уборки 2025'!Z:Z,J48,'Реестр уборки 2025'!G:G)/1000 -> 26.58 | L48: =IFERROR(AVERAGEIF('Реестр уборки 2025'!Z:Z,'Данные 2025'!J48,'Реестр уборки 2025'!C:C),) -> 70.5 | M48: 67-85
K49: =SUM(K4:K48) -> 7098.14
A54: Культура | B54: Орошение | C54: ПЛАН, т | D54: ФАКТ, т | E54: Исполнение плана по валу, % | F54: ПЛАН, га | G54: ФАКТ, га | H54: Исполнение плана по площади, % | I54: Урожайность, т/га
A55: Учхоз Кубань | B55: богара | C55: 1157.4 | D55: =SUMIF('Реестр уборки 2025'!W:W,'Реестр уборки 2025'!$W$3,'Реестр уборки 2025'!G:G)/1000 -> 1320.13 | E55: =IFERROR(D55/C55, ) -> 1.1405996 | F55: 257.2 | G55: =SUMIF('Реестр уборки 2025'!W:W,'Реестр уборки 2025'!$W$3,'Реестр уборки 2025'!V:V) -> 237.2438 | H55: =IFERROR(G55/F55, ) -> 0.92240982 | I55: =Таблица4[[#This Row],[ФАКТ, т]]/Таблица4[[#This Row],[ФАКТ, га]] -> 5.5644446
A56: ГРК собственные семена | B56: богара | C56: 910 | D56: =SUMIF('Реестр уборки 2025'!W:W,'Реестр уборки 2025'!$W$4,'Реестр уборки 2025'!G:G)/1000 -> 503.65 | E56: =IFERROR(D56/C56, ) -> 0.55346154 | F56: 260 | G56: =SUMIF('Реестр уборки 2025'!W:W,'Реестр уборки 2025'!$W$4,'Реестр уборки 2025'!V:V) -> 183.41255 | H56: =IFERROR(G56/F56, ) -> 0.70543288 | I56: =Таблица4[[#This Row],[ФАКТ, т]]/Таблица4[[#This Row],[ФАКТ, га]] -> 2.7459953
A57: ГРК демо | B57: богара | C57: 136.5 | D57: =SUMIF('Реестр уборки 2025'!W:W,'Реестр уборки 2025'!$W$181,'Реестр уборки 2025'!G:G)/1000 -> 91.8 | E57: =IFERROR(D57/C57, ) -> 0.67252747 | F57: 39 | G57: =SUMIF('Реестр уборки 2025'!W:W,'Реестр уборки 2025'!$W$181,'Реестр уборки 2025'!V:V) -> 31 | H57: =IFERROR(G57/F57, ) -> 0.79487179 | I57: =Таблица4[[#This Row],[ФАКТ, т]]/Таблица4[[#This Row],[ФАКТ, га]] -> 2.9612903
A58: ГРК | B58: богара | C58: 936.2 | D58: =SUMIF('Реестр уборки 2025'!W:W,'Реестр уборки 2025'!$W$86,'Реестр уборки 2025'!G:G)/1000 -> 769.25 | E58: =IFERROR(D58/C58, ) -> 0.82167272 | F58: 302 | G58: =SUMIF('Реестр уборки 2025'!W:W,'Реестр уборки 2025'!$W$109,'Реестр уборки 2025'!V:V) -> 246.59801 | H58: =IFERROR(G58/F58, ) -> 0.81654971 | I58: =Таблица4[[#This Row],[ФАКТ, т]]/Таблица4[[#This Row],[ФАКТ, га]] -> 3.1194493
A59: Братковский | B59: полив | C59: 765 | D59: =SUMIF('Реестр уборки 2025'!W:W,'Реестр уборки 2025'!$W$225,'Реестр уборки 2025'!G:G)/1000 -> 842.08 | E59: =IFERROR(D59/C59, ) -> 1.1007582 | F59: 180 | G59: =SUMIF('Реестр уборки 2025'!W:W,'Реестр уборки 2025'!$W$225,'Реестр уборки 2025'!V:V) -> 147.98974 | H59: =IFERROR(G59/F59, ) -> 0.82216523 | I59: =Таблица4[[#This Row],[ФАКТ, т]]/Таблица4[[#This Row],[ФАКТ, га]] -> 5.6901241
A60: Братковский закупка | B60: полив | C60: 522.325 | D60: =SUMIF('Реестр уборки 2025'!W:W,'Реестр уборки 2025'!$W$247,'Реестр уборки 2025'!G:G)/1000 -> 561.3 | E60: =IFERROR(D60/C60, ) -> 1.0746183 | F60: =122.9-2.9 -> 120 | G60: =SUMIF('Реестр уборки 2025'!W:W,'Реестр уборки 2025'!$W$247,'Реестр уборки 2025'!V:V) -> 120.02629 | H60: =IFERROR(G60/F60, ) -> 1.0002191 | I60: =Таблица4[[#This Row],[ФАКТ, т]]/Таблица4[[#This Row],[ФАКТ, га]] -> 4.6764754
A61: Агролидер | B61: полив | C61: 586.5 | D61: =SUMIF('Реестр уборки 2025'!W:W,'Реестр уборки 2025'!$W$275,'Реестр уборки 2025'!G:G)/1000 -> 1017.73 | E61: =IFERROR(D61/C61, ) -> 1.73526 | F61: 138 | G61: =SUMIF('Реестр уборки 2025'!W:W,'Реестр уборки 2025'!$W$275,'Реестр уборки 2025'!V:V) -> 138 | H61: =IFERROR(G61/F61, ) -> 1 | I61: =Таблица4[[#This Row],[ФАКТ, т]]/Таблица4[[#This Row],[ФАКТ, га]] -> 7.3748551
A62: Колос | B62: полив | C62: 1784.12 | D62: =SUMIF('Реестр уборки 2025'!W:W,'Реестр уборки 2025'!$W$431,'Реестр уборки 2025'!G:G)/1000 -> 1992.2 | E62: =IFERROR(D62/C62, ) -> 1.1166289 | F62: 379.6 | G62: =SUMIF('Реестр уборки 2025'!W:W,'Реестр уборки 2025'!$W$431,'Реестр уборки 2025'!V:V) -> 379.58969 | H62: =IFERROR(G62/F62, ) -> 0.99997283 | I62: =Таблица4[[#This Row],[ФАКТ, т]]/Таблица4[[#This Row],[ФАКТ, га]] -> 5.2482986
C63: =SUBTOTAL(109,C55:C62) -> 6798.045 | D63: =SUBTOTAL(109,D55:D62) -> 7098.14 | E63: =D63/C63 -> 1.0441443 | F63: =SUBTOTAL(109,F55:F62) -> 1675.8 | G63: =SUBTOTAL(109,G55:G62) -> 1483.8601 | H63: =IFERROR(G63/F63, ) -> 0.88546371 | I63: =D63/G63 -> 4.7835642
A66: Названия строк | B66: ПЛАН, т | C66: ФАКТ, т | D66: Исполнение, % | E66: ПЛАН, га | F66: ФАКТ, га
A67: Агролидер | B67: 586.5 | C67: 1017.73 | D67: 1.73526 | E67: 138 | F67: 138
A68: Братковский | B68: 765 | C68: 842.08 | D68: 1.1007582 | E68: 180 | F68: 147.98974
A69: Братковский закупка | B69: 522.325 | C69: 561.3 | D69: 1.0746183 | E69: 120 | F69: 120.02629
A70: ГРК | B70: 936.2 | C70: 769.25 | D70: 0.82167272 | E70: 302 | F70: 246.59801
A71: ГРК демо | B71: 136.5 | C71: 91.8 | D71: 0.67252747 | E71: 39 | F71: 31
A72: ГРК собственные семена | B72: 910 | C72: 503.65 | D72: 0.55346154 | E72: 260 | F72: 183.41255
A73: Колос | B73: 1784.12 | C73: 1992.2 | D73: 1.1166289 | E73: 379.6 | F73: 379.58969
A74: Учхоз Кубань | B74: 1157.4 | C74: 1320.13 | D74: 1.1405996 | E74: 257.2 | F74: 237.2438
A75: Общий итог | B75: 6798.045 | C75: 7098.14 | D75: 1.0441443 | E75: 1675.8 | F75: 1483.8601

Sheet СВОД по полям
A1: Контрагент | B1: Полив | C1: Номер поля | D1: Сорт | E1: Площадь сева | F1: Площадь уборки | G1: Остаток площади | H1: Закрытие, % | I1: Урожайность плановая, т/га | J1: Урожайность фактическая, т/га | K1: Валовый сбор плановый, т | L1: Валовый сбор фактический, т | M1: Выполнение плана, %
A2: ООО ГРК | B2: богара | C2: А-17 | D2: Преладо | E2: 48 | F2: #VALUE! | G2: =E2-F2 -> #VALUE! | H2: =IFERROR(F2/E2,"-") -> - | I2: =4*0.9 -> 3.6 | J2: =IFERROR(L2/F2,) -> 0 | K2: =E2*I2 -> 172.8 | L2: #VALUE! | M2: =IFERROR(L2/K2,"-") -> -

Sheet Поступление на завод 
A1: Продажа | B1: (пусто)
A2: Поступление горошка на завод по дням (без учета продажи)
D3: Значения
A4: Регистратор.Дата | B4: Культура | C4: Поле | D4: Физический вес, кг | E4: Зачетный вес, кг
A5: (пусто) | B5: ГРК (богара) | D5: 3586130 | E5: 3055975.4
B6: Агролидер (полив) | D6: 998000 | E6: 898798.1
B7: Колос (полив) | D7: 1357260 | E7: 1222677.6
B8: ГРК (полив) | C8: А-54 | D8: 273690 | E8: 237835.1
C9: А-104/1 | D9: 80320 | E9: 67167.5
C10: А-82/1 | D10: 13830 | E10: 12195.1
C11: А-54/4 | D11: 151350 | E11: 133828.2
C12: А-112/2 | D12: 133390 | E12: 117881.2
C13: А-81/1 | D13: 73080 | E13: 67505.9
C14: А-108/7 | D14: 255800 | E14: 228067.9
C15: А-113/1 | D15: 154940 | E15: 134543.8
B16: ГРК (полив) Итог | D16: 1136400 | E16: 999024.7
A17: Общий итог | D17: 7077790 | E17: 6176475.8

Sheet Поступление на завод по дням
A3: Дата | B3: Физический вес, тонны | C3: Физический вес, кг | D3: Зачетный вес, кг | E3: Дата акта входного контроля | I3: По дате акта входного контроля
A4: 45804 | B4: =C4/1000 -> 29.45 | C4: 29450 | D4: 21740.7 | E4: 45804 | I4: Дата | J4: Физический вес, тонны
A5: 45805 | B5: =C5/1000 -> 98.79 | C5: 98790 | D5: 71595.6 | E5: 45805 | I5: май | J5: 227.18
A6: 45806 | B6: =C6/1000 -> 52.63 | C6: 52630 | D6: 37492 | E6: 45806 | I6: 27.май | J6: 29.45
A7: 45807 | B7: =C7/1000 -> 46.31 | C7: 46310 | D7: 33701.5 | E7: 45808 | I7: 28.май | J7: 98.79
A8: 45808 | I8: 29.май | J8: 52.63
A9: 45809 | B9: =C9/1000 -> 163.7 | C9: 163700 | D9: 124140.6 | E9: 45809 | I9: 30.май | J9: 46.31
A10: 45810 | B10: =C10/1000 -> 181.62 | C10: 181620 | D10: 141581.7 | E10: 45810 | I10: 31.май
A11: 45811 | B11: =C11/1000 -> 137.38 | C11: 137380 | D11: 111232.3 | E11: 45811 | I11: июн | J11: 5031.04
A12: 45812 | B12: =C12/1000 -> 218.34 | C12: 218340 | D12: 186899.6 | E12: 45812 | I12: 01.июн | J12: 163.7
A13: 45813 | B13: =C13/1000 -> 257.7 | C13: 257700 | D13: 215785.7 | E13: 45813 | I13: 02.июн | J13: 181.62
A14: 45814 | B14: =C14/1000 -> 187.54 | C14: 187540 | D14: 157412.6 | E14: 45814 | I14: 03.июн | J14: 137.38
A15: 45815 | B15: =C15/1000 -> 222.75 | C15: 222750 | D15: 189231 | E15: 45815 | I15: 04.июн | J15: 218.34
A16: 45816 | B16: =C16/1000 -> 244.84 | C16: 244840 | D16: 214198.4 | E16: 45816 | I16: 05.июн | J16: 257.7
A17: 45817 | B17: =C17/1000 -> 152.51 | C17: 152510 | D17: 127138.9 | E17: 45817 | I17: 06.июн | J17: 187.54
A18: 45818 | B18: =C18/1000 -> 185.62 | C18: 185620 | D18: 159943.4 | E18: 45818 | I18: 07.июн | J18: 222.75
A19: 45819 | B19: =C19/1000 -> 159.63 | C19: 159630 | D19: 146763.8 | E19: 45819 | I19: 08.июн | J19: 244.84
A20: 45820 | B20: =C20/1000 -> 269.58 | C20: 269580 | D20: 233118.8 | E20: 45820 | I20: 09.июн | J20: 152.51
A21: 45821 | B21: =C21/1000 -> 214.02 | C21: 214020 | D21: 182865.4 | E21: 45821 | I21: 10.июн | J21: 185.62
A22: 45822 | B22: =C22/1000 -> 288.24 | C22: 288240 | D22: 252886.4 | E22: 45822 | I22: 11.июн | J22: 159.63
... A33: 45833 | B33: =C33/1000 -> 125.43 | C33: 125430 | D33: 104544.2 | E33: 45833 | I33: 22.июн | J33: 204.71
A34: 45834 | I34: 23.июн | J34: 228.57
A35: 45835 | I35: 24.июн | J35: 94.08
A36: 45836 | B36: =C36/1000 -> 60.75 | C36: 60750 | D36: 51333.9 | E36: 45836 | I36: 25.июн | J36: 125.43
A37: 45837 | B37: =C37/1000 -> 69.23 | C37: 69230 | D37: 60600.6 | E37: 45837 | I37: 26.июн
A38: 45838 | B38: =C38/1000 -> 28.37 | C38: 28370 | D38: 24692.3 | E38: 45838 | I38: 27.июн
A39: 45839 | B39: =C39/1000 -> 69.19 | C39: 69190 | D39: 60335.2 | E39: 45839 | I39: 28.июн | J39: 60.75
A40: 45840 | B40: =C40/1000 -> 218.92 | C40: 218920 | D40: 187414.8 | E40: 45840 | I40: 29.июн | J40: 69.23
A41: 45841 | B41: =C41/1000 -> 192.37 | C41: 192370 | D41: 161740.5 | E41: 45841 | I41: 30.июн | J41: 28.37
A42: 45842 | B42: =C42/1000 -> 213.73 | C42: 213730 | D42: 190148.5 | E42: 45842 | I42: июл | J42: 1227.23
A43: 45843 | B43: =C43/1000 -> 84.68 | C43: 84680 | D43: 73460.3 | E43: 45843 | I43: 01.июл | J43: 69.19
A44: 45844 | B44: =C44/1000 -> 226.12 | C44: 226120 | D44: 203439.1 | E44: 45844 | I44: 02.июл | J44: 218.92
A45: 45845 | I45: 03.июл | J45: 192.37
A46: 45846 | B46: =C46/1000 -> 40.51 | C46: 40510 | D46: 36604.8 | E46: 45846 | I46: 04.июл | J46: 213.73
A47: 45847 | B47: =C47/1000 -> 143.24 | C47: 143240 | D47: 125850.3 | E47: 45847 | I47: 05.июл | J47: 84.68
A48: 45848 | B48: =C48/1000 -> 38.47 | C48: 38470 | D48: 31337.5 | E48: 45848 | I48: 06.июл | J48: 226.12
I49: 07.июл
I50: 08.июл | J50: 40.51
I51: 09.июл | J51: 143.24
I52: 10.июл | J52: 38.47
I53: Общий итог | J53: 6485.45

Sheet по дням
A1: Продажа | B1: (пусто)
A3: Вес нетто, т | B3: Характеристика
A4: Регистратор.Дата | B4: Первый | C4: Высший | D4: Второй | E4: Общий итог
A5: (пусто) | B5: 1434.53 | C5: 5468.02 | D5: 175.24 | E5: 7077.79
A6: Общий итог | B6: 1434.53 | C6: 5468.02 | D6: 175.24 | E6: 7077.79

Sheet Сев 2026
B1: Поле | C1: Культура | D1: Авола | E1: Площадь поля | F1: Площадь внесения
B2: А-104/1 | C2: Горошек овощной (богара) | E2: 11 | F2: 11
B3: Семена гороха ( п.е.) | C3: Женева 100 т.с. | D3: Женева | E3: 11 | F3: 1.5
B4: Семена гороха овощного протравленные | C4: Тристар 100 тыс.с (лот D0021 15 T25-3033ST) | D4: Тристар | E4: 11 | F4: 1.5
B5: Семена гороха овощного протравленные (кг) | C5: Патриот ЭС | D5: Патриот | E5: 11 | F5: 8
B6: А-105/1 | C6: Горошек овощной (богара) | E6: 56 | F6: 56
B7: Семена гороха ( п.е.) | C7: Женева 100 т.с. | D7: Женева | E7: 56 | F7: 1.5
B8: Семена гороха овощного протравленные | C8: Авола 100 тыс.с (лот D0021 15 K25-6011ST) | D8: Авола | E8: 56 | F8: 24
B9: Семена гороха овощного протравленные | C9: Авола 100 тыс.с (лот D0021 15 K25-6012ST) | D9: Авола | E9: 56 | F9: 30.5
B10: А-111/1 | C10: Горошек овощной (богара) | E10: 14 | F10: 14
B11: Семена гороха овощного протравленные | C11: Авола 100 тыс.с (лот Kl1038104) | D11: Авола | E11: 14 | F11: 14
B12: А-112/1 | C12: Горошек овощной (богара) | E12: 40 | F12: 40
B13: Семена гороха овощного протравленные | C13: Авола 100 тыс.с (лот Kl1038104) | D13: Авола | E13: 40 | F13: 10
B14: Семена гороха овощного протравленные | C14: Тристар 100 тыс.с (лот ES1038103) | D14: Тристар | E14: 40 | F14: 30
B15: А-114 | C15: Горошек овощной (богара) | E15: 4 | F15: 4
B16: Семена гороха ( п.е.) | C16: Женева 100 т.с. | D16: Женева | E16: 4 | F16: 4
B17: А-115/1 | C17: Горошек овощной (богара) | E17: 63 | F17: 63
B18: Семена гороха овощного протравленные | C18: Тристар 100 тыс.с (лот D0021 15 T25-3033ST) | D18: Тристар | E18: 63 | F18: 21
B19: Семена гороха овощного протравленные | C19: Тристар 100 тыс.с (лот ES1038103) | D19: Тристар | E19: 63 | F19: 42
B20: А-116/1 | C20: Горошек овощной (богара) | E20: 47 | F20: 94
B21: Семена гороха овощного протравленные | C21: Фаворит 100 т.с.(партия Н-Х/4402) | D21: Фаворит | E21: 47 | F21: 47
B22: Семена гороха овощного протравленные | C22: Фаворит 100 т.с.(партия Н-Х/5126) | D22: Фаворит | E22: 47 | F22: 36
B23: Семена гороха овощного протравленные | C23: Фаворит 100 т.с.(партия Н-Х/5128) | D23: Фаворит | E23: 47 | F23: 11
B24: А-22/1 | C24: Горошек овощной (богара) | E24: 36 | F24: 36
B25: Семена гороха ( п.е.) | C25: Увертюра 100 000 | D25: Увертюра | E25: 36 | F25: 31
B26: Семена гороха овощного протравленные | C26: Тиара 100 т.с.(партия Н-Х/5120) | D26: Тиара | E26: 36 | F26: 5
B27: А-23 | C27: Горошек овощной (богара) | E27: 41 | F27: 41
B28: Семена гороха ( п.е.) | C28: Увертюра 100 000 | D28: Увертюра | E28: 41 | F28: 20
B29: Семена гороха овощного протравленные | C29: Фаворит 100 т.с.(партия Н-Х/5121) | D29: Фаворит | E29: 41 | F29: 21
B30: А-24/1 | C30: Горошек овощной (богара) | E30: 39 | F30: 39
B31: Семена гороха овощного протравленные | C31: Фаворит 100 т.с.(партия Н-Х/5121) | D31: Фаворит | E31: 39 | F31: 39
B32: А-3 | C32: Горошек овощной (богара) | E32: 79 | F32: 158
B33: Семена гороха овощного протравленные | C33: Авола 100 тыс.с (лот D0021 15 K25-6011ST) | D33: Авола | E33: 79 | F33: 34
B34: Семена гороха овощного протравленные | C34: Авола 100 тыс.с (лот Kl1038104) | D34: Авола | E34: 79 | F34: 45
B35: Семена гороха овощного протравленные (кг) | C35: Преладо | E35: 79 | F35: 79
B36: А-38 | C36: Горошек овощной (богара) | E36: 38 | F36: 76
B37: Семена гороха овощного протравленные | C37: Авола 100 тыс.с (лот Kl1038104) | D37: Авола | E37: 38 | F37: 38
B38: Семена гороха овощного протравленные (кг) | C38: Преладо | E38: 38 | F38: 38
B39: А-4/1 | C39: Горошек овощной (богара) | E39: 111 | F39: 111
B40: Семена гороха овощного протравленные | C40: Тиара 100 т.с.(партия Н-Х/5116) | D40: Тиара | E40: 111 | F40: 62
B41: Семена гороха овощного протравленные | C41: Тиара 100 т.с.(партия Н-Х/5119) | D41: Тиара | E41: 111 | F41: 39
B42: Семена гороха овощного протравленные | C42: Тиара 100 т.с.(партия Н-Х/5120) | D42: Тиара | E42: 111 | F42: 10
B43: А-5/1 | C43: Горошек овощной (богара) | E43: 63 | F43: 126
B44: Семена гороха овощного протравленные | C44: Авола 100 тыс.с (лот D0021 15 K25-6011ST) | D44: Авола | E44: 63 | F44: 63
B45: Семена гороха овощного протравленные (кг) | C45: Преладо | E45: 63 | F45: 63
B46: А-76/3 | C46: Горошек овощной (богара) | E46: 41 | F46: 82
B47: Семена гороха овощного протравленные | C47: Авола 100 тыс.с (лот Kl1038104) | D47: Авола | E47: 41 | F47: 41
B48: Семена гороха овощного протравленные (кг) | C48: Преладо | E48: 41 | F48: 41
B49: А-76/5 | C49: Горошек овощной (богара) | E49: 14 | F49: 28
B50: Семена гороха овощного протравленные | C50: Авола 100 тыс.с (лот Kl1038104) | D50: Авола | E50: 14 | F50: 14
B51: Семена гороха овощного протравленные (кг) | C51: Преладо | E51: 14 | F51: 14
B52: А-83/1 | C52: Горошек овощной (богара) | E52: 24 | F52: 24
B53: Семена гороха овощного протравленные | C53: Фаворит 100 т.с.(партия Н-Х/5121) | D53: Фаворит | E53: 24 | F53: 24
B54: А-83/2 | C54: Горошек овощной (богара) | E54: 57 | F54: 57
B55: Семена гороха овощного протравленные | C55: Авола 100 тыс.с (лот D0021 15 K25-6011ST) | D55: Авола | E55: 57 | F55: 17.3
B56: Семена гороха овощного протравленные | C56: Авола 100 тыс.с (лот D0021 15 K25-6012ST) | D56: Авола | E56: 57 | F56: 34.7
B57: Семена гороха овощного протравленные | C57: Фаворит 100 т.с.(партия Н-Х/5121) | D57: Фаворит | E57: 57 | F57: 5
B58: А-104/1 | C58: Горошек овощной (полив) | E58: 49 | F58: 98
B59: Семена гороха овощного протравленные | C59: Фаворит 100 т.с.(партия Н-Х/4402) | D59: Фаворит | E59: 49 | F59: 49
B60: Семена гороха овощного протравленные | C60: Фаворит 100 т.с.(партия Н-Х/5126) | D60: Фаворит | E60: 49 | F60: 16
B61: Семена гороха овощного протравленные (кг) | C61: Патриот ЭС | D61: Патриот | E61: 49 | F61: 33
B62: А-108/7 | C62: Горошек овощной (полив) | E62: 102 | F62: 204
B63: Семена гороха овощного протравленные | C63: Фаворит 100 т.с.(партия Н-Х/4402) | D63: Фаворит | E63: 102 | F63: 102
B64: Семена гороха овощного протравленные (кг) | C64: Патриот ЭС | D64: Патриот | E64: 102 | F64: 102
B65: А-112/2 | C65: Горошек овощной (полив) | E65: 20 | F65: 40
B66: Семена гороха овощного протравленные | C66: Тристар 100 тыс.с (лот ES1038103) | D66: Тристар | E66: 20 | F66: 20
B67: Семена горчицы | C67: Без характеристики | E67: 20 | F67: 20
B68: А-113/1 | C68: Горошек овощной (полив) | E68: 62 | F68: 124
B69: Семена гороха овощного протравленные | C69: Стандана 6 000 000 | D69: Стандана | E69: 62 | F69: 50
B70: Семена гороха овощного протравленные | C70: Фаворит 100 т.с.(партия Н-Х/4402) | D70: Фаворит | E70: 62 | F70: 12
B71: Семена гороха овощного протравленные | C71: Фаворит 100 т.с.(партия Н-Х/5126) | D71: Фаворит | E71: 62 | F71: 62
B72: А-54 | C72: Горошек овощной (полив) | E72: 55 | F72: 55
B73: Семена гороха ( п.е.) | C73: Женева 100 т.с. | D73: Женева | E73: 55 | F73: 54
B74: Семена гороха овощного протравленные | C74: Тристар 100 тыс.с (лот LE1038105) | D74: Тристар | E74: 55 | F74: 1
B75: А-54/4 | C75: Горошек овощной (полив) | E75: 39 | F75: 78
B76: Семена гороха овощного протравленные | C76: Тристар 100 тыс.с (лот LE1038105) | D76: Тристар | E76: 39 | F76: 39
B77: Семена горчицы | C77: Без характеристики | E77: 39 | F77: 39
B78: А-79 | C78: Горошек овощной (полив) | E78: 54 | F78: 108
B79: Семена гороха ( п.е.) | C79: Увертюра 100 000 | D79: Увертюра | E79: 54 | F79: 30.2
B80: Семена гороха овощного протравленные | C80: Увертюра 100 000 | D80: Увертюра | E80: 54 | F80: 23.8
B81: Семена гороха овощного протравленные | C81: Фаворит 100 т.с.(партия Н-Х/4402) | D81: Фаворит | E81: 54 | F81: 54
B82: А-81/1 | C82: Горошек овощной (полив) | E82: 19 | F82: 38
B83: Семена гороха овощного протравленные | C83: Тристар 100 тыс.с (лот LE1038105) | D83: Тристар | E83: 19 | F83: 19
B84: Семена горчицы | C84: Без характеристики | E84: 19 | F84: 19
B85: А-82/1 | C85: Горошек овощной (полив) | E85: 20 | F85: 40
B86: Семена гороха ( п.е.) | C86: Женева 100 т.с. | D86: Женева | E86: 20 | F86: 8
B87: Семена гороха овощного протравленные | C87: Тристар 100 тыс.с (лот LE1038105) | D87: Тристар | E87: 20 | F87: 12
B88: Семена горчицы | C88: Без характеристики | E88: 20 | F88: 20
B89: 12 Агролидер | C89: Горошек овощной Агролидер (полив) | E89: 76.64 | F89: 76.64
B90: Семена гороха ( п.е.) | C90: Женева 100 т.с. | D90: Женева | E90: 76.64 | F90: 46
B91: Семена гороха овощного протравленные | C91: Тристар 100 тыс.с (лот D0021 15 T25-3034ST) | D91: Тристар | E91: 76.64 | F91: 30.64
B92: 17 Агролидер | C92: Горошек овощной Агролидер (полив) | E92: 63.51 | F92: 63.51
B93: Семена гороха овощного протравленные | C93: Тристар 100 тыс.с (лот D0021 15 T25-3034ST) | D93: Тристар | E93: 63.51 | F93: 63.51
B94: 18 Агролидер | C94: Горошек овощной Агролидер (полив) | E94: 128.85 | F94: 128.85
B95: Семена гороха овощного протравленные | C95: Тристар 100 тыс.с (лот D0021 15 T25-3032ST) | D95: Тристар | E95: 128.85 | F95: 30
B96: Семена гороха овощного протравленные | C96: Тристар 100 тыс.с (лот D0021 15 T25-3034ST) | D96: Тристар | E96: 128.85 | F96: 2.85
B97: Семена гороха овощного протравленные | C97: Тристар 100 тыс.с (лот D0021 15 T25-3035ST) | D97: Тристар | E97: 128.85 | F97: 96
B98: 1.6 Колос | C98: Горошек овощной Колос ООО (полив) | E98: 38.6 | F98: 38.6
B99: Семена гороха овощного протравленные | C99: Фаворит 100 т.с.(партия Н-Х/5125) | D99: Фаворит | E99: 38.6 | F99: 38.6
B100: 1.7 Колос | C100: Горошек овощной Колос ООО (полив) | E100: 55 | F100: 55
...

Sheet Показатели по полям 2026
AR1: Уборка горошка в 2026 году на 06.07.2026
AR3: Сорт "Авола"
AR4: Валовый сбор, тонны | AU4: =GETPIVOTDATA(" Валовый сбор, т",$A$10) -> 1834.69
AR5: Площадь уборки, га | AU5: =AU4/AU6 -> 307.5
AR6: Урожайность вал.вес, т/га | AU6: =GETPIVOTDATA(" Урожайность вал.вес, т/га",$A$10) -> 5.9664715
AR7: Среднее значение финометра, % | AU7: =GETPIVOTDATA("Степень зрелости (финометр), %",$A$10) -> 57.437908
A10: Сорт/Поле/Дата уборки | B10: Степень зрелости (финометр), % | C10: Валовый сбор, т | D10: Урожайность вал.вес, т/га
A11: Авола | B11: 57.437908 | C11: 1834.69 | D11: 5.9664715
A12: А-105/1 | B12: 60.217391 | C12: 272.69 | D12: 5.0034862
A13: 46187 | B13: 57.833333 | C13: 68.82 | D13: 7.6466667
A14: 46188 | B14: 61.058824 | C14: 203.87 | D14: 4.4806593
A15: А-111/1 | B15: 55.5 | C15: 11.42 | D15: 5.71
A16: 46183 | B16: 55.5 | C16: 11.42 | D16: 5.71
A17: А-112/1 | B17: 63 | C17: 4.43 | D17: 4.43
A18: 46183 | B18: 63 | C18: 4.43 | D18: 4.43
A19: А-3 | B19: 49.657895 | C19: 447.05 | D19: 5.6588608
A20: 46177 | B20: 42 | C20: 6.12 | D20: 3.06
A21: 46180 | B21: 50.428571 | C21: 160.93 | D21: 5.3643333
A22: 46181 | B22: 49.55 | C22: 246.5 | D22: 6.0121951
A23: 46182 | B23: 49.333333 | C23: 33.5 | D23: 5.5833333
A24: А-38 | B24: 55.272727 | C24: 292.71 | D24: 7.7028947
A25: 46183 | B25: 55.272727 | C25: 292.71 | D25: 7.7028947
A26: А-5/1 | B26: 63.636364 | C26: 138.16 | D26: 5.3138462
A27: 46184 | B27: 63.636364 | C27: 138.16 | D27: 5.3138462
A28: А-76/3 | B28: 57.115385 | C28: 311.44 | D28: 7.5960976
A29: 46185 | B29: 48.75 | C29: 101.32 | D29: 6.7546667
A30: 46186 | B30: 60.833333 | C30: 210.12 | D30: 8.0815385
A31: А-76/5 | B31: 67.833333 | C31: 70.99 | D31: 5.0707143
A32: 46185 | B32: 67.833333 | C32: 70.99 | D32: 5.0707143
A33: А-83/2 | B33: 63.916667 | C33: 285.8 | D33: 5.4961538
A34: 46187 | B34: 63.888889 | C34: 214.95 | D34: 6.1414286
A35: 46188 | B35: 64 | C35: 70.85 | D35: 4.1676471
A36: Общий итог | B36: 57.437908 | C36: 1834.69 | D36: 5.9664715
AR37: Сорт "Женева"
AR38: Валовый сбор, тонны | AU38: =GETPIVOTDATA(" Валовый сбор, т",$F$45) -> 502.43
AR39: Площадь уборки, га | AU39: =AU38/AU40 -> 103.8
AR40: Урожайность вал.вес, т/га | AU40: =GETPIVOTDATA(" Урожайность вал.вес, т/га",$F$45) -> 4.8403661
AR41: Среднее значение финометра, % | AU41: =GETPIVOTDATA("Степень зрелости (финометр), %",$F$45) -> 54.696429
F45: Сорт/Поле/Дата уборки | G45: Степень зрелости (финометр), % | H45: Валовый сбор, т | I45: Урожайность вал.вес, т/га
F46: Женева | G46: 54.696429 | H46: 502.43 | I46: 4.8403661
F47: 12 Агролидер | G47: 56.235294 | H47: 222.58 | I47: 4.8281996
F48: 46192 | G48: 44 | H48: 4.49 | I48: 4.49
F49: 46196 | G49: 54.181818 | H49: 149.44 | I49: 4.836246
F50: 46197 | G50: 63.2 | H50: 68.65 | I50: 4.834507
F51: А-105/1 | G51: 57 | H51: 5.63 | I51: 3.7533333
F52: 46191 | G52: 57 | H52: 5.63 | I52: 3.7533333
F53: А-114 | G53: 49.5 | H53: 22.56 | I53: 5.64
F54: 46191 | G54: 49.5 | H54: 22.56 | I54: 5.64
F55: А-54 | G55: 54.088235 | H55: 237.83 | I55: 5.1478355
F56: 46192 | G56: 42 | H56: 4.59 | I56: 4.59
F57: 46193 | G57: 47 | H57: 2.35 | I57: 4.7
F58: 46194 | G58: 52.571429 | H58: 103.21 | I58: 5.1348259
F59: 46195 | G59: 51.285714 | H59: 52.42 | I59: 6.5525
F60: 46196 | G60: 58.9 | H60: 67.93 | I60: 4.6527397
F61: 46197 | G61: 66 | H61: 7.33 | I61: 3.665
F62: А-82/1 | G62: 56 | H62: 13.83 | I62: 2.305
F63: 46195 | G63: 56 | H63: 13.83 | I63: 2.305
F64: Общий итог | G64: 54.696429 | H64: 502.43 | I64: 4.8403661
AR68: Сорт "Патриот"
AR69: Валовый сбор, тонны | AU69: =GETPIVOTDATA(" Валовый сбор, т",$K$75) -> 287.74
AR70: Площадь уборки, га | AU70: =AU69/AU71 -> 86.960288
AR71: Урожайность вал.вес, т/га | AU71: =GETPIVOTDATA(" Урожайность вал.вес, т/га",$K$75) -> 3.3088667
AR72: Среднее значение финометра, % | AU72: =GETPIVOTDATA("Степень зрелости (финометр), %",$K$75) -> 59.62069
K75: Сорт/Поле/Дата уборки | L75: Степень зрелости (финометр), % | M75: Валовый сбор, т | N75: Урожайность вал.вес, т/га
K76: Патриот | L76: 59.62069 | M76: 287.74 | N76: 3.3088667
K77: А-104/1 | L77: 60.571429 | M77: 31.94 | N77: 3.2067347
K78: 46192 | L78: 51 | M78: 10.7 | N78: 3.2067347
K79: 46199 | L79: 64.4 | M79: 21.24 | N79: 3.2067347
K80: А-108/7 | L80: 59.318182 | M80: 255.8 | N80: 3.3220779
K81: 46208 | L81: 63.833333 | M81: 62.3 | N81: 3.1464646
K82: 46209 | L82: 57.625 | M82: 193.5 | N82: 3.3828671
K83: Общий итог | L83: 59.62069 | M83: 287.74 | N83: 3.3088667
AR96: Сорт "Тиара"
AR97: Валовый сбор, тонны | AU97: =GETPIVOTDATA(" Валовый сбор, т",$P$103) -> 633.06
AR98: Площадь уборки, га | AU98: =AU97/AU99 -> 116
AR99: Урожайность вал.вес, т/га | AU99: =GETPIVOTDATA(" Урожайность вал.вес, т/га",$P$103) -> 5.4574138
AR100: Среднее значение финометра, % | AU100: =GETPIVOTDATA("Степень зрелости (финометр), %",$P$103) -> 50.509804
P103: Сорт/Поле/Дата уборки | Q103: Степень зрелости (финометр), % | R103: Валовый сбор, т | S103: Урожайность вал.вес, т/га
P104: Тиара | Q104: 50.509804 | R104: 633.06 | S104: 5.4574138
P105: А-22/1 | Q105: 52 | R105: 24.65 | S105: 4.93
P106: 46179 | Q106: 52 | R106: 24.65 | S106: 4.93
P107: А-4/1 | Q107: 50.44898 | R107: 608.41 | S107: 5.4811712
P108: 46176 | Q108: 52.285714 | R108: 191.51 | S108: 5.3197222
P109: 46177 | Q109: 53.25 | R109: 111.25 | S109: 5.5625
P110: 46179 | Q110: 47.428571 | R110: 244.27 | S110: 5.8159524
P111: 46180 | Q111: 53 | R111: 61.38 | S111: 4.7215385
P112: Общий итог | Q112: 50.509804 | R112: 633.06 | S112: 5.4574138
AR121: Сорт "Тристар"
AR122: Валовый сбор, тонны | AU122: =GETPIVOTDATA(" Валовый сбор, т",$U$129) -> 2147.93
AR123: Площадь уборки, га | AU123: =AU122/AU124 -> 411.8
AR124: Урожайность вал.вес, т/га | AU124: =GETPIVOTDATA(" Урожайность вал.вес, т/га",$U$129) -> 5.2159543
AR125: Среднее значение финометра, % | AU125: =GETPIVOTDATA("Степень зрелости (финометр), %",$U$129) -> 59.805556
U129: Сорт/Поле/Дата уборки | V129: Степень зрелости (финометр), % | W129: Валовый сбор, т | X129: Урожайность вал.вес, т/га
U130: Тристар | V130: 59.805556 | W130: 2147.93 | X130: 5.2159543
U131: 12 Агролидер | V131: 55.6 | W131: 115.94 | X131: 3.7888889
U132: 46192 | V132: 45 | W132: 13.77 | X132: 4.59
U133: 46193 | V133: 52.6 | W133: 47 | X133: 3.6153846
U134: 46195 | V134: 62 | W134: 55.17 | X134: 3.7787671
U135: 17 Агролидер | V135: 58.291667 | W135: 312.26 | X135: 4.9174803
U136: 46197 | V136: 55.333333 | W136: 26.58 | X136: 6.9947368
...

Sheet Откл АВК и Отчета
A1: Культура | B1: Агролидер (полив) | J1: Культура | K1: Колос (полив) | P1: Культура | Q1: ГРК (богара)
F3: Значения | J3: Площадь уборки, га | P3: Площадь уборки, га
A4: Поле ОТЧЕТ | B4: Дата отчета | C4: № взвешивания | D4: № акта входного контроля | E4: Поле акт/ТТН | F4: Регистратор.Вес нетто | G4: Площадь уборки, га | J4: Поле ОТЧЕТ | K4: Дата отчета | L4: № акта входного контроля | M4: Поле акт | N4: Итог | P4: Поле ОТЧЕТ | Q4: Дата отчета | R4: Культура акт | S4: № акта входного контроля | T4: Поле акт | U4: Итог
A5: 12 Агролидер | B5: 46192 | C5: 460 | D5: 345 | E5: 12 Агролидер | F5: 13770 | G5: 3 | J5: 2.2 Колос | K5: 46198 | L5: 467 | M5: 2.2 Колос | N5: 3.5 | P5: А-104/1 | Q5: 46192 | R5: Горошек овощной 2026 (богара) | S5: 343 | T5: А-104/1 | U5: 1.4188888
C6: 462 | D6: 347 | E6: 12 Агролидер | F6: 4490 | G6: 1 | L6: 469 | M6: 2.2 Колос | N6: 3.4 | S6: 344 | T6: А-104/1 | U6: 1.9178387
B7: 46193 | C7: 467 | D7: 354 | E7: 12 Агролидер | F7: 4440 | G7: 1.2 | L7: 470 | M7: 2.2 Колос | N7: 3.4 | Q7: 46199 | R7: Горошек овощной 2026 (полив) | S7: 480 | T7: А-104/1 | U7: 1.2941513 | V7: Исправить культуру
C8: 468 | D8: 350 | E8: 12 Агролидер | F8: 12990 | G8: 3.6 | L8: 475 | M8: 2.2 Колос | N8: 3.4 | S8: 481 | T8: А-104/1 | U8: 1.334691 | V8: Исправить культуру
C9: 469 | D9: 351 | E9: 12 Агролидер | F9: 12870 | G9: 3.6 | L9: 479 | M9: 2.2 Колос | N9: 3.3 | S9: 483 | T9: А-104/1 | U9: 1.2380195 | V9: Исправить культуру
C10: 470 | D10: 352 | E10: 12 Агролидер | F10: 3980 | G10: 1.1 | L10: 723 | M10: 2.2 Колос | N10: 3 | S10: 486 | T10: А-104/1 | U10: 1.3596385 | V10: Исправить культуру
C11: 471 | D11: 353 | E11: 12 Агролидер | F11: 12720 | G11: 3.5 | L11: 724 | M11: 2.2 Колос | N11: 3.4 | S11: 487 | T11: А-104/1 | U11: 1.3970598 | V11: Исправить культуру
B12: 46195 | C12: 505 | D12: 386 | E12: 12 Агролидер | F12: 12870 | G12: 3.4 | L12: 721 | M12: 2.2 Колос | N12: 3.8 | P12: А-104/1 Итог | U12: 9.9602877 | V12: Исправить культуру и поле
C13: 508 | D13: 388 | E13: 12 Агролидер | F13: 13140 | G13: 3.5 | L13: 722 | M13: 2.2 Колос | N13: 2.8 | P13: А-105/1 | Q13: 46187 | R13: Горошек овощной 2026 (богара) | S13: 204 | T13: А-83/1 | U13: 1.1
C14: 509 | D14: 389 | E14: 12 Агролидер | F14: 13140 | G14: 3.5 | K14: 46199 | L14: 494 | M14: 2.2 Колос | N14: 7 | S14: 205 | T14: А-105/1 | U14: 1.8 | V14: Исправить поле
C15: 511 | D15: 390 | E15: 12 Агролидер | F15: 16020 | G15: 4.2 | L15: 495 | M15: 2.2 Колос | N15: 6.2 | S15: 206 | T15: А-105/1 | U15: 1.7
B16: 46196 | C16: 541 | D16: 418 | E16: 12 Агролидер | F16: 13480 | G16: 2.8 | L16: 496 | M16: 2.2 Колос | N16: 6.1 | S16: 207 | T16: А-105 | U16: 0.6
C17: 544 | D17: 421 | E17: 12 Агролидер | F17: 13390 | G17: 2.8 | L17: 526 | M17: 2.2 Колос | N17: 5.9 | S17: 208 | T17: А-105 | U17: 1.8 | V17: Исправить (уточнить) поле
C18: 547 | D18: 423 | E18: 12 Агролидер | F18: 16590 | G18: 3.4 | K18: 46200 | L18: 497 | M18: 2.2 Колос | N18: 4.2 | S18: 209 | T18: А-105/1 | U18: 2 | V18: Исправить (уточнить) поле
C19: 549 | D19: 425 | E19: 12 Агролидер | F19: 13080 | G19: 2.7 | L19: 498 | M19: 2.2 Колос | N19: 6.3 | Q19: 46188 | R19: Горошек овощной 2026 (богара) | S19: 235 | T19: А-105 | U19: 3
C20: 550 | D20: 426 | E20: 12 Агролидер | F20: 13050 | G20: 2.7 | L20: 499 | M20: 2.2 Колос | N20: 6.4 | S20: 236 | T20: А-105/1 | U20: 2.9 | V20: Исправить (уточнить) поле
C21: 553 | D21: 429 | E21: 12 Агролидер | F21: 13040 | G21: 2.7 | L21: 500 | M21: 2.2 Колос | N21: 7 | S21: 237 | T21: А-105/1 | U21: 1
C22: 554 | D22: 430 | E22: 12 Агролидер | F22: 13090 | G22: 2.7 | J22: 2.2 Колос Итог | N22: 79.1 | S22: 238 | T22: А-105/1 | U22: 3
C23: 556 | D23: 432 | E23: 12 Агролидер | F23: 13380 | G23: 2.8 | J23: 3.3 Колос | K23: 46200 | L23: 515 | M23: 3.3 Колос | N23: 2.2939028 | S23: 239 | T23: А-105/1 | U23: 2.9
C24: (пусто) | D24: 611 | E24: 18 Агролидер | F24: 13120 | G24: 2.7 | H24: Исправить поле | L24: 516 | M24: 3.3 Колос | N24: 2.2513903 | S24: 240 | T24: А-105/1 | U24: 3
D25: 598 | E25: 18 Агролидер | F25: 13420 | G25: 2.8 | L25: 517 | M25: 3.3 Колос | N25: 2.2868173 | S25: 241 | T25: А-105/1 | U25: 2.9
D26: 599 | E26: 18 Агролидер | F26: 13800 | G26: 2.8 | K26: 46201 | L26: 502 | M26: 3.3 Колос | N26: 2.2 | S26: 242 | T26: А-105/1 | U26: 1
B27: 46197 | C27: 560 | D27: 434 | E27: 12 Агролидер | F27: 12970 | G27: 2.7 | L27: 503 | M27: 3.3 Колос | N27: 1.7 | S27: 243 | T27: А-105/1 | U27: 3
C28: 563 | D28: 436 | E28: 12 Агролидер | F28: 13190 | G28: 2.7 | H28: Исправить поле | L28: 507 | M28: 3.3 Колос | N28: 2.3 | S28: 244 | T28: А-105/1 | U28: 2.9
C29: 569 | D29: 440 | E29: 12 Агролидер | F29: 16090 | G29: 3.3 | L29: 518 | M29: 3.3 Колос | N29: 1.9 | S29: 245 | T29: А-105/1 | U29: 3
C30: (пусто) | D30: 625 | E30: 18 Агролидер | F30: 13320 | G30: 2.7 | L30: 519 | M30: 3.3 Колос | N30: 1.9 | S30: 246 | T30: А-105/1 | U30: 3
D31: 626 | E31: 18 Агролидер | F31: 13080 | G31: 2.8 | L31: 520 | M31: 3.3 Колос | N31: 1.9 | S31: 247 | T31: А-105/1 | U31: 1
A32: 12 Агролидер Итог | F32: 338520 | G32: 76.7 | L32: 521 | M32: 3.3 Колос | N32: 1.9 | S32: 248 | T32: А-105 | U32: 3
A33: 17 Агролидер | B33: 46197 | C33: 573 | D33: 444 | E33: 17 Агролидер | F33: 9250 | G33: 1.3 | L33: 522 | M33: 3.3 Колос | N33: 1.9 | S33: 249 | T33: А-105/1 | U33: 2.9 | V33: Исправить (уточнить) поле
C34: 580 | D34: 453 | E34: 17 Агролидер | F34: 8800 | G34: 1.3 | L34: 523 | M34: 3.3 Колос | N34: 2 | S34: 250 | T34: А-105/1 | U34: 4
C35: 583 | D35: 452 | E35: 17 Агролидер | F35: 8530 | G35: 1.2 | L35: 524 | M35: 3.3 Колос | N35: 1.9 | S35: 278 | T35: А-105 | U35: 3
B36: 46198 | C36: 585 | D36: 456 | E36: 17 Агролидер | F36: 8520 | G36: 1.3 | L36: 525 | M36: 3.3 Колос | N36: 1.9 | Q36: 46191 | R36: Горошек овощной 2026 (богара) | S36: 327 | T36: А-105 | U36: 1.5 | V36: Исправить (уточнить) поле
C37: 588 | D37: 458 | E37: 17 Агролидер | F37: 8710 | G37: 1.3 | L37: 527 | M37: 3.3 Колос | N37: 1.9 | P37: А-105/1 Итог | U37: 56 | V37: Исправить (уточнить) поле
C38: 594 | D38: 460 | E38: 17 Агролидер | F38: 8790 | G38: 1.3 | L38: 528 | M38: 3.3 Колос | N38: 2 | P38: А-111/1 | Q38: 46183 | R38: Горошек овощной 2026 (богара) | S38: 131 | T38: А-111/1 | U38: 1.2
C39: 596 | D39: 462 | E39: 17 Агролидер | F39: 8810 | G39: 1.3 | L39: 529 | M39: 3.3 Колос | N39: 1.9 | S39: 132 | T39: А-111 | U39: 0.8
C40: 599 | D40: 464 | E40: 17 Агролидер | F40: 8810 | G40: 1.3 | L40: 545 | M40: 3.3 Колос | N40: 1.9 | P40: А-111/1 Итог | U40: 2 | V40: Исправить (уточнить) поле
C41: 600 | D41: 465 | E41: 17 Агролидер | F41: 8750 | G41: 1.3 | L41: 547 | M41: 3.3 Колос | N41: 1.9 | P41: А-112/1 | Q41: 46183 | R41: Горошек овощной 2026 (богара) | S41: 129 | T41: А-112 | U41: 1
C42: 607 | D42: 472 | E42: 17 Агролидер | F42: 13190 | G42: 2 | L42: 549 | M42: 3.3 Колос | N42: 1.9 | Q42: 46189 | R42: Горошек овощной 2026 (богара) | S42: 256 | T42: А-112/1 | U42: 1 | V42: Исправить (уточнить) поле
C43: 609 | D43: 474 | E43: 17 Агролидер | F43: 12930 | G43: 2 | L43: 551 | M43: 3.3 Колос | N43: 2 | S43: 257 | T43: А-112 | U43: 1.6
C44: 611 | D44: 476 | E44: 17 Агролидер | F44: 12840 | G44: 2 | K44: 46202 | L44: 508 | M44: 3.3 Колос | N44: 2.4373824 | S44: 258 | T44: А-112/1 | U44: 3.1 | V44: Исправить (уточнить) поле
C45: 613 | D45: 478 | E45: 17 Агролидер | F45: 12770 | G45: 2 | L45: 509 | M45: 3.3 Колос | N45: 2.3966413 | S45: 259 | T45: А-112/1 | U45: 3.2
B46: 46199 | C46: 622 | D46: 484 | E46: 17 Агролидер | F46: 13180 | G46: 1.5 | L46: 510 | M46: 3.3 Колос | N46: 2.400184 | S46: 260 | T46: А-112 | U46: 3.2
B47: 46200 | C47: (пусто) | D47: 567 | E47: 17 Агролидер | F47: 17680 | G47: 4.6 | H47: Исправить поле | L47: 511 | M47: 3.3 Колос | N47: 2.3523574 | S47: 261 | T47: А-112 | U47: 3.2 | V47: Исправить (уточнить) поле
D48: 568 | E48: 17 Агролидер | F48: 17480 | G48: 4.5 | H48: Исправить поле | L48: 512 | M48: 3.3 Колос | N48: 2.3541288 | S48: 262 | T48: А-112 | U48: 1.1 | V48: Исправить (уточнить) поле
D49: 569 | E49: 17 Агролидер | F49: 18080 | G49: 4.7 | H49: Исправить поле | L49: 513 | M49: 3.3 Колос | N49: 2.4037267 | S49: 263 | T49: А-112 | U49: 3.2 | V49: Исправить (уточнить) поле
D50: 570 | E50: 17 Агролидер | F50: 15140 | G50: 4.4 | H50: Исправить поле | L50: 514 | M50: 3.3 Колос | N50: 2.3063022 | S50: 264 | T50: А-112 | U50: 3 | V50: Исправить (уточнить) поле
D51: 606 | E51: 17 Агролидер | F51: 17420 | G51: 4.5 | H51: Исправить поле | L51: 530 | M51: 3.3 Колос | N51: 2.3045309 | S51: 265 | T51: А-112 | U51: 1.2 | V51: Исправить (уточнить) поле
D52: 607 | E52: 17 Агролидер | F52: 17200 | G52: 4.4 | H52: Исправить поле | L52: 531 | M52: 3.3 Колос | N52: 2.2921314 | S52: 266 | T52: А-112 | U52: 3.1 | V52: Исправить (уточнить) поле
B53: 46201 | C53: (пусто) | D53: 635 | E53: 17 Агролидер | F53: 17500 | G53: 4.5 | H53: Исправить поле | L53: 532 | M53: 3.3 Колос | N53: 2.3966413 | S53: 267 | T53: А-112/1 | U53: 3 | V53: Исправить (уточнить) поле
D54: 597 | E54: 17 Агролидер | F54: 15000 | G54: 3.9 | H54: Исправить поле | L54: 533 | M54: 3.3 Колос | N54: 2.3080736 | S54: 268 | T54: А-112/1 | U54: 3.1
D55: 594 | E55: 17 Агролидер | F55: 16040 | G55: 2.6 | H55: Исправить поле | L55: 534 | M55: 3.3 Колос | N55: 2.3417293 | S55: 269 | T55: А-112/1 | U55: 3
D56: 595 | E56: 17 Агролидер | F56: 16840 | G56: 4.3 | H56: Исправить поле | L56: 535 | M56: 3.3 Колос | N56: 2.3098449 | S56: 273 | T56: А-112/1 | U56: 3
A57: 17 Агролидер Итог | F57: 312260 | G57: 63.5 | H57: Исправить поле | L57: 536 | M57: 3.3 Колос | N57: 2.1433377 | P57: А-112/1 Итог | U57: 40
A58: 18 Агролидер | B58: 46193 | C58: 466 | D58: 349 | E58: 18 Агролидер | F58: 4460 | G58: 1 | H58: Исправить поле | L58: 537 | M58: 3.3 Колос | N58: 2.2726465 | P58: А-114 | Q58: 46191 | R58: Горошек овощной 2026 (богара) | S58: 324 | T58: А-114 | U58: 1.2
B59: 46194 | C59: 472 | D59: 355 | E59: 12 Агролидер | F59: 12650 | G59: 2 | H59: Исправить поле | L59: 538 | M59: 3.3 Колос | N59: 2.3187017 | S59: 326 | T59: А-114 | U59: 2.8
C60: 473 | D60: 356 | E60: 12 Агролидер | F60: 12990 | G60: 2.1 | H60: Исправить поле | L60: 539 | M60: 3.3 Колос | N60: 2.2779606 | P60: А-114 Итог | U60: 4
C61: 474 | D61: 357 | E61: 12 Агролидер | F61: 12770 | G61: 2 | H61: Исправить поле | L61: 540 | M61: 3.3 Колос | N61: 2.2761892 | P61: А-115/1 | Q61: 46190 | R61: Горошек овощной 2026 (богара) | S61: 297 | T61: А-115/1 | U61: 2.2
C62: 477 | D62: 360 | E62: 12 Агролидер | F62: 12810 | G62: 2 | H62: Исправить поле | L62: 541 | M62: 3.3 Колос | N62: 2.2797319 | S62: 298 | T62: А-115/1 | U62: 2.2
C63: 479 | D63: 362 | E63: 12 Агролидер | F63: 12870 | G63: 2 | L63: 542 | M63: 3.3 Колос | N63: 2.254933 | S63: 299 | T63: А-115/1 | U63: 2.2
C64: 481 | D64: 364 | E64: 12 Агролидер | F64: 13050 | G64: 2.1 | K64: 46203 | L64: 543 | M64: 3.3 Колос | N64: 2.2673325 | S64: 300 | T64: А-115/1 | U64: 0.7
C65: 484 | D65: 367 | E65: 12 Агролидер | F65: 13150 | G65: 2.1 | L65: 544 | M65: 3.3 Колос | N65: 2.3275585 | S65: 301 | T65: А-115/1 | U65: 2.2
C66: 486 | D66: 369 | E66: 12 Агролидер | F66: 13190 | G66: 2.1 | L66: 552 | M66: 3.3 Колос | N66: 2.254933 | S66: 302 | T66: А-115/1 | U66: 2.2
C67: 488 | D67: 371 | E67: 12 Агролидер | F67: 8830 | G67: 1.4 | L67: 553 | M67: 3.3 Колос | N67: 2.2567043 | S67: 303 | T67: А-115/1 | U67: 2.1
C68: 491 | D68: 374 | E68: 12 Агролидер | F68: 13190 | G68: 2.1 | L68: 555 | M68: 3.3 Колос | N68: 2.6889146 | S68: 304 | T68: А-115/1 | U68: 0.7
C69: 494 | D69: 377 | E69: 12 Агролидер | F69: 12810 | G69: 2 | L69: 557 | M69: 3.3 Колос | N69: 2.345272 | S69: 308 | T69: А-115/1 | U69: 2.2
C70: 495 | D70: 378 | E70: 12 Агролидер | F70: 12750 | G70: 2 | J70: 3.3 Колос Итог | N70: 102.4 | S70: 309 | T70: А-115/1 | U70: 2.2
C71: 497 | D71: 380 | E71: 12 Агролидер | F71: 12790 | G71: 2 | J71: 3.6 Колос | K71: 46203 | L71: 558 | M71: 2.2 Колос | N71: 2.5725528 | S71: 311 | T71: А-115/1 | U71: 2.2
C72: 500 | D72: 382 | E72: 12 Агролидер | F72: 12890 | G72: 2 | L72: 561 | M72: 3.6 Колос | N72: 2.5351066 | Q72: 46191 | R72: Горошек овощной 2026 (богара) | S72: 312 | T72: А-115/1 | U72: 2.1
C73: 501 | D73: 383 | E73: 12 Агролидер | F73: 12670 | G73: 2 | L73: 562 | M73: 3.6 Колос | N73: 2.3291526 | S73: 313 | T73: А-115/1 | U73: 2
C74: 502 | D74: 384 | E74: 12 Агролидер | F74: 12830 | G74: 2 | L74: 564 | M74: 3.6 Колос | N74: 2.1662617 | S74: 316 | T74: А-115/1 | U74: 2.1
B75: 46195 | C75: 515 | D75: 393 | E75: 18 Агролидер | F75: 13260 | G75: 1.8 | K75: 46207 | L75: 663 | M75: 3.6 Колос | N75: 1.3836365 | S75: 317 | T75: А-115 | U75: 0.7
C76: 516 | D76: 394 | E76: 18 Агролидер | F76: 13090 | G76: 1.8 | L76: 668 | M76: 3.6 Колос | N76: 0.57292661 | S76: 318 | T76: А-115/1 | U76: 2.1 | V76: Исправить (уточнить) поле в АВК? Взвешивание загрузилось верно
C77: 517 | D77: 395 | E77: 18 Агролидер | F77: 13440 | G77: 1.8 | K77: 46208 | L77: 694 | M77: 3.6 Колос | N77: 2.4208958 | S77: 319 | T77: А-115/1 | U77: 2.1
C78: 520 | D78: 398 | E78: 18 Агролидер | F78: 13330 | G78: 1.8 | L78: 691 | M78: 3.6 Колос | N78: 2.5107666 | S78: 320 | T78: А-115/1 | U78: 2
C79: 521 | D79: 399 | E79: 18 Агролидер | F79: 13200 | G79: 1.8 | L79: 692 | M79: 3.6 Колос | N79: 2.4171512 | S79: 321 | T79: А-115/1 | U79: 2.1
C80: 522 | D80: 400 | E80: 18 Агролидер | F80: 13090 | G80: 1.8 | H80: Исправить поле | L80: 697 | M80: 3.6 Колос | N80: 2.5032774 | S80: 322 | T80: А-115/1 | U80: 0.7
C81: 524 | D81: 402 | E81: 18 Агролидер | F81: 12870 | G81: 1.7 | H81: Исправить поле | L81: 698 | M81: 3.6 Колос | N81: 2.4976604 | S81: 323 | T81: А-115/1 | U81: 2.1
C82: 525 | D82: 405 | E82: 18 Агролидер | F82: 12800 | G82: 1.7 | H82: Исправить поле | L82: 700 | M82: 3.6 Колос | N82: 2.4751927 | S82: 325 | T82: А-115/1 | U82: 1.5
C83: 527 | D83: 404 | E83: 18 Агролидер | F83: 12810 | G83: 1.7 | H83: Исправить поле | K83: 46209 | L83: 659 | M83: 3.6 Колос | N83: 2.4733204 | S83: 328 | T83: А-115/1 | U83: 2
C84: 528 | D84: 406 | E84: 18 Агролидер | F84: 12780 | G84: 1.7 | H84: Исправить поле | L84: 677 | M84: 3.6 Колос | N84: 2.3366419 | S84: 329 | T84: А-115 | U84: 2
C85: 529 | D85: 407 | E85: 18 Агролидер | F85: 12960 | G85: 1.7 | H85: Исправить поле | L85: 680 | M85: 3.6 Колос | N85: 2.4208958 | S85: 330 | T85: А-115/1 | U85: 2 | V85: Исправить (уточнить) поле в АВК? Взвешивание загрузилось верно
C86: 531 | D86: 409 | E86: 18 Агролидер | F86: 13070 | G86: 1.8 | H86: Исправить поле | L86: 681 | M86: 3.6 Колос | N86: 2.4452358 | S86: 331 | T86: А-115/1 | U86: 0.7
B87: 46196 | C87: 532 | D87: 410 | E87: 18 Агролидер | F87: 13130 | G87: 2 | H87: Исправить поле | L87: 683 | M87: 3.6 Колос | N87: 2.4190235 | S87: 332 | T87: А-115/1 | U87: 2.1
C88: 535 | D88: 412 | E88: 18 Агролидер | F88: 13290 | G88: 2 | H88: Исправить поле | L88: 686 | M88: 3.6 Колос | N88: 2.531362 | S88: 333 | T88: А-115 | U88: 2
C89: 536 | D89: 413 | E89: 18 Агролидер | F89: 13230 | G89: 2 | H89: Исправить поле | L89: 687 | M89: 3.6 Колос | N89: 2.5182558 | S89: 334 | T89: А-115 | U89: 2 | V89: Исправить (уточнить) поле в АВК? Взвешивание загрузилось верно
C90: 538 | D90: 415 | E90: 18 Агролидер | F90: 13140 | G90: 2 | H90: Исправить поле | L90: 701 | M90: 3.6 Колос | N90: 2.8908454 | S90: 335 | T90: А-115/1 | U90: 0.6 | V90: Исправить (уточнить) поле в АВК? Взвешивание загрузилось верно
C91: 539 | D91: 416 | E91: 18 Агролидер | F91: 13230 | G91: 2 | H91: Исправить поле | L91: 704 | M91: 3.6 Колос | N91: 2.3291526 | S91: 336 | T91: А-115/1 | U91: 2
B92: 46198 | C92: (пусто) | D92: 632 | E92: 17 Агролидер | F92: 13220 | G92: 2 | H92: Исправить поле | L92: 706 | M92: 3.6 Колос | N92: 2.3815773 | S92: 337 | T92: А-115/1 | U92: 2
D93: 633 | E93: 17 Агролидер | F93: 13560 | G93: 2.1 | H93: Исправить поле | L93: 707 | M93: 3.6 Колос | N93: 2.458342 | S93: 338 | T93: А-115/1 | U93: 2.1
B94: 46199 | C94: 619 | D94: 482 | E94: 17 Агролидер | F94: 13250 | G94: 3.4 | H94: Исправить поле | L94: 709 | M94: 3.6 Колос | N94: 2.5107666 | Q94: 46192 | R94: Горошек овощной 2026 (богара) | S94: 339 | T94: А-115 | U94: 2.9
C95: 624 | D95: 485 | E95: 17 Агролидер | F95: 13030 | G95: 3.4 | H95: Исправить поле | J95: 3.6 Колос Итог | N95: 56.1 | P95: А-115/1 Итог | U95: 63 | V95: Исправить (уточнить) поле в АВК? Взвешивание загрузилось верно
C96: 629 | D96: 488 | E96: 17 Агролидер | F96: 13180 | G96: 3.4 | J96: 3.1 Колос | K96: 46204 | L96: 578 | M96: 3.1 Колос | N96: 2.8 | P96: А-22/1 | Q96: 46179 | R96: Горошек овощной 2026 (богара) | S96: 37 | T96: А-22/1 | U96: 1.8
C97: 631 | D97: 489 | E97: 17 Агролидер | F97: 13020 | G97: 3.4 | L97: 582 | M97: 3.1 Колос | N97: 2.8 | S97: 41 | T97: А-22/1 | U97: 3.2
C98: 632 | D98: 490 | E98: 17 Агролидер | F98: 13370 | G98: 3.4 | L98: 583 | M98: 3.1 Колос | N98: 2.8 | Q98: 46182 | R98: Горошек овощной 2026 (богара) | S98: 104 | T98: А-22/1 | U98: 2
C99: 634 | D99: 491 | E99: 17 Агролидер | F99: 13240 | G99: 3.5 | L99: 584 | M99: 3.1 Колос | N99: 2.8 | S99: 105 | T99: А-22/1 | U99: 0.7
C100: 635 | D100: 492 | E100: 17 Агролидер | F100: 12990 | G100: 3.4 | L100: 586 | M100: 3.1 Колос | N100: 2.8 | S100: 106 | T100: А-22 | U100: 1.9
C101: (пусто) | D101: 634 | E101: 17 Агролидер | F101: 13200 | G101: 3.4 | L101: 588 | M101: 3.1 Колос | N101: 2.7 | S101: 107 | T101: А-22 | U101: 2
...

Sheet Реестр уборки 2026
A1: Показатель | B1: Количество | C1: Значение финометра | D1: Регистратор.Номер | E1: Регистратор.Дата | F1: Регистратор.Вес брутто | G1: Регистратор.Вес нетто | H1: Регистратор.Вес тары | I1: Регистратор.Вес чистый | J1: Культура акт | K1: Сорт акт | L1: Поле акт | M1: Регистратор.Водитель | N1: Регистратор.Время прибытия | O1: Регистратор.Время убытия | P1: Регистратор.Комбайнеры.Комбайнер.Наименование | Q1: Регистратор.Номера талонов | R1: Регистратор.Номер машины | S1: Регистратор.Номер прицепа | T1: Поле | U1: Сорт уточн | V1: Площадь уборки, га | W1: Культура | X1: Орошение | Y1: Смена | Z1: Дата отчета | AA1: Продажа | AB1: Примечание | AC1: Финометр | AD1: Характеристика | AE1: № акта | AF1: Дата акта | AG1: Вх № | AH1: Степень зрелости вспом | AJ1: № акта | AK1: Дата акта | AL1: Регистратор.Номер | AM1: Регистратор.Дата | AN1: Регистратор.Вес брутто | AO1: Регистратор.Вес нетто | AP1: Регистратор.Вес чистый | AQ1: Культура акт 8 | AR1: Сорт акт 9 | AS1: Поле акт 10 | AT1: Регистратор.Водитель | AU1: Регистратор.Время прибытия | AV1: Регистратор.Номер машины | AW1: Регистратор.Номер прицепа | AX1: Поле 15 | AY1: Сорт уточн 16 | AZ1: Площадь уборки, га 17 | BA1: Культура 18 | BB1: Орошение 19 | BC1: Смена 20 | BD1: Дата отчета 21 | BE1: Продажа | BF1: Примечание 23 | BG1: Финометр | BH1: Характеристика | BI1: Вх № | BJ1: Степень зрелости вспом
A2: Степень зрелости | C2: =Таблица3[[#This Row],[Степень зрелости вспом]] -> 49 | D2: 40 | G2: 16070 | I2: 12936.4 | J2: Горошек овощной 2026 (богара) | K2: Тиара | L2: А-4/1 | M2: Богучарский А. И. | R2: А718ВХ | T2: =VLOOKUP(Таблица3[[#This Row],[№ акта]],$AJ$1:$BJ$691,15,FALSE) -> А-4/1 | U2: =VLOOKUP(Таблица3[[#This Row],[№ акта]],$AJ$1:$BJ$691,16,FALSE) -> Тиара | V2: =VLOOKUP(Таблица3[[#This Row],[№ акта]],$AJ$1:$BJ$691,17,FALSE) -> 3 | W2: =VLOOKUP(Таблица3[[#This Row],[№ акта]],$AJ$1:$BJ$691,18,FALSE) -> ГРК (богара) | X2: =VLOOKUP(Таблица3[[#This Row],[№ акта]],$AJ$1:$BJ$691,19,FALSE) -> богара | Y2: =VLOOKUP(Таблица3[[#This Row],[№ акта]],$AJ$1:$BJ$691,20,FALSE) -> 1 | Z2: =VLOOKUP(Таблица3[[#This Row],[№ акта]],$AJ$1:$BJ$691,21,FALSE) -> 46176 | AB2: =IF(VLOOKUP(Таблица3[[#This Row],[№ акта]],$AJ$1:$BJ$691,23,FALSE)<>0,VLOOKUP(Таблица3[[#This Row],[№ акта]],$AJ$1:$BJ$691,23,FALSE),"-") -> - | AC2: =IF(Таблица3[[#This Row],[Степень зрелости вспом]]=0,"нет данных",IF(Таблица3[[#This Row],[Степень зрелости вспом]]<40,"до 40",IF(Таблица3[[#This Row],[Степень зрелости вспом]]<53,"40-52",IF(Таблица3[[#This Row],[Степень зрелости вспом]]<64,"53-63",IF(Таблица3[[#This Row],[Степень зрелости вспом]]<67,"64-66",IF(Таблица3[[#This Row],[Степень зрелости вспом]]<85,"67-85",)))))) -> 40-52 | AD2: Высший | AE2: 14 | AF2: 46176 | AG2: 1 | AH2: =IFERROR(VLOOKUP(Таблица3[[#This Row],[№ акта]],'Степень зрелости 2026'!$H$12:$I$800,2,FALSE),) -> 49 | AJ2: 14 | AK2: 46176 | AL2: 40 | AO2: 16070 | AP2: 12936.4 | AQ2: Горошек овощной 2026 (богара) | AR2: Тиара | AS2: А-4/1 | AT2: Богучарский А. И. | AV2: А718ВХ | AX2: А-4/1 | AY2: Тиара | AZ2: 3 | BA2: ГРК (богара) | BB2: богара | BC2: 1 | BD2: 46176 | BG2: 40-52 | BH2: Высший | BI2: 1 | BJ2: 49
A3: Степень зрелости | C3: =Таблица3[[#This Row],[Степень зрелости вспом]] -> 53 | D3: 42 | G3: 13670 | I3: 9637.4 | J3: Горошек овощной 2026 (богара) | K3: Тиара | L3: А-4/1 | M3: Сероштан Станислав Викторович | R3: Е758РЕ | T3: =VLOOKUP(Таблица3[[#This Row],[№ акта]],$AJ$1:$BJ$691,15,FALSE) -> А-4/1 | U3: =VLOOKUP(Таблица3[[#This Row],[№ акта]],$AJ$1:$BJ$691,16,FALSE) -> Тиара | V3: =VLOOKUP(Таблица3[[#This Row],[№ акта]],$AJ$1:$BJ$691,17,FALSE) -> 2.6 | W3: =VLOOKUP(Таблица3[[#This Row],[№ акта]],$AJ$1:$BJ$691,18,FALSE) -> ГРК (богара) | X3: =VLOOKUP(Таблица3[[#This Row],[№ акта]],$AJ$1:$BJ$691,19,FALSE) -> богара | Y3: =VLOOKUP(Таблица3[[#This Row],[№ акта]],$AJ$1:$BJ$691,20,FALSE) -> 1 | Z3: =VLOOKUP(Таблица3[[#This Row],[№ акта]],$AJ$1:$BJ$691,21,FALSE) -> 46176 | AB3: =IF(VLOOKUP(Таблица3[[#This Row],[№ акта]],$AJ$1:$BJ$691,23,FALSE)<>0,VLOOKUP(Таблица3[[#This Row],[№ акта]],$AJ$1:$BJ$691,23,FALSE),"-") -> - | AC3: =IF(Таблица3[[#This Row],[Степень зрелости вспом]]=0,"нет данных",IF(Таблица3[[#This Row],[Степень зрелости вспом]]<40,"до 40",IF(Таблица3[[#This Row],[Степень зрелости вспом]]<53,"40-52",IF(Таблица3[[#This Row],[Степень зрелости вспом]]<64,"53-63",IF(Таблица3[[#This Row],[Степень зрелости вспом]]<67,"64-66",IF(Таблица3[[#This Row],[Степень зрелости вспом]]<85,"67-85",)))))) -> 53-63 | AD3: Высший | AE3: 15 | AF3: 46176 | AG3: 2 | AH3: =IFERROR(VLOOKUP(Таблица3[[#This Row],[№ акта]],'Степень зрелости 2026'!$H$12:$I$800,2,FALSE),) -> 53 | AJ3: 15 | AK3: 46176 | AL3: 42 | AO3: 13670 | AP3: 9637.4 | AQ3: Горошек овощной 2026 (богара) | AR3: Тиара | AS3: А-4/1 | AT3: Сероштан Станислав Викторович | AV3: Е758РЕ | AX3: А-4/1 | AY3: Тиара | AZ3: 2.6 | BA3: ГРК (богара) | BB3: богара | BC3: 1 | BD3: 46176 | BG3: 53-63 | BH3: Высший | BI3: 2 | BJ3: 53
A4: Степень зрелости | C4: =Таблица3[[#This Row],[Степень зрелости вспом]] -> 50 | D4: 43 | G4: 13610 | I4: 10683.9 | J4: Горошек овощной 2026 (богара) | K4: Тиара | L4: А-4/1 | M4: Богучарский А. И. | R4: А718ВХ | T4: =VLOOKUP(Таблица3[[#This Row],[№ акта]],$AJ$1:$BJ$691,15,FALSE) -> А-4/1 | U4: =VLOOKUP(Таблица3[[#This Row],[№ акта]],$AJ$1:$BJ$691,16,FALSE) -> Тиара | V4: =VLOOKUP(Таблица3[[#This Row],[№ акта]],$AJ$1:$BJ$691,17,FALSE) -> 2.6 | W4: =VLOOKUP(Таблица3[[#This Row],[№ акта]],$AJ$1:$BJ$691,18,FALSE) -> ГРК (богара) | X4: =VLOOKUP(Таблица3[[#This Row],[№ акта]],$AJ$1:$BJ$691,19,FALSE) -> богара | Y4: =VLOOKUP(Таблица3[[#This Row],[№ акта]],$AJ$1:$BJ$691,20,FALSE) -> 1 | Z4: =VLOOKUP(Таблица3[[#This Row],[№ акта]],$AJ$1:$BJ$691,21,FALSE) -> 46176 | AB4: =IF(VLOOKUP(Таблица3[[#This Row],[№ акта]],$AJ$1:$BJ$691,23,FALSE)<>0,VLOOKUP(Таблица3[[#This Row],[№ акта]],$AJ$1:$BJ$691,23,FALSE),"-") -> - | AC4: =IF(Таблица3[[#This Row],[Степень зрелости вспом]]=0,"нет данных",IF(Таблица3[[#This Row],[Степень зрелости вспом]]<40,"до 40",IF(Таблица3[[#This Row],[Степень зрелости вспом]]<53,"40-52",IF(Таблица3[[#This Row],[Степень зрелости вспом]]<64,"53-63",IF(Таблица3[[#This Row],[Степень зрелости вспом]]<67,"64-66",IF(Таблица3[[#This Row],[Степень зрелости вспом]]<85,"67-85",)))))) -> 40-52 | AD4: Высший | AE4: 16 | AF4: 46176 | AG4: 3 | AH4: =IFERROR(VLOOKUP(Таблица3[[#This Row],[№ акта]],'Степень зрелости 2026'!$H$12:$I$800,2,FALSE),) -> 50 | AJ4: 16 | AK4: 46176 | AL4: 43 | AO4: 13610 | AP4: 10683.9 | AQ4: Горошек овощной 2026 (богара) | AR4: Тиара | AS4: А-4/1 | AT4: Богучарский А. И. | AV4: А718ВХ | AX4: А-4/1 | AY4: Тиара | AZ4: 2.6 | BA4: ГРК (богара) | BB4: богара | BC4: 1 | BD4: 46176 | BG4: 40-52 | BH4: Высший | BI4: 3 | BJ4: 50
A5: Степень зрелости | C5: =Таблица3[[#This Row],[Степень зрелости вспом]] -> 54 | D5: 48 | G5: 13740 | I5: 10648.5 | J5: Горошек овощной 2026 (богара) | K5: Тиара | L5: А-4/1 | M5: Кудря Евгений | R5: А719ОО | T5: =VLOOKUP(Таблица3[[#This Row],[№ акта]],$AJ$1:$BJ$691,15,FALSE) -> А-4/1 | U5: =VLOOKUP(Таблица3[[#This Row],[№ акта]],$AJ$1:$BJ$691,16,FALSE) -> Тиара | V5: =VLOOKUP(Таблица3[[#This Row],[№ акта]],$AJ$1:$BJ$691,17,FALSE) -> 2.6 | W5: =VLOOKUP(Таблица3[[#This Row],[№ акта]],$AJ$1:$BJ$691,18,FALSE) -> ГРК (богара) | X5: =VLOOKUP(Таблица3[[#This Row],[№ акта]],$AJ$1:$BJ$691,19,FALSE) -> богара | Y5: =VLOOKUP(Таблица3[[#This Row],[№ акта]],$AJ$1:$BJ$691,20,FALSE) -> 1 | Z5: =VLOOKUP(Таблица3[[#This Row],[№ акта]],$AJ$1:$BJ$691,21,FALSE) -> 46176 | AB5: =IF(VLOOKUP(Таблица3[[#This Row],[№ акта]],$AJ$1:$BJ$691,23,FALSE)<>0,VLOOKUP(Таблица3[[#This Row],[№ акта]],$AJ$1:$BJ$691,23,FALSE),"-") -> - | AC5: =IF(Таблица3[[#This Row],[Степень зрелости вспом]]=0,"нет данных",IF(Таблица3[[#This Row],[Степень зрелости вспом]]<40,"до 40",IF(Таблица3[[#This Row],[Степень зрелости вспом]]<53,"40-52",IF(Таблица3[[#This Row],[Степень зрелости вспом]]<64,"53-63",IF(Таблица3[[#This Row],[Степень зрелости вспом]]<67,"64-66",IF(Таблица3[[#This Row],[Степень зрелости вспом]]<85,"67-85",)))))) -> 53-63 | AD5: Высший | AE5: 17 | AF5: 46176 | AG5: 4 | AH5: =IFERROR(VLOOKUP(Таблица3[[#This Row],[№ акта]],'Степень зрелости 2026'!$H$12:$I$800,2,FALSE),) -> 54 | AJ5: 17 | AK5: 46176 | AL5: 48 | AO5: 13740 | AP5: 10648.5 | AQ5: Горошек овощной 2026 (богара) | AR5: Тиара | AS5: А-4/1 | AT5: Кудря Евгений | AV5: А719ОО | AX5: А-4/1 | AY5: Тиара | AZ5: 2.6 | BA5: ГРК (богара) | BB5: богара | BC5: 1 | BD5: 46176 | BG5: 53-63 | BH5: Высший | BI5: 4 | BJ5: 54
A6: Степень зрелости | C6: =Таблица3[[#This Row],[Степень зрелости вспом]] -> 53 | D6: 49 | G6: 13660 | I6: 10996.3 | J6: Горошек овощной 2026 (богара) | K6: Тиара | L6: А-4/1 | M6: Богучарский А. И. | R6: А718ВХ | T6: =VLOOKUP(Таблица3[[#This Row],[№ акта]],$AJ$1:$BJ$691,15,FALSE) -> А-4/1 | U6: =VLOOKUP(Таблица3[[#This Row],[№ акта]],$AJ$1:$BJ$691,16,FALSE) -> Тиара | V6: =VLOOKUP(Таблица3[[#This Row],[№ акта]],$AJ$1:$BJ$691,17,FALSE) -> 2.6 | W6: =VLOOKUP(Таблица3[[#This Row],[№ акта]],$AJ$1:$BJ$691,18,FALSE) -> ГРК (богара) | X6: =VLOOKUP(Таблица3[[#This Row],[№ акта]],$AJ$1:$BJ$691,19,FALSE) -> богара | Y6: =VLOOKUP(Таблица3[[#This Row],[№ акта]],$AJ$1:$BJ$691,20,FALSE) -> 1 | Z6: =VLOOKUP(Таблица3[[#This Row],[№ акта]],$AJ$1:$BJ$691,21,FALSE) -> 46176 | AB6: =IF(VLOOKUP(Таблица3[[#This Row],[№ акта]],$AJ$1:$BJ$691,23,FALSE)<>0,VLOOKUP(Таблица3[[#This Row],[№ акта]],$AJ$1:$BJ$691,23,FALSE),"-") -> - | AC6: =IF(Таблица3[[#This Row],[Степень зрелости вспом]]=0,"нет данных",IF(Таблица3[[#This Row],[Степень зрелости вспом]]<40,"до 40",IF(Таблица3[[#This Row],[Степень зрелости вспом]]<53,"40-52",IF(Таблица3[[#This Row],[Степень зрелости вспом]]<64,"53-63",IF(Таблица3[[#This Row],[Степень зрелости вспом]]<67,"64-66",IF(Таблица3[[#This Row],[Степень зрелости вспом]]<85,"67-85",)))))) -> 53-63 | AD6: Высший | AE6: 18 | AF6: 46176 | AG6: 5 | AH6: =IFERROR(VLOOKUP(Таблица3[[#This Row],[№ акта]],'Степень зрелости 2026'!$H$12:$I$800,2,FALSE),) -> 53 | AJ6: 18 | AK6: 46176 | AL6: 49 | AO6: 13660 | AP6: 10996.3 | AQ6: Горошек овощной 2026 (богара) | AR6: Тиара | AS6: А-4/1 | AT6: Богучарский А. И. | AV6: А718ВХ | AX6: А-4/1 | AY6: Тиара | AZ6: 2.6 | BA6: ГРК (богара) | BB6: богара | BC6: 1 | BD6: 46176 | BG6: 53-63 | BH6: Высший | BI6: 5 | BJ6: 53
A7: Степень зрелости | C7: =Таблица3[[#This Row],[Степень зрелости вспом]] -> 53 | D7: 50 | G7: 13390 | I7: 10645.1 | J7: Горошек овощной 2026 (богара) | K7: Тиара | L7: А-4/1 | M7: Черевко Александр Владимирович | R7: А114МК | T7: =VLOOKUP(Таблица3[[#This Row],[№ акта]],$AJ$1:$BJ$691,15,FALSE) -> А-4/1 | U7: =VLOOKUP(Таблица3[[#This Row],[№ акта]],$AJ$1:$BJ$691,16,FALSE) -> Тиара | V7: =VLOOKUP(Таблица3[[#This Row],[№ акта]],$AJ$1:$BJ$691,17,FALSE) -> 2.5 | W7: =VLOOKUP(Таблица3[[#This Row],[№ акта]],$AJ$1:$BJ$691,18,FALSE) -> ГРК (богара) | X7: =VLOOKUP(Таблица3[[#This Row],[№ акта]],$AJ$1:$BJ$691,19,FALSE) -> богара | Y7: =VLOOKUP(Таблица3[[#This Row],[№ акта]],$AJ$1:$BJ$691,20,FALSE) -> 1 | Z7: =VLOOKUP(Таблица3[[#This Row],[№ акта]],$AJ$1:$BJ$691,21,FALSE) -> 46176 | AB7: =IF(VLOOKUP(Таблица3[[#This Row],[№ акта]],$AJ$1:$BJ$691,23,FALSE)<>0,VLOOKUP(Таблица3[[#This Row],[№ акта]],$AJ$1:$BJ$691,23,FALSE),"-") -> - | AC7: =IF(Таблица3[[#This Row],[Степень зрелости вспом]]=0,"нет данных",IF(Таблица3[[#This Row],[Степень зрелости вспом]]<40,"до 40",IF(Таблица3[[#This Row],[Степень зрелости вспом]]<53,"40-52",IF(Таблица3[[#This Row],[Степень зрелости вспом]]<64,"53-63",IF(Таблица3[[#This Row],[Степень зрелости вспом]]<67,"64-66",IF(Таблица3[[#This Row],[Степень зрелости вспом]]<85,"67-85",)))))) -> 53-63 | AD7: Высший | AE7: 19 | AF7: 46176 | AG7: 6 | AH7: =IFERROR(VLOOKUP(Таблица3[[#This Row],[№ акта]],'Степень зрелости 2026'!$H$12:$I$800,2,FALSE),) -> 53 | AJ7: 19 | AK7: 46176 | AL7: 50 | AO7: 13390 | AP7: 10645.1 | AQ7: Горошек овощной 2026 (богара) | AR7: Тиара | AS7: А-4/1 | AT7: Черевко Александр Владимирович | AV7: А114МК | AX7: А-4/1 | AY7: Тиара | AZ7: 2.5 | BA7: ГРК (богара) | BB7: богара | BC7: 1 | BD7: 46176 | BG7: 53-63 | BH7: Высший | BI7: 6 | BJ7: 53
A8: Степень зрелости | C8: =Таблица3[[#This Row],[Степень зрелости вспом]] -> 52 | D8: 51 | G8: 13720 | I8: 10907.4 | J8: Горошек овощной 2026 (богара) | K8: Тиара | L8: А-4/1 | M8: Кудря Евгений | R8: А719ОО | T8: =VLOOKUP(Таблица3[[#This Row],[№ акта]],$AJ$1:$BJ$691,15,FALSE) -> А-4/1 | U8: =VLOOKUP(Таблица3[[#This Row],[№ акта]],$AJ$1:$BJ$691,16,FALSE) -> Тиара | V8: =VLOOKUP(Таблица3[[#This Row],[№ акта]],$AJ$1:$BJ$691,17,FALSE) -> 2.6 | W8: =VLOOKUP(Таблица3[[#This Row],[№ акта]],$AJ$1:$BJ$691,18,FALSE) -> ГРК (богара) | X8: =VLOOKUP(Таблица3[[#This Row],[№ акта]],$AJ$1:$BJ$691,19,FALSE) -> богара | Y8: =VLOOKUP(Таблица3[[#This Row],[№ акта]],$AJ$1:$BJ$691,20,FALSE) -> 1 | Z8: =VLOOKUP(Таблица3[[#This Row],[№ акта]],$AJ$1:$BJ$691,21,FALSE) -> 46176 | AB8: =IF(VLOOKUP(Таблица3[[#This Row],[№ акта]],$AJ$1:$BJ$691,23,FALSE)<>0,VLOOKUP(Таблица3[[#This Row],[№ акта]],$AJ$1:$BJ$691,23,FALSE),"-") -> - | AC8: =IF(Таблица3[[#This Row],[Степень зрелости вспом]]=0,"нет данных",IF(Таблица3[[#This Row],[Степень зрелости вспом]]<40,"до 40",IF(Таблица3[[#This Row],[Степень зрелости вспом]]<53,"40-52",IF(Таблица3[[#This Row],[Степень зрелости вспом]]<64,"53-63",IF(Таблица3[[#This Row],[Степень зрелости вспом]]<67,"64-66",IF(Таблица3[[#This Row],[Степень зрелости вспом]]<85,"67-85",)))))) -> 40-52 | AD8: Высший | AE8: 20 | AF8: 46176 | AG8: 7 | AH8: =IFERROR(VLOOKUP(Таблица3[[#This Row],[№ акта]],'Степень зрелости 2026'!$H$12:$I$800,2,FALSE),) -> 52 | AJ8: 20 | AK8: 46176 | AL8: 51 | AO8: 13720 | AP8: 10907.4 | AQ8: Горошек овощной 2026 (богара) | AR8: Тиара | AS8: А-4/1 | AT8: Кудря Евгений | AV8: А719ОО | AX8: А-4/1 | AY8: Тиара | AZ8: 2.6 | BA8: ГРК (богара) | BB8: богара | BC8: 1 | BD8: 46176 | BG8: 40-52 | BH8: Высший | BI8: 7 | BJ8: 52
A9: Степень зрелости | C9: =Таблица3[[#This Row],[Степень зрелости вспом]] -> 52 | D9: 52 | G9: 13740 | I9: 11060.7 | J9: Горошек овощной 2026 (богара) | K9: Тиара | L9: А-4/1 | M9: Богучарский А. И. | R9: А718ВХ | T9: =VLOOKUP(Таблица3[[#This Row],[№ акта]],$AJ$1:$BJ$691,15,FALSE) -> А-4/1 | U9: =VLOOKUP(Таблица3[[#This Row],[№ акта]],$AJ$1:$BJ$691,16,FALSE) -> Тиара | V9: =VLOOKUP(Таблица3[[#This Row],[№ акта]],$AJ$1:$BJ$691,17,FALSE) -> 2.6 | W9: =VLOOKUP(Таблица3[[#This Row],[№ акта]],$AJ$1:$BJ$691,18,FALSE) -> ГРК (богара) | X9: =VLOOKUP(Таблица3[[#This Row],[№ акта]],$AJ$1:$BJ$691,19,FALSE) -> богара | Y9: =VLOOKUP(Таблица3[[#This Row],[№ акта]],$AJ$1:$BJ$691,20,FALSE) -> 1 | Z9: =VLOOKUP(Таблица3[[#This Row],[№ акта]],$AJ$1:$BJ$691,21,FALSE) -> 46176 | AB9: =IF(VLOOKUP(Таблица3[[#This Row],[№ акта]],$AJ$1:$BJ$691,23,FALSE)<>0,VLOOKUP(Таблица3[[#This Row],[№ акта]],$AJ$1:$BJ$691,23,FALSE),"-") -> - | AC9: =IF(Таблица3[[#This Row],[Степень зрелости вспом]]=0,"нет данных",IF(Таблица3[[#This Row],[Степень зрелости вспом]]<40,"до 40",IF(Таблица3[[#This Row],[Степень зрелости вспом]]<53,"40-52",IF(Таблица3[[#This Row],[Степень зрелости вспом]]<64,"53-63",IF(Таблица3[[#This Row],[Степень зрелости вспом]]<67,"64-66",IF(Таблица3[[#This Row],[Степень зрелости вспом]]<85,"67-85",)))))) -> 40-52 | AD9: Высший | AE9: 21 | AF9: 46176 | AG9: 8 | AH9: =IFERROR(VLOOKUP(Таблица3[[#This Row],[№ акта]],'Степень зрелости 2026'!$H$12:$I$800,2,FALSE),) -> 52 | AJ9: 21 | AK9: 46176 | AL9: 52 | AO9: 13740 | AP9: 11060.7 | AQ9: Горошек овощной 2026 (богара) | AR9: Тиара | AS9: А-4/1 | AT9: Богучарский А. И. | AV9: А718ВХ | AX9: А-4/1 | AY9: Тиара | AZ9: 2.6 | BA9: ГРК (богара) | BB9: богара | BC9: 1 | BD9: 46176 | BG9: 40-52 | BH9: Высший | BI9: 8 | BJ9: 52
A10: Степень зрелости | C10: =Таблица3[[#This Row],[Степень зрелости вспом]] -> 51 | D10: 53 | G10: 13260 | I10: 10674.3 | J10: Горошек овощной 2026 (богара) | K10: Тиара | L10: А-4/1 | M10: Черевко Александр Владимирович | R10: А114МК | T10: =VLOOKUP(Таблица3[[#This Row],[№ акта]],$AJ$1:$BJ$691,15,FALSE) -> А-4/1 | U10: =VLOOKUP(Таблица3[[#This Row],[№ акта]],$AJ$1:$BJ$691,16,FALSE) -> Тиара | V10: =VLOOKUP(Таблица3[[#This Row],[№ акта]],$AJ$1:$BJ$691,17,FALSE) -> 2.5 | W10: =VLOOKUP(Таблица3[[#This Row],[№ акта]],$AJ$1:$BJ$691,18,FALSE) -> ГРК (богара) | X10: =VLOOKUP(Таблица3[[#This Row],[№ акта]],$AJ$1:$BJ$691,19,FALSE) -> богара | Y10: =VLOOKUP(Таблица3[[#This Row],[№ акта]],$AJ$1:$BJ$691,20,FALSE) -> 1 | Z10: =VLOOKUP(Таблица3[[#This Row],[№ акта]],$AJ$1:$BJ$691,21,FALSE) -> 46176 | AB10: =IF(VLOOKUP(Таблица3[[#This Row],[№ акта]],$AJ$1:$BJ$691,23,FALSE)<>0,VLOOKUP(Таблица3[[#This Row],[№ акта]],$AJ$1:$BJ$691,23,FALSE),"-") -> - | AC10: =IF(Таблица3[[#This Row],[Степень зрелости вспом]]=0,"нет данных",IF(Таблица3[[#This Row],[Степень зрелости вспом]]<40,"до 40",IF(Таблица3[[#This Row],[Степень зрелости вспом]]<53,"40-52",IF(Таблица3[[#This Row],[Степень зрелости вспом]]<64,"53-63",IF(Таблица3[[#This Row],[Степень зрелости вспом]]<67,"64-66",IF(Таблица3[[#This Row],[Степень зрелости вспом]]<85,"67-85",)))))) -> 40-52 | AD10: Высший | AE10: 22 | AF10: 46177 | AG10: 9 | AH10: =IFERROR(VLOOKUP(Таблица3[[#This Row],[№ акта]],'Степень зрелости 2026'!$H$12:$I$800,2,FALSE),) -> 51 | AJ10: 22 | AK10: 46177 | AL10: 53 | AO10: 13260 | AP10: 10674.3 | AQ10: Горошек овощной 2026 (богара) | AR10: Тиара | AS10: А-4/1 | AT10: Черевко Александр Владимирович | AV10: А114МК | AX10: А-4/1 | AY10: Тиара | AZ10: 2.5 | BA10: ГРК (богара) | BB10: богара | BC10: 1 | BD10: 46176 | BG10: 40-52 | BH10: Высший | BI10: 9 | BJ10: 51
A11: Степень зрелости | C11: =Таблица3[[#This Row],[Степень зрелости вспом]] -> 53 | D11: 54 | G11: 13390 | I11: 10779 | J11: Горошек овощной 2026 (богара) | K11: Тиара | L11: А-4/1 | M11: Кудря Евгений | R11: А719ОО | T11: =VLOOKUP(Таблица3[[#This Row],[№ акта]],$AJ$1:$BJ$691,15,FALSE) -> А-4/1 | U11: =VLOOKUP(Таблица3[[#This Row],[№ акта]],$AJ$1:$BJ$691,16,FALSE) -> Тиара | V11: =VLOOKUP(Таблица3[[#This Row],[№ акта]],$AJ$1:$BJ$691,17,FALSE) -> 2.5 | W11: =VLOOKUP(Таблица3[[#This Row],[№ акта]],$AJ$1:$BJ$691,18,FALSE) -> ГРК (богара) | X11: =VLOOKUP(Таблица3[[#This Row],[№ акта]],$AJ$1:$BJ$691,19,FALSE) -> богара | Y11: =VLOOKUP(Таблица3[[#This Row],[№ акта]],$AJ$1:$BJ$691,20,FALSE) -> 1 | Z11: =VLOOKUP(Таблица3[[#This Row],[№ акта]],$AJ$1:$BJ$691,21,FALSE) -> 46176 | AB11: =IF(VLOOKUP(Таблица3[[#This Row],[№ акта]],$AJ$1:$BJ$691,23,FALSE)<>0,VLOOKUP(Таблица3[[#This Row],[№ акта]],$AJ$1:$BJ$691,23,FALSE),"-") -> - | AC11: =IF(Таблица3[[#This Row],[Степень зрелости вспом]]=0,"нет данных",IF(Таблица3[[#This Row],[Степень зрелости вспом]]<40,"до 40",IF(Таблица3[[#This Row],[Степень зрелости вспом]]<53,"40-52",IF(Таблица3[[#This Row],[Степень зрелости вспом]]<64,"53-63",IF(Таблица3[[#This Row],[Степень зрелости вспом]]<67,"64-66",IF(Таблица3[[#This Row],[Степень зрелости вспом]]<85,"67-85",)))))) -> 53-63 | AD11: Высший | AE11: 23 | AF11: 46177 | AG11: 10 | AH11: =IFERROR(VLOOKUP(Таблица3[[#This Row],[№ акта]],'Степень зрелости 2026'!$H$12:$I$800,2,FALSE),) -> 53 | AJ11: 23 | AK11: 46177 | AL11: 54 | AO11: 13390 | AP11: 10779 | AQ11: Горошек овощной 2026 (богара) | AR11: Тиара | AS11: А-4/1 | AT11: Кудря Евгений | AV11: А719ОО | AX11: А-4/1 | AY11: Тиара | AZ11: 2.5 | BA11: ГРК (богара) | BB11: богара | BC11: 1 | BD11: 46176 | BG11: 53-63 | BH11: Высший | BI11: 10 | BJ11: 53
A12: Степень зрелости | C12: =Таблица3[[#This Row],[Степень зрелости вспом]] -> 55 | D12: 55 | G12: 13270 | I12: 10815.1 | J12: Горошек овощной 2026 (богара) | K12: Тиара | L12: А-4/1 | M12: Богучарский А. И. | R12: А718ВХ | T12: =VLOOKUP(Таблица3[[#This Row],[№ акта]],$AJ$1:$BJ$691,15,FALSE) -> А-4/1 | U12: =VLOOKUP(Таблица3[[#This Row],[№ акта]],$AJ$1:$BJ$691,16,FALSE) -> Тиара | V12: =VLOOKUP(Таблица3[[#This Row],[№ акта]],$AJ$1:$BJ$691,17,FALSE) -> 2.5 | W12: =VLOOKUP(Таблица3[[#This Row],[№ акта]],$AJ$1:$BJ$691,18,FALSE) -> ГРК (богара) | X12: =VLOOKUP(Таблица3[[#This Row],[№ акта]],$AJ$1:$BJ$691,19,FALSE) -> богара | Y12: =VLOOKUP(Таблица3[[#This Row],[№ акта]],$AJ$1:$BJ$691,20,FALSE) -> 1 | Z12: =VLOOKUP(Таблица3[[#This Row],[№ акта]],$AJ$1:$BJ$691,21,FALSE) -> 46176 | AB12: =IF(VLOOKUP(Таблица3[[#This Row],[№ акта]],$AJ$1:$BJ$691,23,FALSE)<>0,VLOOKUP(Таблица3[[#This Row],[№ акта]],$AJ$1:$BJ$691,23,FALSE),"-") -> - | AC12: =IF(Таблица3[[#This Row],[Степень зрелости вспом]]=0,"нет данных",IF(Таблица3[[#This Row],[Степень зрелости вспом]]<40,"до 40",IF(Таблица3[[#This Row],[Степень зрелости вспом]]<53,"40-52",IF(Таблица3[[#This Row],[Степень зрелости вспом]]<64,"53-63",IF(Таблица3[[#This Row],[Степень зрелости вспом]]<67,"64-66",IF(Таблица3[[#This Row],[Степень зрелости вспом]]<85,"67-85",)))))) -> 53-63 | AD12: Высший | AE12: 24 | AF12: 46177 | AG12: 11 | AH12: =IFERROR(VLOOKUP(Таблица3[[#This Row],[№ акта]],'Степень зрелости 2026'!$H$12:$I$800,2,FALSE),) -> 55 | AJ12: 24 | AK12: 46177 | AL12: 55 | AO12: 13270 | AP12: 10815.1 | AQ12: Горошек овощной 2026 (богара) | AR12: Тиара | AS12: А-4/1 | AT12: Богучарский А. И. | AV12: А718ВХ | AX12: А-4/1 | AY12: Тиара | AZ12: 2.5 | BA12: ГРК (богара) | BB12: богара | BC12: 1 | BD12: 46176 | BG12: 53-63 | BH12: Высший | BI12: 11 | BJ12: 55
A13: Степень зрелости | C13: =Таблица3[[#This Row],[Степень зрелости вспом]] -> 50 | D13: 56 | G13: 13200 | I13: 10362 | J13: Горошек овощной 2026 (богара) | K13: Тиара | L13: А-4/1 | M13: Черевко Александр Владимирович | R13: А114МК | T13: =VLOOKUP(Таблица3[[#This Row],[№ акта]],$AJ$1:$BJ$691,15,FALSE) -> А-4/1 | U13: =VLOOKUP(Таблица3[[#This Row],[№ акта]],$AJ$1:$BJ$691,16,FALSE) -> Тиара | V13: =VLOOKUP(Таблица3[[#This Row],[№ акта]],$AJ$1:$BJ$691,17,FALSE) -> 2.5 | W13: =VLOOKUP(Таблица3[[#This Row],[№ акта]],$AJ$1:$BJ$691,18,FALSE) -> ГРК (богара) | X13: =VLOOKUP(Таблица3[[#This Row],[№ акта]],$AJ$1:$BJ$691,19,FALSE) -> богара | Y13: =VLOOKUP(Таблица3[[#This Row],[№ акта]],$AJ$1:$BJ$691,20,FALSE) -> 1 | Z13: =VLOOKUP(Таблица3[[#This Row],[№ акта]],$AJ$1:$BJ$691,21,FALSE) -> 46176 | AB13: =IF(VLOOKUP(Таблица3[[#This Row],[№ акта]],$AJ$1:$BJ$691,23,FALSE)<>0,VLOOKUP(Таблица3[[#This Row],[№ акта]],$AJ$1:$BJ$691,23,FALSE),"-") -> - | AC13: =IF(Таблица3[[#This Row],[Степень зрелости вспом]]=0,"нет данных",IF(Таблица3[[#This Row],[Степень зрелости вспом]]<40,"до 40",IF(Таблица3[[#This Row],[Степень зрелости вспом]]<53,"40-52",IF(Таблица3[[#This Row],[Степень зрелости вспом]]<64,"53-63",IF(Таблица3[[#This Row],[Степень зрелости вспом]]<67,"64-66",IF(Таблица3[[#This Row],[Степень зрелости вспом]]<85,"67-85",)))))) -> 40-52 | AD13: Высший | AE13: 25 | AF13: 46177 | AG13: 12 | AH13: =IFERROR(VLOOKUP(Таблица3[[#This Row],[№ акта]],'Степень зрелости 2026'!$H$12:$I$800,2,FALSE),) -> 50 | AJ13: 25 | AK13: 46177 | AL13: 56 | AO13: 13200 | AP13: 10362 | AQ13: Горошек овощной 2026 (богара) | AR13: Тиара | AS13: А-4/1 | AT13: Черевко Александр Владимирович | AV13: А114МК | AX13: А-4/1 | AY13: Тиара | AZ13: 2.5 | BA13: ГРК (богара) | BB13: богара | BC13: 1 | BD13: 46176 | BG13: 40-52 | BH13: Высший | BI13: 12 | BJ13: 50
... A94: Степень зрелости | C94: =Таблица3[[#This Row],[Степень зрелости вспом]] -> 53 | D94: 163 | G94: 13470 | I94: 10978 | J94: Горошек овощной 2026 (богара) | K94: Увертюра | L94: А-22 | M94: Рудик Александр Иванович | R94: А309АТ | T94: =VLOOKUP(Таблица3[[#This Row],[№ акта]],$AJ$1:$BJ$691,15,FALSE) -> А-22/1 | U94: =VLOOKUP(Таблица3[[#This Row],[№ акта]],$AJ$1:$BJ$691,16,FALSE) -> Увертюра | V94: =VLOOKUP(Таблица3[[#This Row],[№ акта]],$AJ$1:$BJ$691,17,FALSE) -> 2 | W94: =VLOOKUP(Таблица3[[#This Row],[№ акта]],$AJ$1:$BJ$691,18,FALSE) -> ГРК (богара) | X94: =VLOOKUP(Таблица3[[#This Row],[№ акта]],$AJ$1:$BJ$691,19,FALSE) -> богара | Y94: =VLOOKUP(Таблица3[[#This Row],[№ акта]],$AJ$1:$BJ$691,20,FALSE) -> 6 | Z94: =VLOOKUP(Таблица3[[#This Row],[№ акта]],$AJ$1:$BJ$691,21,FALSE) -> 46182 | AB94: =IF(VLOOKUP(Таблица3[[#This Row],[№ акта]],$AJ$1:$BJ$691,23,FALSE)<>0,VLOOKUP(Таблица3[[#This Row],[№ акта]],$AJ$1:$BJ$691,23,FALSE),"-") -> - | AC94: =IF(Таблица3[[#This Row],[Степень зрелости вспом]]=0,"нет данных",IF(Таблица3[[#This Row],[Степень зрелости вспом]]<40,"до 40",IF(Таблица3[[#This Row],[Степень зрелости вспом]]<53,"40-52",IF(Таблица3[[#This Row],[Степень зрелости вспом]]<64,"53-63",IF(Таблица3[[#This Row],[Степень зрелости вспом]]<67,"64-66",IF(Таблица3[[#This Row],[Степень зрелости вспом]]<85,"67-85",)))))) -> 53-63 | AD94: Высший | AE94: 107 | AF94: 46182 | AG94: 93 | AH94: =IFERROR(VLOOKUP(Таблица3[[#This Row],[№ акта]],'Степень зрелости 2026'!$H$12:$I$800,2,FALSE),) -> 53 | AJ94: 107 | AK94: 46182 | AL94: 163 | AO94: 13470 | AP94: 10978 | AQ94: Горошек овощной 2026 (богара) | AR94: Увертюра | AS94: А-22 | AT94: Рудик Александр Иванович | AV94: А309АТ | AX94: А-22/1 | AY94: Увертюра | AZ94: 2 | BA94: ГРК (богара) | BB94: богара | BC94: 6 | BD94: 46182 | BG94: 53-63 | BH94: Высший | BI94: 93 | BJ94: 53
A95: Степень зрелости | C95: =Таблица3[[#This Row],[Степень зрелости вспом]] -> 58 | D95: 165 | G95: 17540 | I95: 14875.5 | J95: Горошек овощной 2026 (богара) | K95: Увертюра | L95: А-22 | M95: Алтадуков Заур Баталбиевич | R95: В841АН | T95: =VLOOKUP(Таблица3[[#This Row],[№ акта]],$AJ$1:$BJ$691,15,FALSE) -> А-22/1 | U95: =VLOOKUP(Таблица3[[#This Row],[№ акта]],$AJ$1:$BJ$691,16,FALSE) -> Увертюра | V95: =VLOOKUP(Таблица3[[#This Row],[№ акта]],$AJ$1:$BJ$691,17,FALSE) -> 2.6 | W95: =VLOOKUP(Таблица3[[#This Row],[№ акта]],$AJ$1:$BJ$691,18,FALSE) -> ГРК (богара) | X95: =VLOOKUP(Таблица3[[#This Row],[№ акта]],$AJ$1:$BJ$691,19,FALSE) -> богара | Y95: =VLOOKUP(Таблица3[[#This Row],[№ акта]],$AJ$1:$BJ$691,20,FALSE) -> 6 | Z95: =VLOOKUP(Таблица3[[#This Row],[№ акта]],$AJ$1:$BJ$691,21,FALSE) -> 46182 | AA95: =Таблица3[[#This Row],[Регистратор.Вес нетто]] -> 17540 | AB95: =IF(VLOOKUP(Таблица3[[#This Row],[№ акта]],$AJ$1:$BJ$691,23,FALSE)<>0,VLOOKUP(Таблица3[[#This Row],[№ акта]],$AJ$1:$BJ$691,23,FALSE),"-") -> ТПК ЮЖНЫЙ ПРОДУКТ ООО | AC95: =IF(Таблица3[[#This Row],[Степень зрелости вспом]]=0,"нет данных",IF(Таблица3[[#This Row],[Степень зрелости вспом]]<40,"до 40",IF(Таблица3[[#This Row],[Степень зрелости вспом]]<53,"40-52",IF(Таблица3[[#This Row],[Степень зрелости вспом]]<64,"53-63",IF(Таблица3[[#This Row],[Степень зрелости вспом]]<67,"64-66",IF(Таблица3[[#This Row],[Степень зрелости вспом]]<85,"67-85",)))))) -> 53-63 | AD95: Высший | AE95: 272 | AF95: 46182 | AG95: 165/2 | AH95: =IFERROR(VLOOKUP(Таблица3[[#This Row],[№ акта]],'Степень зрелости 2026'!$H$12:$I$800,2,FALSE),) -> 58 | AJ95: 272 | AK95: 46182 | AL95: 165 | AO95: 17540 | AP95: 14875.5 | AQ95: Горошек овощной 2026 (богара) | AR95: Увертюра | AS95: А-22 | AT95: Алтадуков Заур Баталбиевич | AV95: В841АН | AX95: А-22/1 | AY95: Увертюра | AZ95: 2.6 | BA95: ГРК (богара) | BB95: богара | BC95: 6 | BD95: 46182 | BE95: 17540 | BF95: ТПК ЮЖНЫЙ ПРОДУКТ ООО | BG95: 53-63 | BH95: Высший | BI95: 165/2 | BJ95: 58
A96: Степень зрелости | C96: =Таблица3[[#This Row],[Степень зрелости вспом]] -> 54 | D96: 166 | G96: 15390 | I96: 13701 | J96: Горошек овощной 2026 (богара) | K96: Увертюра | L96: А-22/1 | M96: Баранов Николай Александрович | R96: М540АС | T96: =VLOOKUP(Таблица3[[#This Row],[№ акта]],$AJ$1:$BJ$691,15,FALSE) -> А-22/1 | U96: =VLOOKUP(Таблица3[[#This Row],[№ акта]],$AJ$1:$BJ$691,16,FALSE) -> Увертюра | V96: =VLOOKUP(Таблица3[[#This Row],[№ акта]],$AJ$1:$BJ$691,17,FALSE) -> 2.3 | W96: =VLOOKUP(Таблица3[[#This Row],[№ акта]],$AJ$1:$BJ$691,18,FALSE) -> ГРК (богара) | X96: =VLOOKUP(Таблица3[[#This Row],[№ акта]],$AJ$1:$BJ$691,19,FALSE) -> богара | Y96: =VLOOKUP(Таблица3[[#This Row],[№ акта]],$AJ$1:$BJ$691,20,FALSE) -> 6 | Z96: =VLOOKUP(Таблица3[[#This Row],[№ акта]],$AJ$1:$BJ$691,21,FALSE) -> 46182 | AA96: =Таблица3[[#This Row],[Регистратор.Вес нетто]] -> 15390 | AB96: =IF(VLOOKUP(Таблица3[[#This Row],[№ акта]],$AJ$1:$BJ$691,23,FALSE)<>0,VLOOKUP(Таблица3[[#This Row],[№ акта]],$AJ$1:$BJ$691,23,FALSE),"-") -> ТПК ЮЖНЫЙ ПРОДУКТ ООО | AC96: =IF(Таблица3[[#This Row],[Степень зрелости вспом]]=0,"нет данных",IF(Таблица3[[#This Row],[Степень зрелости вспом]]<40,"до 40",IF(Таблица3[[#This Row],[Степень зрелости вспом]]<53,"40-52",IF(Таблица3[[#This Row],[Степень зрелости вспом]]<64,"53-63",IF(Таблица3[[#This Row],[Степень зрелости вспом]]<67,"64-66",IF(Таблица3[[#This Row],[Степень зрелости вспом]]<85,"67-85",)))))) -> 53-63 | AD96: Высший | AE96: 228 | AF96: 46188 | AG96: 166/1 | AH96: =IFERROR(VLOOKUP(Таблица3[[#This Row],[№ акта]],'Степень зрелости 2026'!$H$12:$I$800,2,FALSE),) -> 54 | AJ96: 228 | AK96: 46188 | AL96: 166 | AO96: 15390 | AP96: 13701 | AQ96: Горошек овощной 2026 (богара) | AR96: Увертюра | AS96: А-22/1 | AT96: Баранов Николай Александрович | AV96: М540АС | AX96: А-22/1 | AY96: Увертюра | AZ96: 2.3 | BA96: ГРК (богара) | BB96: богара | BC96: 6 | BD96: 46182 | BE96: 15390 | BF96: ТПК ЮЖНЫЙ ПРОДУКТ ООО | BG96: 53-63 | BH96: Высший | BI96: 166/1 | BJ96: 54
A97: Степень зрелости | C97: =Таблица3[[#This Row],[Степень зрелости вспом]] -> 56 | D97: 167 | G97: 13530 | I97: 10756.3 | J97: Горошек овощной 2026 (богара) | K97: Увертюра | L97: А-22 | M97: Ревенко Андрей Вячеславович | R97: А781РР | T97: =VLOOKUP(Таблица3[[#This Row],[№ акта]],$AJ$1:$BJ$691,15,FALSE) -> А-22/1 | U97: =VLOOKUP(Таблица3[[#This Row],[№ акта]],$AJ$1:$BJ$691,16,FALSE) -> Увертюра | V97: =VLOOKUP(Таблица3[[#This Row],[№ акта]],$AJ$1:$BJ$691,17,FALSE) -> 2 | W97: =VLOOKUP(Таблица3[[#This Row],[№ акта]],$AJ$1:$BJ$691,18,FALSE) -> ГРК (богара) | X97: =VLOOKUP(Таблица3[[#This Row],[№ акта]],$AJ$1:$BJ$691,19,FALSE) -> богара | Y97: =VLOOKUP(Таблица3[[#This Row],[№ акта]],$AJ$1:$BJ$691,20,FALSE) -> 6 | Z97: =VLOOKUP(Таблица3[[#This Row],[№ акта]],$AJ$1:$BJ$691,21,FALSE) -> 46182 | AB97: =IF(VLOOKUP(Таблица3[[#This Row],[№ акта]],$AJ$1:$BJ$691,23,FALSE)<>0,VLOOKUP(Таблица3[[#This Row],[№ акта]],$AJ$1:$BJ$691,23,FALSE),"-") -> - | AC97: =IF(Таблица3[[#This Row],[Степень зрелости вспом]]=0,"нет данных",IF(Таблица3[[#This Row],[Степень зрелости вспом]]<40,"до 40",IF(Таблица3[[#This Row],[Степень зрелости вспом]]<53,"40-52",IF(Таблица3[[#This Row],[Степень зрелости вспом]]<64,"53-63",IF(Таблица3[[#This Row],[Степень зрелости вспом]]<67,"64-66",IF(Таблица3[[#This Row],[Степень зрелости вспом]]<85,"67-85",)))))) -> 53-63 | AD97: Высший | AE97: 108 | AF97: 46182 | AG97: 94 | AH97: =IFERROR(VLOOKUP(Таблица3[[#This Row],[№ акта]],'Степень зрелости 2026'!$H$12:$I$800,2,FALSE),) -> 56 | AJ97: 108 | AK97: 46182 | AL97: 167 | AO97: 13530 | AP97: 10756.3 | AQ97: Горошек овощной 2026 (богара) | AR97: Увертюра | AS97: А-22 | AT97: Ревенко Андрей Вячеславович | AV97: А781РР | AX97: А-22/1 | AY97: Увертюра | AZ97: 2 | BA97: ГРК (богара) | BB97: богара | BC97: 6 | BD97: 46182 | BG97: 53-63 | BH97: Высший | BI97: 94 | BJ97: 56
A98: Степень зрелости | C98: =Таблица3[[#This Row],[Степень зрелости вспом]] -> 54 | D98: 168 | G98: 4090 | I98: 3456.1 | J98: Горошек овощной 2026 (богара) | K98: Увертюра | L98: А-22/1 | M98: Роговской Роман Алексеевич | R98: Т945РВ | T98: =VLOOKUP(Таблица3[[#This Row],[№ акта]],$AJ$1:$BJ$691,15,FALSE) -> А-22/1 | U98: =VLOOKUP(Таблица3[[#This Row],[№ акта]],$AJ$1:$BJ$691,16,FALSE) -> Увертюра | V98: =VLOOKUP(Таблица3[[#This Row],[№ акта]],$AJ$1:$BJ$691,17,FALSE) -> 0.6 | W98: =VLOOKUP(Таблица3[[#This Row],[№ акта]],$AJ$1:$BJ$691,18,FALSE) -> ГРК (богара) | X98: =VLOOKUP(Таблица3[[#This Row],[№ акта]],$AJ$1:$BJ$691,19,FALSE) -> богара | Y98: =VLOOKUP(Таблица3[[#This Row],[№ акта]],$AJ$1:$BJ$691,20,FALSE) -> 6 | Z98: =VLOOKUP(Таблица3[[#This Row],[№ акта]],$AJ$1:$BJ$691,21,FALSE) -> 46182 | AB98: =IF(VLOOKUP(Таблица3[[#This Row],[№ акта]],$AJ$1:$BJ$691,23,FALSE)<>0,VLOOKUP(Таблица3[[#This Row],[№ акта]],$AJ$1:$BJ$691,23,FALSE),"-") -> - | AC98: =IF(Таблица3[[#This Row],[Степень зрелости вспом]]=0,"нет данных",IF(Таблица3[[#This Row],[Степень зрелости вспом]]<40,"до 40",IF(Таблица3[[#This Row],[Степень зрелости вспом]]<53,"40-52",IF(Таблица3[[#This Row],[Степень зрелости вспом]]<64,"53-63",IF(Таблица3[[#This Row],[Степень зрелости вспом]]<67,"64-66",IF(Таблица3[[#This Row],[Степень зрелости вспом]]<85,"67-85",)))))) -> 53-63 | AD98: Высший | AE98: 109 | AF98: 46182 | AG98: 95 | AH98: =IFERROR(VLOOKUP(Таблица3[[#This Row],[№ акта]],'Степень зрелости 2026'!$H$12:$I$800,2,FALSE),) -> 54 | AJ98: 109 | AK98: 46182 | AL98: 168 | AO98: 4090 | AP98: 3456.1 | AQ98: Горошек овощной 2026 (богара) | AR98: Увертюра | AS98: А-22/1 | AT98: Роговской Роман Алексеевич | AV98: Т945РВ | AX98: А-22/1 | AY98: Увертюра | AZ98: 0.6 | BA98: ГРК (богара) | BB98: богара | BC98: 6 | BD98: 46182 | BG98: 53-63 | BH98: Высший | BI98: 95 | BJ98: 54
A99: Степень зрелости | C99: =Таблица3[[#This Row],[Степень зрелости вспом]] -> 56 | D99: 170 | G99: 13410 | I99: 12136.1 | J99: Горошек овощной 2026 (богара) | K99: Увертюра | L99: А-22/1 | M99: Извеков Владимир Владимирович | R99: Н378ХЕ | T99: =VLOOKUP(Таблица3[[#This Row],[№ акта]],$AJ$1:$BJ$691,15,FALSE) -> А-22/1 | U99: =VLOOKUP(Таблица3[[#This Row],[№ акта]],$AJ$1:$BJ$691,16,FALSE) -> Увертюра | V99: =VLOOKUP(Таблица3[[#This Row],[№ акта]],$AJ$1:$BJ$691,17,FALSE) -> 2 | W99: =VLOOKUP(Таблица3[[#This Row],[№ акта]],$AJ$1:$BJ$691,18,FALSE) -> ГРК (богара) | X99: =VLOOKUP(Таблица3[[#This Row],[№ акта]],$AJ$1:$BJ$691,19,FALSE) -> богара | Y99: =VLOOKUP(Таблица3[[#This Row],[№ акта]],$AJ$1:$BJ$691,20,FALSE) -> 6 | Z99: =VLOOKUP(Таблица3[[#This Row],[№ акта]],$AJ$1:$BJ$691,21,FALSE) -> 46182 | AB99: =IF(VLOOKUP(Таблица3[[#This Row],[№ акта]],$AJ$1:$BJ$691,23,FALSE)<>0,VLOOKUP(Таблица3[[#This Row],[№ акта]],$AJ$1:$BJ$691,23,FALSE),"-") -> - | AC99: =IF(Таблица3[[#This Row],[Степень зрелости вспом]]=0,"нет данных",IF(Таблица3[[#This Row],[Степень зрелости вспом]]<40,"до 40",IF(Таблица3[[#This Row],[Степень зрелости вспом]]<53,"40-52",IF(Таблица3[[#This Row],[Степень зрелости вспом]]<64,"53-63",IF(Таблица3[[#This Row],[Степень зрелости вспом]]<67,"64-66",IF(Таблица3[[#This Row],[Степень зрелости вспом]]<85,"67-85",)))))) -> 53-63 | AD99: Высший | AE99: 110 | AF99: 46182 | AG99: 96 | AH99: =IFERROR(VLOOKUP(Таблица3[[#This Row],[№ акта]],'Степень зрелости 2026'!$H$12:$I$800,2,FALSE),) -> 56 | AJ99: 110 | AK99: 46182 | AL99: 170 | AO99: 13410 | AP99: 12136.1 | AQ99: Горошек овощной 2026 (богара) | AR99: Увертюра | AS99: А-22/1 | AT99: Извеков Владимир Владимирович | AV99: Н378ХЕ | AX99: А-22/1 | AY99: Увертюра | AZ99: 2 | BA99: ГРК (богара) | BB99: богара | BC99: 6 | BD99: 46182 | BG99: 53-63 | BH99: Высший | BI99: 96 | BJ99: 56
A100: Степень зрелости | C100: =Таблица3[[#This Row],[Степень зрелости вспом]] -> 54 | D100: 171 | G100: 13300 | I100: 11238.5 | J100: Горошек овощной 2026 (богара) | K100: Увертюра | L100: А-22 | M100: Гуйда Николай Николаевич | R100: А816ЕВ | T100: =VLOOKUP(Таблица3[[#This Row],[№ акта]],$AJ$1:$BJ$691,15,FALSE) -> А-22/1 | U100: =VLOOKUP(Таблица3[[#This Row],[№ акта]],$AJ$1:$BJ$691,16,FALSE) -> Увертюра | V100: =VLOOKUP(Таблица3[[#This Row],[№ акта]],$AJ$1:$BJ$691,17,FALSE) -> 2 | W100: =VLOOKUP(Таблица3[[#This Row],[№ акта]],$AJ$1:$BJ$691,18,FALSE) -> ГРК (богара) | X100: =VLOOKUP(Таблица3[[#This Row],[№ акта]],$AJ$1:$BJ$691,19,FALSE) -> богара | Y100: =VLOOKUP(Таблица3[[#This Row],[№ акта]],$AJ$1:$BJ$691,20,FALSE) -> 6 | Z100: =VLOOKUP(Таблица3[[#This Row],[№ акта]],$AJ$1:$BJ$691,21,FALSE) -> 46182 | AB100: =IF(VLOOKUP(Таблица3[[#This Row],[№ акта]],$AJ$1:$BJ$691,23,FALSE)<>0,VLOOKUP(Таблица3[[#This Row],[№ акта]],$AJ$1:$BJ$691,23,FALSE),"-") -> - | AC100: =IF(Таблица3[[#This Row],[Степень зрелости вспом]]=0,"нет данных",IF(Таблица3[[#This Row],[Степень зрелости вспом]]<40,"до 40",IF(Таблица3[[#This Row],[Степень зрелости вспом]]<53,"40-52",IF(Таблица3[[#This Row],[Степень зрелости вспом]]<64,"53-63",IF(Таблица3[[#This Row],[Степень зрелости вспом]]<67,"64-66",IF(Таблица3[[#This Row],[Степень зрелости вспом]]<85,"67-85",)))))) -> 53-63 | AD100: Высший | AE100: 111 | AF100: 46182 | AG100: 92 | AH100: =IFERROR(VLOOKUP(Таблица3[[#This Row],[№ акта]],'Степень зрелости 2026'!$H$12:$I$800,2,FALSE),) -> 54 | AJ100: 111 | AK100: 46182 | AL100: 171 | AO100: 13300 | AP100: 11238.5 | AQ100: Горошек овощной 2026 (богара) | AR100: Увертюра | AS100: А-22 | AT100: Гуйда Николай Николаевич | AV100: А816ЕВ | AX100: А-22/1 | AY100: Увертюра | AZ100: 2 | BA100: ГРК (богара) | BB100: богара | BC100: 6 | BD100: 46182 | BG100: 53-63 | BH100: Высший | BI100: 92 | BJ100: 54
A101: Степень зрелости | C101: =Таблица3[[#This Row],[Степень зрелости вспом]] -> 51 | D101: 172 | G101: 13070 | I101: 11566.9 | J101: Горошек овощной 2026 (богара) | K101: Увертюра | L101: А-22 | M101: Рудик Александр Иванович | R101: А309АТ | T101: =VLOOKUP(Таблица3[[#This Row],[№ акта]],$AJ$1:$BJ$691,15,FALSE) -> А-22/1 | U101: =VLOOKUP(Таблица3[[#This Row],[№ акта]],$AJ$1:$BJ$691,16,FALSE) -> Увертюра | V101: =VLOOKUP(Таблица3[[#This Row],[№ акта]],$AJ$1:$BJ$691,17,FALSE) -> 2 | W101: =VLOOKUP(Таблица3[[#This Row],[№ акта]],$AJ$1:$BJ$691,18,FALSE) -> ГРК (богара) | X101: =VLOOKUP(Таблица3[[#This Row],[№ акта]],$AJ$1:$BJ$691,19,FALSE) -> богара | Y101: =VLOOKUP(Таблица3[[#This Row],[№ акта]],$AJ$1:$BJ$691,20,FALSE) -> 6 | Z101: =VLOOKUP(Таблица3[[#This Row],[№ акта]],$AJ$1:$BJ$691,21,FALSE) -> 46182 | AB101: =IF(VLOOKUP(Таблица3[[#This Row],[№ акта]],$AJ$1:$BJ$691,23,FALSE)<>0,VLOOKUP(Таблица3[[#This Row],[№ акта]],$AJ$1:$BJ$691,23,FALSE),"-") -> - | AC101: =IF(Таблица3[[#This Row],[Степень зрелости вспом]]=0,"нет данных",IF(Таблица3[[#This Row],[Степень зрелости вспом]]<40,"до 40",IF(Таблица3[[#This Row],[Степень зрелости вспом]]<53,"40-52",IF(Таблица3[[#This Row],[Степень зрелости вспом]]<64,"53-63",IF(Таблица3[[#This Row],[Степень зрелости вспом]]<67,"64-66",IF(Таблица3[[#This Row],[Степень зрелости вспом]]<85,"67-85",)))))) -> 40-52 | AD101: Высший | AE101: 112 | AF101: 46182 | AG101: 98 | AH101: =IFERROR(VLOOKUP(Таблица3[[#This Row],[№ акта]],'Степень зрелости 2026'!$H$12:$I$800,2,FALSE),) -> 51 | AJ101: 112 | AK101: 46182 | AL101: 172 | AO101: 13070 | AP101: 11566.9 | AQ101: Горошек овощной 2026 (богара) | AR101: Увертюра | AS101: А-22 | AT101: Рудик Александр Иванович | AV101: А309АТ | AX101: А-22/1 | AY101: Увертюра | AZ101: 2 | BA101: ГРК (богара) | BB101: богара | BC101: 6 | BD101: 46182 | BG101: 40-52 | BH101: Высший | BI101: 98 | BJ101: 51
A102: Степень зрелости | C102: =Таблица3[[#This Row],[Степень зрелости вспом]] -> 54 | D102: 173 | G102: 13100 | I102: 10283.5 | J102: Горошек овощной 2026 (богара) | K102: Увертюра | L102: А-22 | M102: Ревенко Андрей Вячеславович | R102: А781РР | T102: =VLOOKUP(Таблица3[[#This Row],[№ акта]],$AJ$1:$BJ$691,15,FALSE) -> А-22/1 | U102: =VLOOKUP(Таблица3[[#This Row],[№ акта]],$AJ$1:$BJ$691,16,FALSE) -> Увертюра | V102: =VLOOKUP(Таблица3[[#This Row],[№ акта]],$AJ$1:$BJ$691,17,FALSE) -> 2 | W102: =VLOOKUP(Таблица3[[#This Row],[№ акта]],$AJ$1:$BJ$691,18,FALSE) -> ГРК (богара) | X102: =VLOOKUP(Таблица3[[#This Row],[№ акта]],$AJ$1:$BJ$691,19,FALSE) -> богара | Y102: =VLOOKUP(Таблица3[[#This Row],[№ акта]],$AJ$1:$BJ$691,20,FALSE) -> 6 | Z102: =VLOOKUP(Таблица3[[#This Row],[№ акта]],$AJ$1:$BJ$691,21,FALSE) -> 46182 | AB102: =IF(VLOOKUP(Таблица3[[#This Row],[№ акта]],$AJ$1:$BJ$691,23,FALSE)<>0,VLOOKUP(Таблица3[[#This Row],[№ акта]],$AJ$1:$BJ$691,23,FALSE),"-") -> - | AC102: =IF(Таблица3[[#This Row],[Степень зрелости вспом]]=0,"нет данных",IF(Таблица3[[#This Row],[Степень зрелости вспом]]<40,"до 40",IF(Таблица3[[#This Row],[Степень зрелости вспом]]<53,"40-52",IF(Таблица3[[#This Row],[Степень зрелости вспом]]<64,"53-63",IF(Таблица3[[#This Row],[Степень зрелости вспом]]<67,"64-66",IF(Таблица3[[#This Row],[Степень зрелости вспом]]<85,"67-85",)))))) -> 53-63 | AD102: Высший | AE102: 113 | AF102: 46182 | AG102: 99 | AH102: =IFERROR(VLOOKUP(Таблица3[[#This Row],[№ акта]],'Степень зрелости 2026'!$H$12:$I$800,2,FALSE),) -> 54 | AJ102: 113 | AK102: 46182 | AL102: 173 | AO102: 13100 | AP102: 10283.5 | AQ102: Горошек овощной 2026 (богара) | AR102: Увертюра | AS102: А-22 | AT102: Ревенко Андрей Вячеславович | AV102: А781РР | AX102: А-22/1 | AY102: Увертюра | AZ102: 2 | BA102: ГРК (богара) | BB102: богара | BC102: 6 | BD102: 46182 | BG102: 53-63 | BH102: Высший | BI102: 99 | BJ102: 54
A103: Степень зрелости | C103: =Таблица3[[#This Row],[Степень зрелости вспом]] -> 53 | D103: 174 | G103: 4430 | I103: 3743.4 | J103: Горошек овощной 2026 (богара) | K103: Увертюра | L103: А-22/1 | M103: Роговской Роман Алексеевич | R103: Т945РВ | T103: =VLOOKUP(Таблица3[[#This Row],[№ акта]],$AJ$1:$BJ$691,15,FALSE) -> А-22/1 | U103: =VLOOKUP(Таблица3[[#This Row],[№ акта]],$AJ$1:$BJ$691,16,FALSE) -> Увертюра | V103: =VLOOKUP(Таблица3[[#This Row],[№ акта]],$AJ$1:$BJ$691,17,FALSE) -> 0.7 | W103: =VLOOKUP(Таблица3[[#This Row],[№ акта]],$AJ$1:$BJ$691,18,FALSE) -> ГРК (богара) | X103: =VLOOKUP(Таблица3[[#This Row],[№ акта]],$AJ$1:$BJ$691,19,FALSE) -> богара | Y103: =VLOOKUP(Таблица3[[#This Row],[№ акта]],$AJ$1:$BJ$691,20,FALSE) -> 6 | Z103: =VLOOKUP(Таблица3[[#This Row],[№ акта]],$AJ$1:$BJ$691,21,FALSE) -> 46182 | AB103: =IF(VLOOKUP(Таблица3[[#This Row],[№ акта]],$AJ$1:$BJ$691,23,FALSE)<>0,VLOOKUP(Таблица3[[#This Row],[№ акта]],$AJ$1:$BJ$691,23,FALSE),"-") -> - | AC103: =IF(Таблица3[[#This Row],[Степень зрелости вспом]]=0,"нет данных",IF(Таблица3[[#This Row],[Степень зрелости вспом]]<40,"до 40",IF(Таблица3[[#This Row],[Степень зрелости вспом]]<53,"40-52",IF(Таблица3[[#This Row],[Степень зрелости вспом]]<64,"53-63",IF(Таблица3[[#This Row],[Степень зрелости вспом]]<67,"64-66",IF(Таблица3[[#This Row],[Степень зрелости вспом]]<85,"67-85",)))))) -> 53-63 | AD103: Высший | AE103: 114 | AF103: 46182 | AG103: 100 | AH103: =IFERROR(VLOOKUP(Таблица3[[#This Row],[№ акта]],'Степень зрелости 2026'!$H$12:$I$800,2,FALSE),) -> 53 | AJ103: 114 | AK103: 46182 | AL103: 174 | AO103: 4430 | AP103: 3743.4 | AQ103: Горошек овощной 2026 (богара) | AR103: Увертюра | AS103: А-22/1 | AT103: Роговской Роман Алексеевич | AV103: Т945РВ | AX103: А-22/1 | AY103: Увертюра | AZ103: 0.7 | BA103: ГРК (богара) | BB103: богара | BC103: 6 | BD103: 46182 | BG103: 53-63 | BH103: Высший | BI103: 100 | BJ103: 53
A104: Степень зрелости | C104: =Таблица3[[#This Row],[Степень зрелости вспом]] -> 54 | D104: 175 | G104: 13270 | I104: 11611.3 | J104: Горошек овощной 2026 (богара) | K104: Увертюра | L104: А-22/1 | M104: Извеков Владимир Владимирович | R104: Н378ХЕ | T104: =VLOOKUP(Таблица3[[#This Row],[№ акта]],$AJ$1:$BJ$691,15,FALSE) -> А-22/1 | U104: =VLOOKUP(Таблица3[[#This Row],[№ акта]],$AJ$1:$BJ$691,16,FALSE) -> Увертюра | V104: =VLOOKUP(Таблица3[[#This Row],[№ акта]],$AJ$1:$BJ$691,17,FALSE) -> 2 | W104: =VLOOKUP(Таблица3[[#This Row],[№ акта]],$AJ$1:$BJ$691,18,FALSE) -> ГРК (богара) | X104: =VLOOKUP(Таблица3[[#This Row],[№ акта]],$AJ$1:$BJ$691,19,FALSE) -> богара | Y104: =VLOOKUP(Таблица3[[#This Row],[№ акта]],$AJ$1:$BJ$691,20,FALSE) -> 6 | Z104: =VLOOKUP(Таблица3[[#This Row],[№ акта]],$AJ$1:$BJ$691,21,FALSE) -> 46182 | AB104: =IF(VLOOKUP(Таблица3[[#This Row],[№ акта]],$AJ$1:$BJ$691,23,FALSE)<>0,VLOOKUP(Таблица3[[#This Row],[№ акта]],$AJ$1:$BJ$691,23,FALSE),"-") -> - | AC104: =IF(Таблица3[[#This Row],[Степень зрелости вспом]]=0,"нет данных",IF(Таблица3[[#This Row],[Степень зрелости вспом]]<40,"до 40",IF(Таблица3[[#This Row],[Степень зрелости вспом]]<53,"40-52",IF(Таблица3[[#This Row],[Степень зрелости вспом]]<64,"53-63",IF(Таблица3[[#This Row],[Степень зрелости вспом]]<67,"64-66",IF(Таблица3[[#This Row],[Степень зрелости вспом]]<85,"67-85",)))))) -> 53-63 | AD104: Высший | AE104: 115 | AF104: 46182 | AG104: 101 | AH104: =IFERROR(VLOOKUP(Таблица3[[#This Row],[№ акта]],'Степень зрелости 2026'!$H$12:$I$800,2,FALSE),) -> 54 | AJ104: 115 | AK104: 46182 | AL104: 175 | AO104: 13270 | AP104: 11611.3 | AQ104: Горошек овощной 2026 (богара) | AR104: Увертюра | AS104: А-22/1 | AT104: Извеков Владимир Владимирович | AV104: Н378ХЕ | AX104: А-22/1 | AY104: Увертюра | AZ104: 2 | BA104: ГРК (богара) | BB104: богара | BC104: 6 | BD104: 46182 | BG104: 53-63 | BH104: Высший | BI104: 101 | BJ104: 54
A105: Степень зрелости | C105: =Таблица3[[#This Row],[Степень зрелости вспом]] -> 53 | D105: 176 | G105: 13030 | I105: 11448 | J105: Горошек овощной 2026 (богара) | K105: Увертюра | L105: А-23 | M105: Магадиев Александр Сайлаувич | R105: У184НО | T105: =VLOOKUP(Таблица3[[#This Row],[№ акта]],$AJ$1:$BJ$691,15,FALSE) -> А-23 | U105: =VLOOKUP(Таблица3[[#This Row],[№ акта]],$AJ$1:$BJ$691,16,FALSE) -> Увертюра | V105: =VLOOKUP(Таблица3[[#This Row],[№ акта]],$AJ$1:$BJ$691,17,FALSE) -> 1.9 | W105: =VLOOKUP(Таблица3[[#This Row],[№ акта]],$AJ$1:$BJ$691,18,FALSE) -> ГРК (богара) | X105: =VLOOKUP(Таблица3[[#This Row],[№ акта]],$AJ$1:$BJ$691,19,FALSE) -> богара | Y105: =VLOOKUP(Таблица3[[#This Row],[№ акта]],$AJ$1:$BJ$691,20,FALSE) -> 6 | Z105: =VLOOKUP(Таблица3[[#This Row],[№ акта]],$AJ$1:$BJ$691,21,FALSE) -> 46182 | AA105: =Таблица3[[#This Row],[Регистратор.Вес нетто]] -> 13030 | AB105: =IF(VLOOKUP(Таблица3[[#This Row],[№ акта]],$AJ$1:$BJ$691,23,FALSE)<>0,VLOOKUP(Таблица3[[#This Row],[№ акта]],$AJ$1:$BJ$691,23,FALSE),"-") -> ГРАНД-СТАР ООО | AC105: =IF(Таблица3[[#This Row],[Степень зрелости вспом]]=0,"нет данных",IF(Таблица3[[#This Row],[Степень зрелости вспом]]<40,"до 40",IF(Таблица3[[#This Row],[Степень зрелости вспом]]<53,"40-52",IF(Таблица3[[#This Row],[Степень зрелости вспом]]<64,"53-63",IF(Таблица3[[#This Row],[Степень зрелости вспом]]<67,"64-66",IF(Таблица3[[#This Row],[Степень зрелости вспом]]<85,"67-85",)))))) -> 53-63 | AD105: Высший | AE105: 270 | AF105: 46182 | AG105: 176/3 | AH105: =IFERROR(VLOOKUP(Таблица3[[#This Row],[№ акта]],'Степень зрелости 2026'!$H$12:$I$800,2,FALSE),) -> 53 | AJ105: 270 | AK105: 46182 | AL105: 176 | AO105: 13030 | AP105: 11448 | AQ105: Горошек овощной 2026 (богара) | AR105: Увертюра | AS105: А-23 | AT105: Магадиев Александр Сайлаувич | AV105: У184НО | AX105: А-23 | AY105: Увертюра | AZ105: 1.9 | BA105: ГРК (богара) | BB105: богара | BC105: 6 | BD105: 46182 | BE105: 13030 | BF105: ГРАНД-СТАР ООО | BG105: 53-63 | BH105: Высший | BI105: 176/3 | BJ105: 53
A106: Степень зрелости | C106: =Таблица3[[#This Row],[Степень зрелости вспом]] -> 50 | D106: 177 | G106: 13100 | I106: 11283 | J106: Горошек овощной 2026 (богара) | K106: Увертюра | L106: А-23 | M106: Кулинич Евгений Владимирович | R106: У801СТ | T106: =VLOOKUP(Таблица3[[#This Row],[№ акта]],$AJ$1:$BJ$691,15,FALSE) -> А-23 | U106: =VLOOKUP(Таблица3[[#This Row],[№ акта]],$AJ$1:$BJ$691,16,FALSE) -> Увертюра | V106: =VLOOKUP(Таблица3[[#This Row],[№ акта]],$AJ$1:$BJ$691,17,FALSE) -> 1.9 | W106: =VLOOKUP(Таблица3[[#This Row],[№ акта]],$AJ$1:$BJ$691,18,FALSE) -> ГРК (богара) | X106: =VLOOKUP(Таблица3[[#This Row],[№ акта]],$AJ$1:$BJ$691,19,FALSE) -> богара | Y106: =VLOOKUP(Таблица3[[#This Row],[№ акта]],$AJ$1:$BJ$691,20,FALSE) -> 6 | Z106: =VLOOKUP(Таблица3[[#This Row],[№ акта]],$AJ$1:$BJ$691,21,FALSE) -> 46182 | AA106: =Таблица3[[#This Row],[Регистратор.Вес нетто]] -> 13100 | AB106: =IF(VLOOKUP(Таблица3[[#This Row],[№ акта]],$AJ$1:$BJ$691,23,FALSE)<>0,VLOOKUP(Таблица3[[#This Row],[№ акта]],$AJ$1:$BJ$691,23,FALSE),"-") -> ГРАНД-СТАР ООО | AC106: =IF(Таблица3[[#This Row],[Степень зрелости вспом]]=0,"нет данных",IF(Таблица3[[#This Row],[Степень зрелости вспом]]<40,"до 40",IF(Таблица3[[#This Row],[Степень зрелости вспом]]<53,"40-52",IF(Таблица3[[#This Row],[Степень зрелости вспом]]<64,"53-63",IF(Таблица3[[#This Row],[Степень зрелости вспом]]<67,"64-66",IF(Таблица3[[#This Row],[Степень зрелости вспом]]<85,"67-85",)))))) -> 40-52 | AD106: Высший | AE106: 271 | AF106: 46182 | AG106: 177/4 | AH106: =IFERROR(VLOOKUP(Таблица3[[#This Row],[№ акта]],'Степень зрелости 2026'!$H$12:$I$800,2,FALSE),) -> 50 | AJ106: 271 | AK106: 46182 | AL106: 177 | AO106: 13100 | AP106: 11283 | AQ106: Горошек овощной 2026 (богара) | AR106: Увертюра | AS106: А-23 | AT106: Кулинич Евгений Владимирович | AV106: У801СТ | AX106: А-23 | AY106: Увертюра | AZ106: 1.9 | BA106: ГРК (богара) | BB106: богара | BC106: 6 | BD106: 46182 | BE106: 13100 | BF106: ГРАНД-СТАР ООО | BG106: 40-52 | BH106: Высший | BI106: 177/4 | BJ106: 50
A107: Степень зрелости | C107: =Таблица3[[#This Row],[Степень зрелости вспом]] -> 55 | D107: 178 | G107: 12880 | I107: 11527.6 | J107: Горошек овощной 2026 (богара) | K107: Увертюра | L107: А-22/1 | M107: Гуйда Николай Николаевич | R107: А816ЕВ | T107: =VLOOKUP(Таблица3[[#This Row],[№ акта]],$AJ$1:$BJ$691,15,FALSE) -> А-22/1 | U107: =VLOOKUP(Таблица3[[#This Row],[№ акта]],$AJ$1:$BJ$691,16,FALSE) -> Увертюра | V107: =VLOOKUP(Таблица3[[#This Row],[№ акта]],$AJ$1:$BJ$691,17,FALSE) -> 1.9 | W107: =VLOOKUP(Таблица3[[#This Row],[№ акта]],$AJ$1:$BJ$691,18,FALSE) -> ГРК (богара) | X107: =VLOOKUP(Таблица3[[#This Row],[№ акта]],$AJ$1:$BJ$691,19,FALSE) -> богара | Y107: =VLOOKUP(Таблица3[[#This Row],[№ акта]],$AJ$1:$BJ$691,20,FALSE) -> 6 | Z107: =VLOOKUP(Таблица3[[#This Row],[№ акта]],$AJ$1:$BJ$691,21,FALSE) -> 46182 | AB107: =IF(VLOOKUP(Таблица3[[#This Row],[№ акта]],$AJ$1:$BJ$691,23,FALSE)<>0,VLOOKUP(Таблица3[[#This Row],[№ акта]],$AJ$1:$BJ$691,23,FALSE),"-") -> - | AC107: =IF(Таблица3[[#This Row],[Степень зрелости вспом]]=0,"нет данных",IF(Таблица3[[#This Row],[Степень зрелости вспом]]<40,"до 40",IF(Таблица3[[#This Row],[Степень зрелости вспом]]<53,"40-52",IF(Таблица3[[#This Row],[Степень зрелости вспом]]<64,"53-63",IF(Таблица3[[#This Row],[Степень зрелости вспом]]<67,"64-66",IF(Таблица3[[#This Row],[Степень зрелости вспом]]<85,"67-85",)))))) -> 53-63 | AD107: Высший | AE107: 116 | AF107: 46182 | AG107: 102 | AH107: =IFERROR(VLOOKUP(Таблица3[[#This Row],[№ акта]],'Степень зрелости 2026'!$H$12:$I$800,2,FALSE),) -> 55 | AJ107: 116 | AK107: 46182 | AL107: 178 | AO107: 12880 | AP107: 11527.6 | AQ107: Горошек овощной 2026 (богара) | AR107: Увертюра | AS107: А-22/1 | AT107: Гуйда Николай Николаевич | AV107: А816ЕВ | AX107: А-22/1 | AY107: Увертюра | AZ107: 1.9 | BA107: ГРК (богара) | BB107: богара | BC107: 6 | BD107: 46182 | BG107: 53-63 | BH107: Высший | BI107: 102 | BJ107: 55
A108: Степень зрелости | C108: =Таблица3[[#This Row],[Степень зрелости вспом]] -> 56 | D108: 179 | G108: 12970 | I108: 10700.3 | J108: Горошек овощной 2026 (богара) | K108: Увертюра | L108: А-22/1 | M108: Рудик Александр Иванович | R108: А309АТ | T108: =VLOOKUP(Таблица3[[#This Row],[№ акта]],$AJ$1:$BJ$691,15,FALSE) -> А-22/1 | U108: =VLOOKUP(Таблица3[[#This Row],[№ акта]],$AJ$1:$BJ$691,16,FALSE) -> Увертюра | V108: =VLOOKUP(Таблица3[[#This Row],[№ акта]],$AJ$1:$BJ$691,17,FALSE) -> 1.9 | W108: =VLOOKUP(Таблица3[[#This Row],[№ акта]],$AJ$1:$BJ$691,18,FALSE) -> ГРК (богара) | X108: =VLOOKUP(Таблица3[[#This Row],[№ акта]],$AJ$1:$BJ$691,19,FALSE) -> богара | Y108: =VLOOKUP(Таблица3[[#This Row],[№ акта]],$AJ$1:$BJ$691,20,FALSE) -> 6 | Z108: =VLOOKUP(Таблица3[[#This Row],[№ акта]],$AJ$1:$BJ$691,21,FALSE) -> 46182 | AB108: =IF(VLOOKUP(Таблица3[[#This Row],[№ акта]],$AJ$1:$BJ$691,23,FALSE)<>0,VLOOKUP(Таблица3[[#This Row],[№ акта]],$AJ$1:$BJ$691,23,FALSE),"-") -> - | AC108: =IF(Таблица3[[#This Row],[Степень зрелости вспом]]=0,"нет данных",IF(Таблица3[[#This Row],[Степень зрелости вспом]]<40,"до 40",IF(Таблица3[[#This Row],[Степень зрелости вспом]]<53,"40-52",IF(Таблица3[[#This Row],[Степень зрелости вспом]]<64,"53-63",IF(Таблица3[[#This Row],[Степень зрелости вспом]]<67,"64-66",IF(Таблица3[[#This Row],[Степень зрелости вспом]]<85,"67-85",)))))) -> 53-63 | AD108: Высший | AE108: 117 | AF108: 46182 | AG108: 103 | AH108: =IFERROR(VLOOKUP(Таблица3[[#This Row],[№ акта]],'Степень зрелости 2026'!$H$12:$I$800,2,FALSE),) -> 56 | AJ108: 117 | AK108: 46182 | AL108: 179 | AO108: 12970 | AP108: 10700.3 | AQ108: Горошек овощной 2026 (богара) | AR108: Увертюра | AS108: А-22/1 | AT108: Рудик Александр Иванович | AV108: А309АТ | AX108: А-22/1 | AY108: Увертюра | AZ108: 1.9 | BA108: ГРК (богара) | BB108: богара | BC108: 6 | BD108: 46182 | BG108: 53-63 | BH108: Высший | BI108: 103 | BJ108: 56
A109: Степень зрелости | C109: =Таблица3[[#This Row],[Степень зрелости вспом]] -> 55 | D109: 180 | G109: 15420 | I109: 13338.3 | J109: Горошек овощной 2026 (богара) | K109: Увертюра | L109: А-22/1 | M109: Ревенко Андрей Вячеславович | R109: А781РР | T109: =VLOOKUP(Таблица3[[#This Row],[№ акта]],$AJ$1:$BJ$691,15,FALSE) -> А-22/1 | U109: =VLOOKUP(Таблица3[[#This Row],[№ акта]],$AJ$1:$BJ$691,16,FALSE) -> Увертюра | V109: =VLOOKUP(Таблица3[[#This Row],[№ акта]],$AJ$1:$BJ$691,17,FALSE) -> 2.4 | W109: =VLOOKUP(Таблица3[[#This Row],[№ акта]],$AJ$1:$BJ$691,18,FALSE) -> ГРК (богара) | X109: =VLOOKUP(Таблица3[[#This Row],[№ акта]],$AJ$1:$BJ$691,19,FALSE) -> богара | Y109: =VLOOKUP(Таблица3[[#This Row],[№ акта]],$AJ$1:$BJ$691,20,FALSE) -> 6 | Z109: =VLOOKUP(Таблица3[[#This Row],[№ акта]],$AJ$1:$BJ$691,21,FALSE) -> 46182 | AB109: =IF(VLOOKUP(Таблица3[[#This Row],[№ акта]],$AJ$1:$BJ$691,23,FALSE)<>0,VLOOKUP(Таблица3[[#This Row],[№ акта]],$AJ$1:$BJ$691,23,FALSE),"-") -> - | AC109: =IF(Таблица3[[#This Row],[Степень зрелости вспом]]=0,"нет данных",IF(Таблица3[[#This Row],[Степень зрелости вспом]]<40,"до 40",IF(Таблица3[[#This Row],[Степень зрелости вспом]]<53,"40-52",IF(Таблица3[[#This Row],[Степень зрелости вспом]]<64,"53-63",IF(Таблица3[[#This Row],[Степень зрелости вспом]]<67,"64-66",IF(Таблица3[[#This Row],[Степень зрелости вспом]]<85,"67-85",)))))) -> 53-63 | AD109: Высший | AE109: 118 | AF109: 46182 | AG109: 104 | AH109: =IFERROR(VLOOKUP(Таблица3[[#This Row],[№ акта]],'Степень зрелости 2026'!$H$12:$I$800,2,FALSE),) -> 55 | AJ109: 118 | AK109: 46182 | AL109: 180 | AO109: 15420 | AP109: 13338.3 | AQ109: Горошек овощной 2026 (богара) | AR109: Увертюра | AS109: А-22/1 | AT109: Ревенко Андрей Вячеславович | AV109: А781РР | AX109: А-22/1 | AY109: Увертюра | AZ109: 2.4 | BA109: ГРК (богара) | BB109: богара | BC109: 6 | BD109: 46182 | BG109: 53-63 | BH109: Высший | BI109: 104 | BJ109: 55
A110: Степень зрелости | C110: =Таблица3[[#This Row],[Степень зрелости вспом]] -> 55 | D110: 181 | G110: 4250 | I110: 3591.2 | J110: Горошек овощной 2026 (богара) | K110: Увертюра | L110: А-23 | M110: Роговской Роман Алексеевич | R110: Т945РВ | T110: =VLOOKUP(Таблица3[[#This Row],[№ акта]],$AJ$1:$BJ$691,15,FALSE) -> А-23 | U110: =VLOOKUP(Таблица3[[#This Row],[№ акта]],$AJ$1:$BJ$691,16,FALSE) -> Увертюра | V110: =VLOOKUP(Таблица3[[#This Row],[№ акта]],$AJ$1:$BJ$691,17,FALSE) -> 0.7 | W110: =VLOOKUP(Таблица3[[#This Row],[№ акта]],$AJ$1:$BJ$691,18,FALSE) -> ГРК (богара) | X110: =VLOOKUP(Таблица3[[#This Row],[№ акта]],$AJ$1:$BJ$691,19,FALSE) -> богара | Y110: =VLOOKUP(Таблица3[[#This Row],[№ акта]],$AJ$1:$BJ$691,20,FALSE) -> 7 | Z110: =VLOOKUP(Таблица3[[#This Row],[№ акта]],$AJ$1:$BJ$691,21,FALSE) -> 46183 | AB110: =IF(VLOOKUP(Таблица3[[#This Row],[№ акта]],$AJ$1:$BJ$691,23,FALSE)<>0,VLOOKUP(Таблица3[[#This Row],[№ акта]],$AJ$1:$BJ$691,23,FALSE),"-") -> - | AC110: =IF(Таблица3[[#This Row],[Степень зрелости вспом]]=0,"нет данных",IF(Таблица3[[#This Row],[Степень зрелости вспом]]<40,"до 40",IF(Таблица3[[#This Row],[Степень зрелости вспом]]<53,"40-52",IF(Таблица3[[#This Row],[Степень зрелости вспом]]<64,"53-63",IF(Таблица3[[#This Row],[Степень зрелости вспом]]<67,"64-66",IF(Таблица3[[#This Row],[Степень зрелости вспом]]<85,"67-85",)))))) -> 53-63 | AD110: Высший | AE110: 119 | AF110: 46183 | AG110: 105 | AH110: =IFERROR(VLOOKUP(Таблица3[[#This Row],[№ акта]],'Степень зрелости 2026'!$H$12:$I$800,2,FALSE),) -> 55 | AJ110: 119 | AK110: 46183 | AL110: 181 | AO110: 4250 | AP110: 3591.2 | AQ110: Горошек овощной 2026 (богара) | AR110: Увертюра | AS110: А-23 | AT110: Роговской Роман Алексеевич | AV110: Т945РВ | AX110: А-23 | AY110: Увертюра | AZ110: 0.7 | BA110: ГРК (богара) | BB110: богара | BC110: 7 | BD110: 46183 | BG110: 53-63 | BH110: Высший | BI110: 105 | BJ110: 55
C111: =Таблица3[[#This Row],[Степень зрелости вспом]] -> 56 | D111: 182 | G111: 12980 | I111: 10968.1 | J111: Горошек овощной 2026 (богара) | K111: Увертюра | L111: А-23 | M111: Извеков Владимир Владимирович | R111: Н378ХЕ | T111: =VLOOKUP(Таблица3[[#This Row],[№ акта]],$AJ$1:$BJ$691,15,FALSE) -> А-23 | U111: =VLOOKUP(Таблица3[[#This Row],[№ акта]],$AJ$1:$BJ$691,16,FALSE) -> Увертюра | V111: =VLOOKUP(Таблица3[[#This Row],[№ акта]],$AJ$1:$BJ$691,17,FALSE) -> 2 | W111: =VLOOKUP(Таблица3[[#This Row],[№ акта]],$AJ$1:$BJ$691,18,FALSE) -> ГРК (богара) | X111: =VLOOKUP(Таблица3[[#This Row],[№ акта]],$AJ$1:$BJ$691,19,FALSE) -> богара | Y111: =VLOOKUP(Таблица3[[#This Row],[№ акта]],$AJ$1:$BJ$691,20,FALSE) -> 7 | Z111: =VLOOKUP(Таблица3[[#This Row],[№ акта]],$AJ$1:$BJ$691,21,FALSE) -> 46183 | AB111: =IF(VLOOKUP(Таблица3[[#This Row],[№ акта]],$AJ$1:$BJ$691,23,FALSE)<>0,VLOOKUP(Таблица3[[#This Row],[№ акта]],$AJ$1:$BJ$691,23,FALSE),"-") -> - | AC111: =IF(Таблица3[[#This Row],[Степень зрелости вспом]]=0,"нет данных",IF(Таблица3[[#This Row],[Степень зрелости вспом]]<40,"до 40",IF(Таблица3[[#This Row],[Степень зрелости вспом]]<53,"40-52",IF(Таблица3[[#This Row],[Степень зрелости вспом]]<64,"53-63",IF(Таблица3[[#This Row],[Степень зрелости вспом]]<67,"64-66",IF(Таблица3[[#This Row],[Степень зрелости вспом]]<85,"67-85",)))))) -> 53-63 | AD111: Высший | AE111: 120 | AF111: 46183 | AG111: 106 | AH111: =IFERROR(VLOOKUP(Таблица3[[#This Row],[№ акта]],'Степень зрелости 2026'!$H$12:$I$800,2,FALSE),) -> 56 | AJ111: 120 | AK111: 46183 | AL111: 182 | AO111: 12980 | AP111: 10968.1 | AQ111: Горошек овощной 2026 (богара) | AR111: Увертюра | AS111: А-23 | AT111: Извеков Владимир Владимирович | AV111: Н378ХЕ | AX111: А-23 | AY111: Увертюра | AZ111: 2 | BA111: ГРК (богара) | BB111: богара | BC111: 7 | BD111: 46183 | BG111: 53-63 | BH111: Высший | BI111: 106 | BJ111: 56
A112: Степень зрелости | C112: =Таблица3[[#This Row],[Степень зрелости вспом]] -> 54 | D112: 184 | G112: 13060 | I112: 11688.7 | J112: Горошек овощной 2026 (богара) | K112: Увертюра | L112: А-23 | M112: Гуйда Николай Николаевич | R112: А816ЕВ | T112: =VLOOKUP(Таблица3[[#This Row],[№ акта]],$AJ$1:$BJ$691,15,FALSE) -> А-23 | U112: =VLOOKUP(Таблица3[[#This Row],[№ акта]],$AJ$1:$BJ$691,16,FALSE) -> Увертюра | V112: =VLOOKUP(Таблица3[[#This Row],[№ акта]],$AJ$1:$BJ$691,17,FALSE) -> 1.9 | W112: =VLOOKUP(Таблица3[[#This Row],[№ акта]],$AJ$1:$BJ$691,18,FALSE) -> ГРК (богара) | X112: =VLOOKUP(Таблица3[[#This Row],[№ акта]],$AJ$1:$BJ$691,19,FALSE) -> богара | Y112: =VLOOKUP(Таблица3[[#This Row],[№ акта]],$AJ$1:$BJ$691,20,FALSE) -> 6 | Z112: =VLOOKUP(Таблица3[[#This Row],[№ акта]],$AJ$1:$BJ$691,21,FALSE) -> 46182 | AB112: =IF(VLOOKUP(Таблица3[[#This Row],[№ акта]],$AJ$1:$BJ$691,23,FALSE)<>0,VLOOKUP(Таблица3[[#This Row],[№ акта]],$AJ$1:$BJ$691,23,FALSE),"-") -> - | AC112: =IF(Таблица3[[#This Row],[Степень зрелости вспом]]=0,"нет данных",IF(Таблица3[[#This Row],[Степень зрелости вспом]]<40,"до 40",IF(Таблица3[[#This Row],[Степень зрелости вспом]]<53,"40-52",IF(Таблица3[[#This Row],[Степень зрелости вспом]]<64,"53-63",IF(Таблица3[[#This Row],[Степень зрелости вспом]]<67,"64-66",IF(Таблица3[[#This Row],[Степень зрелости вспом]]<85,"67-85",)))))) -> 53-63 | AD112: Высший | AE112: 121 | AF112: 46183 | AG112: 107 | AH112: =IFERROR(VLOOKUP(Таблица3[[#This Row],[№ акта]],'Степень зрелости 2026'!$H$12:$I$800,2,FALSE),) -> 54 | AJ112: 121 | AK112: 46183 | AL112: 184 | AO112: 13060 | AP112: 11688.7 | AQ112: Горошек овощной 2026 (богара) | AR112: Увертюра | AS112: А-23 | AT112: Гуйда Николай Николаевич | AV112: А816ЕВ | AX112: А-23 | AY112: Увертюра | AZ112: 1.9 | BA112: ГРК (богара) | BB112: богара | BC112: 6 | BD112: 46182 | BG112: 53-63 | BH112: Высший | BI112: 107 | BJ112: 54
A113: Степень зрелости | C113: =Таблица3[[#This Row],[Степень зрелости вспом]] -> 54 | D113: 185 | G113: 12930 | I113: 11701.6 | J113: Горошек овощной 2026 (богара) | K113: Увертюра | L113: А-23 | M113: Рудик Александр Иванович | R113: А309АТ | T113: =VLOOKUP(Таблица3[[#This Row],[№ акта]],$AJ$1:$BJ$691,15,FALSE) -> А-23 | U113: =VLOOKUP(Таблица3[[#This Row],[№ акта]],$AJ$1:$BJ$691,16,FALSE) -> Увертюра | V113: =VLOOKUP(Таблица3[[#This Row],[№ акта]],$AJ$1:$BJ$691,17,FALSE) -> 1.9 | W113: =VLOOKUP(Таблица3[[#This Row],[№ акта]],$AJ$1:$BJ$691,18,FALSE) -> ГРК (богара) | X113: =VLOOKUP(Таблица3[[#This Row],[№ акта]],$AJ$1:$BJ$691,19,FALSE) -> богара | Y113: =VLOOKUP(Таблица3[[#This Row],[№ акта]],$AJ$1:$BJ$691,20,FALSE) -> 6 | Z113: =VLOOKUP(Таблица3[[#This Row],[№ акта]],$AJ$1:$BJ$691,21,FALSE) -> 46182 | AB113: =IF(VLOOKUP(Таблица3[[#This Row],[№ акта]],$AJ$1:$BJ$691,23,FALSE)<>0,VLOOKUP(Таблица3[[#This Row],[№ акта]],$AJ$1:$BJ$691,23,FALSE),"-") -> - | AC113: =IF(Таблица3[[#This Row],[Степень зрелости вспом]]=0,"нет данных",IF(Таблица3[[#This Row],[Степень зрелости вспом]]<40,"до 40",IF(Таблица3[[#This Row],[Степень зрелости вспом]]<53,"40-52",IF(Таблица3[[#This Row],[Степень зрелости вспом]]<64,"53-63",IF(Таблица3[[#This Row],[Степень зрелости вспом]]<67,"64-66",IF(Таблица3[[#This Row],[Степень зрелости вспом]]<85,"67-85",)))))) -> 53-63 | AD113: Высший | AE113: 122 | AF113: 46183 | AG113: 108 | AH113: =IFERROR(VLOOKUP(Таблица3[[#This Row],[№ акта]],'Степень зрелости 2026'!$H$12:$I$800,2,FALSE),) -> 54 | AJ113: 122 | AK113: 46183 | AL113: 185 | AO113: 12930 | AP113: 11701.6 | AQ113: Горошек овощной 2026 (богара) | AR113: Увертюра | AS113: А-23 | AT113: Рудик Александр Иванович | AV113: А309АТ | AX113: А-23 | AY113: Увертюра | AZ113: 1.9 | BA113: ГРК (богара) | BB113: богара | BC113: 6 | BD113: 46182 | BG113: 53-63 | BH113: Высший | BI113: 108 | BJ113: 54
C114: =Таблица3[[#This Row],[Степень зрелости вспом]] -> 56 | D114: 186 | G114: 12930 | I114: 10796.6 | J114: Горошек овощной 2026 (богара) | K114: Увертюра | L114: А-23 | M114: Ревенко Андрей Вячеславович | R114: А781РР | T114: =VLOOKUP(Таблица3[[#This Row],[№ акта]],$AJ$1:$BJ$691,15,FALSE) -> А-23 | U114: =VLOOKUP(Таблица3[[#This Row],[№ акта]],$AJ$1:$BJ$691,16,FALSE) -> Увертюра | V114: =VLOOKUP(Таблица3[[#This Row],[№ акта]],$AJ$1:$BJ$691,17,FALSE) -> 1.9 | W114: =VLOOKUP(Таблица3[[#This Row],[№ акта]],$AJ$1:$BJ$691,18,FALSE) -> ГРК (богара) | X114: =VLOOKUP(Таблица3[[#This Row],[№ акта]],$AJ$1:$BJ$691,19,FALSE) -> богара | Y114: =VLOOKUP(Таблица3[[#This Row],[№ акта]],$AJ$1:$BJ$691,20,FALSE) -> 6 | Z114: =VLOOKUP(Таблица3[[#This Row],[№ акта]],$AJ$1:$BJ$691,21,FALSE) -> 46182 | AB114: =IF(VLOOKUP(Таблица3[[#This Row],[№ акта]],$AJ$1:$BJ$691,23,FALSE)<>0,VLOOKUP(Таблица3[[#This Row],[№ акта]],$AJ$1:$BJ$691,23,FALSE),"-") -> - | AC114: =IF(Таблица3[[#This Row],[Степень зрелости вспом]]=0,"нет данных",IF(Таблица3[[#This Row],[Степень зрелости вспом]]<40,"до 40",IF(Таблица3[[#This Row],[Степень зрелости вспом]]<53,"40-52",IF(Таблица3[[#This Row],[Степень зрелости вспом]]<64,"53-63",IF(Таблица3[[#This Row],[Степень зрелости вспом]]<67,"64-66",IF(Таблица3[[#This Row],[Степень зрелости вспом]]<85,"67-85",)))))) -> 53-63 | AD114: Высший | AE114: 123 | AF114: 46183 | AG114: 109 | AH114: =IFERROR(VLOOKUP(Таблица3[[#This Row],[№ акта]],'Степень зрелости 2026'!$H$12:$I$800,2,FALSE),) -> 56 | AJ114: 123 | AK114: 46183 | AL114: 186 | AO114: 12930 | AP114: 10796.6 | AQ114: Горошек овощной 2026 (богара) | AR114: Увертюра | AS114: А-23 | AT114: Ревенко Андрей Вячеславович | AV114: А781РР | AX114: А-23 | AY114: Увертюра | AZ114: 1.9 | BA114: ГРК (богара) | BB114: богара | BC114: 6 | BD114: 46182 | BG114: 53-63 | BH114: Высший | BI114: 109 | BJ114: 56
A115: Степень зрелости | C115: =Таблица3[[#This Row],[Степень зрелости вспом]] -> 53 | D115: 187 | G115: 4420 | I115: 3734.9 | J115: Горошек овощной 2026 (богара) | K115: Увертюра | L115: А-23 | M115: Роговской Роман Алексеевич | R115: Т945РВ | T115: =VLOOKUP(Таблица3[[#This Row],[№ акта]],$AJ$1:$BJ$691,15,FALSE) -> А-23 | U115: =VLOOKUP(Таблица3[[#This Row],[№ акта]],$AJ$1:$BJ$691,16,FALSE) -> Увертюра | V115: =VLOOKUP(Таблица3[[#This Row],[№ акта]],$AJ$1:$BJ$691,17,FALSE) -> 0.5 | W115: =VLOOKUP(Таблица3[[#This Row],[№ акта]],$AJ$1:$BJ$691,18,FALSE) -> ГРК (богара) | X115: =VLOOKUP(Таблица3[[#This Row],[№ акта]],$AJ$1:$BJ$691,19,FALSE) -> богара | Y115: =VLOOKUP(Таблица3[[#This Row],[№ акта]],$AJ$1:$BJ$691,20,FALSE) -> 6 | Z115: =VLOOKUP(Таблица3[[#This Row],[№ акта]],$AJ$1:$BJ$691,21,FALSE) -> 46182 | AB115: =IF(VLOOKUP(Таблица3[[#This Row],[№ акта]],$AJ$1:$BJ$691,23,FALSE)<>0,VLOOKUP(Таблица3[[#This Row],[№ акта]],$AJ$1:$BJ$691,23,FALSE),"-") -> - | AC115: =IF(Таблица3[[#This Row],[Степень зрелости вспом]]=0,"нет данных",IF(Таблица3[[#This Row],[Степень зрелости вспом]]<40,"до 40",IF(Таблица3[[#This Row],[Степень зрелости вспом]]<53,"40-52",IF(Таблица3[[#This Row],[Степень зрелости вспом]]<64,"53-63",IF(Таблица3[[#This Row],[Степень зрелости вспом]]<67,"64-66",IF(Таблица3[[#This Row],[Степень зрелости вспом]]<85,"67-85",)))))) -> 53-63 | AD115: Высший | AE115: 124 | AF115: 46183 | AG115: 110 | AH115: =IFERROR(VLOOKUP(Таблица3[[#This Row],[№ акта]],'Степень зрелости 2026'!$H$12:$I$800,2,FALSE),) -> 53 | AJ115: 124 | AK115: 46183 | AL115: 187 | AO115: 4420 | AP115: 3734.9 | AQ115: Горошек овощной 2026 (богара) | AR115: Увертюра | AS115: А-23 | AT115: Роговской Роман Алексеевич | AV115: Т945РВ | AX115: А-23 | AY115: Увертюра | AZ115: 0.5 | BA115: ГРК (богара) | BB115: богара | BC115: 6 | BD115: 46182 | BG115: 53-63 | BH115: Высший | BI115: 110 | BJ115: 53
A116: Степень зрелости | C116: =Таблица3[[#This Row],[Степень зрелости вспом]] -> 55 | D116: 189 | G116: 13160 | I116: 11383.4 | J116: Горошек овощной 2026 (богара) | K116: Увертюра | L116: А-23 | M116: Черевко Александр Владимирович | R116: А114МК | T116: =VLOOKUP(Таблица3[[#This Row],[№ акта]],$AJ$1:$BJ$691,15,FALSE) -> А-23 | U116: =VLOOKUP(Таблица3[[#This Row],[№ акта]],$AJ$1:$BJ$691,16,FALSE) -> Увертюра | V116: =VLOOKUP(Таблица3[[#This Row],[№ акта]],$AJ$1:$BJ$691,17,FALSE) -> 2.1 | W116: =VLOOKUP(Таблица3[[#This Row],[№ акта]],$AJ$1:$BJ$691,18,FALSE) -> ГРК (богара) | X116: =VLOOKUP(Таблица3[[#This Row],[№ акта]],$AJ$1:$BJ$691,19,FALSE) -> богара | Y116: =VLOOKUP(Таблица3[[#This Row],[№ акта]],$AJ$1:$BJ$691,20,FALSE) -> 7 | Z116: =VLOOKUP(Таблица3[[#This Row],[№ акта]],$AJ$1:$BJ$691,21,FALSE) -> 46183 | AB116: =IF(VLOOKUP(Таблица3[[#This Row],[№ акта]],$AJ$1:$BJ$691,23,FALSE)<>0,VLOOKUP(Таблица3[[#This Row],[№ акта]],$AJ$1:$BJ$691,23,FALSE),"-") -> - | AC116: =IF(Таблица3[[#This Row],[Степень зрелости вспом]]=0,"нет данных",IF(Таблица3[[#This Row],[Степень зрелости вспом]]<40,"до 40",IF(Таблица3[[#This Row],[Степень зрелости вспом]]<53,"40-52",IF(Таблица3[[#This Row],[Степень зрелости вспом]]<64,"53-63",IF(Таблица3[[#This Row],[Степень зрелости вспом]]<67,"64-66",IF(Таблица3[[#This Row],[Степень зрелости вспом]]<85,"67-85",)))))) -> 53-63 | AD116: Высший | AE116: 125 | AF116: 46183 | AG116: 111 | AH116: =IFERROR(VLOOKUP(Таблица3[[#This Row],[№ акта]],'Степень зрелости 2026'!$H$12:$I$800,2,FALSE),) -> 55 | AJ116: 125 | AK116: 46183 | AL116: 189 | AO116: 13160 | AP116: 11383.4 | AQ116: Горошек овощной 2026 (богара) | AR116: Увертюра | AS116: А-23 | AT116: Черевко Александр Владимирович | AV116: А114МК | AX116: А-23 | AY116: Увертюра | AZ116: 2.1 | BA116: ГРК (богара) | BB116: богара | BC116: 7 | BD116: 46183 | BG116: 53-63 | BH116: Высший | BI116: 111 | BJ116: 55
A117: Степень зрелости | C117: =Таблица3[[#This Row],[Степень зрелости вспом]] -> 57 | D117: 190 | G117: 12700 | I117: 10985.5 | J117: Горошек овощной 2026 (богара) | K117: Увертюра | L117: А-23 | M117: Богучарский А. И. | R117: А718ВХ | T117: =VLOOKUP(Таблица3[[#This Row],[№ акта]],$AJ$1:$BJ$691,15,FALSE) -> А-23 | U117: =VLOOKUP(Таблица3[[#This Row],[№ акта]],$AJ$1:$BJ$691,16,FALSE) -> Увертюра | V117: =VLOOKUP(Таблица3[[#This Row],[№ акта]],$AJ$1:$BJ$691,17,FALSE) -> 2 | W117: =VLOOKUP(Таблица3[[#This Row],[№ акта]],$AJ$1:$BJ$691,18,FALSE) -> ГРК (богара) | X117: =VLOOKUP(Таблица3[[#This Row],[№ акта]],$AJ$1:$BJ$691,19,FALSE) -> богара | Y117: =VLOOKUP(Таблица3[[#This Row],[№ акта]],$AJ$1:$BJ$691,20,FALSE) -> 7 | Z117: =VLOOKUP(Таблица3[[#This Row],[№ акта]],$AJ$1:$BJ$691,21,FALSE) -> 46183 | AB117: =IF(VLOOKUP(Таблица3[[#This Row],[№ акта]],$AJ$1:$BJ$691,23,FALSE)<>0,VLOOKUP(Таблица3[[#This Row],[№ акта]],$AJ$1:$BJ$691,23,FALSE),"-") -> - | AC117: =IF(Таблица3[[#This Row],[Степень зрелости вспом]]=0,"нет данных",IF(Таблица3[[#This Row],[Степень зрелости вспом]]<40,"до 40",IF(Таблица3[[#This Row],[Степень зрелости вспом]]<53,"40-52",IF(Таблица3[[#This Row],[Степень зрелости вспом]]<64,"53-63",IF(Таблица3[[#This Row],[Степень зрелости вспом]]<67,"64-66",IF(Таблица3[[#This Row],[Степень зрелости вспом]]<85,"67-85",)))))) -> 53-63 | AD117: Высший | AE117: 126 | AF117: 46183 | AG117: 112 | AH117: =IFERROR(VLOOKUP(Таблица3[[#This Row],[№ акта]],'Степень зрелости 2026'!$H$12:$I$800,2,FALSE),) -> 57 | AJ117: 126 | AK117: 46183 | AL117: 190 | AO117: 12700 | AP117: 10985.5 | AQ117: Горошек овощной 2026 (богара) | AR117: Увертюра | AS117: А-23 | AT117: Богучарский А. И. | AV117: А718ВХ | AX117: А-23 | AY117: Увертюра | AZ117: 2 | BA117: ГРК (богара) | BB117: богара | BC117: 7 | BD117: 46183 | BG117: 53-63 | BH117: Высший | BI117: 112 | BJ117: 57
A118: Степень зрелости | C118: =Таблица3[[#This Row],[Степень зрелости вспом]] -> 57 | D118: 192 | G118: 13380 | I118: 11439.9 | J118: Горошек овощной 2026 (богара) | K118: Увертюра | L118: А-23 | M118: Кудря Евгений | R118: А719ОО | T118: =VLOOKUP(Таблица3[[#This Row],[№ акта]],$AJ$1:$BJ$691,15,FALSE) -> А-23 | U118: =VLOOKUP(Таблица3[[#This Row],[№ акта]],$AJ$1:$BJ$691,16,FALSE) -> Увертюра | V118: =VLOOKUP(Таблица3[[#This Row],[№ акта]],$AJ$1:$BJ$691,17,FALSE) -> 2.1 | W118: =VLOOKUP(Таблица3[[#This Row],[№ акта]],$AJ$1:$BJ$691,18,FALSE) -> ГРК (богара) | X118: =VLOOKUP(Таблица3[[#This Row],[№ акта]],$AJ$1:$BJ$691,19,FALSE) -> богара | Y118: =VLOOKUP(Таблица3[[#This Row],[№ акта]],$AJ$1:$BJ$691,20,FALSE) -> 7 | Z118: =VLOOKUP(Таблица3[[#This Row],[№ акта]],$AJ$1:$BJ$691,21,FALSE) -> 46183 | AB118: =IF(VLOOKUP(Таблица3[[#This Row],[№ акта]],$AJ$1:$BJ$691,23,FALSE)<>0,VLOOKUP(Таблица3[[#This Row],[№ акта]],$AJ$1:$BJ$691,23,FALSE),"-") -> - | AC118: =IF(Таблица3[[#This Row],[Степень зрелости вспом]]=0,"нет данных",IF(Таблица3[[#This Row],[Степень зрелости вспом]]<40,"до 40",IF(Таблица3[[#This Row],[Степень зрелости вспом]]<53,"40-52",IF(Таблица3[[#This Row],[Степень зрелости вспом]]<64,"53-63",IF(Таблица3[[#This Row],[Степень зрелости вспом]]<67,"64-66",IF(Таблица3[[#This Row],[Степень зрелости вспом]]<85,"67-85",)))))) -> 53-63 | AD118: Высший | AE118: 127 | AF118: 46183 | AG118: 113 | AH118: =IFERROR(VLOOKUP(Таблица3[[#This Row],[№ акта]],'Степень зрелости 2026'!$H$12:$I$800,2,FALSE),) -> 57 | AJ118: 127 | AK118: 46183 | AL118: 192 | AO118: 13380 | AP118: 11439.9 | AQ118: Горошек овощной 2026 (богара) | AR118: Увертюра | AS118: А-23 | AT118: Кудря Евгений | AV118: А719ОО | AX118: А-23 | AY118: Увертюра | AZ118: 2.1 | BA118: ГРК (богара) | BB118: богара | BC118: 7 | BD118: 46183 | BG118: 53-63 | BH118: Высший | BI118: 113 | BJ118: 57
A119: Степень зрелости | C119: =Таблица3[[#This Row],[Степень зрелости вспом]] -> 53 | D119: 193 | G119: 8650 | I119: 7612 | J119: Горошек овощной 2026 (богара) | K119: Увертюра | L119: А-23 | M119: Чигрин Н.А. | R119: А819ЕВ | T119: =VLOOKUP(Таблица3[[#This Row],[№ акта]],$AJ$1:$BJ$691,15,FALSE) -> А-23 | U119: =VLOOKUP(Таблица3[[#This Row],[№ акта]],$AJ$1:$BJ$691,16,FALSE) -> Увертюра | V119: =VLOOKUP(Таблица3[[#This Row],[№ акта]],$AJ$1:$BJ$691,17,FALSE) -> 1.1 | W119: =VLOOKUP(Таблица3[[#This Row],[№ акта]],$AJ$1:$BJ$691,18,FALSE) -> ГРК (богара) | X119: =VLOOKUP(Таблица3[[#This Row],[№ акта]],$AJ$1:$BJ$691,19,FALSE) -> богара | Y119: =VLOOKUP(Таблица3[[#This Row],[№ акта]],$AJ$1:$BJ$691,20,FALSE) -> 7 | Z119: =VLOOKUP(Таблица3[[#This Row],[№ акта]],$AJ$1:$BJ$691,21,FALSE) -> 46183 | AB119: =IF(VLOOKUP(Таблица3[[#This Row],[№ акта]],$AJ$1:$BJ$691,23,FALSE)<>0,VLOOKUP(Таблица3[[#This Row],[№ акта]],$AJ$1:$BJ$691,23,FALSE),"-") -> - | AC119: =IF(Таблица3[[#This Row],[Степень зрелости вспом]]=0,"нет данных",IF(Таблица3[[#This Row],[Степень зрелости вспом]]<40,"до 40",IF(Таблица3[[#This Row],[Степень зрелости вспом]]<53,"40-52",IF(Таблица3[[#This Row],[Степень зрелости вспом]]<64,"53-63",IF(Таблица3[[#This Row],[Степень зрелости вспом]]<67,"64-66",IF(Таблица3[[#This Row],[Степень зрелости вспом]]<85,"67-85",)))))) -> 53-63 | AD119: Высший | AE119: 128 | AF119: 46183 | AG119: 114 | AH119: =IFERROR(VLOOKUP(Таблица3[[#This Row],[№ акта]],'Степень зрелости 2026'!$H$12:$I$800,2,FALSE),) -> 53 | AJ119: 128 | AK119: 46183 | AL119: 193 | AO119: 8650 | AP119: 7612 | AQ119: Горошек овощной 2026 (богара) | AR119: Увертюра | AS119: А-23 | AT119: Чигрин Н.А. | AV119: А819ЕВ | AX119: А-23 | AY119: Увертюра | AZ119: 1.1 | BA119: ГРК (богара) | BB119: богара | BC119: 7 | BD119: 46183 | BG119: 53-63 | BH119: Высший | BI119: 114 | BJ119: 53
A120: Степень зрелости | C120: =Таблица3[[#This Row],[Степень зрелости вспом]] -> 52 | D120: 194 | G120: 13430 | I120: 11111 | J120: Горошек овощной 2026 (богара) | K120: Авола | L120: А-38 | M120: Магадиев Александр Сайлаувич | R120: У184НО | T120: =VLOOKUP(Таблица3[[#This Row],[№ акта]],$AJ$1:$BJ$691,15,FALSE) -> А-38 | U120: =VLOOKUP(Таблица3[[#This Row],[№ акта]],$AJ$1:$BJ$691,16,FALSE) -> Авола | V120: =VLOOKUP(Таблица3[[#This Row],[№ акта]],$AJ$1:$BJ$691,17,FALSE) -> 1.7 | W120: =VLOOKUP(Таблица3[[#This Row],[№ акта]],$AJ$1:$BJ$691,18,FALSE) -> ГРК (богара) | X120: =VLOOKUP(Таблица3[[#This Row],[№ акта]],$AJ$1:$BJ$691,19,FALSE) -> богара | Y120: =VLOOKUP(Таблица3[[#This Row],[№ акта]],$AJ$1:$BJ$691,20,FALSE) -> 7 | Z120: =VLOOKUP(Таблица3[[#This Row],[№ акта]],$AJ$1:$BJ$691,21,FALSE) -> 46183 | AA120: =Таблица3[[#This Row],[Регистратор.Вес нетто]] -> 13430 | AB120: =IF(VLOOKUP(Таблица3[[#This Row],[№ акта]],$AJ$1:$BJ$691,23,FALSE)<>0,VLOOKUP(Таблица3[[#This Row],[№ акта]],$AJ$1:$BJ$691,23,FALSE),"-") -> ГРАНД-СТАР ООО | AC120: =IF(Таблица3[[#This Row],[Степень зрелости вспом]]=0,"нет данных",IF(Таблица3[[#This Row],[Степень зрелости вспом]]<40,"до 40",IF(Таблица3[[#This Row],[Степень зрелости вспом]]<53,"40-52",IF(Таблица3[[#This Row],[Степень зрелости вспом]]<64,"53-63",IF(Таблица3[[#This Row],[Степень зрелости вспом]]<67,"64-66",IF(Таблица3[[#This Row],[Степень зрелости вспом]]<85,"67-85",)))))) -> 40-52 | AD120: Высший | AE120: 274 | AF120: 46183 | AG120: 194/5 | AH120: =IFERROR(VLOOKUP(Таблица3[[#This Row],[№ акта]],'Степень зрелости 2026'!$H$12:$I$800,2,FALSE),) -> 52 | AJ120: 274 | AK120: 46183 | AL120: 194 | AO120: 13430 | AP120: 11111 | AQ120: Горошек овощной 2026 (богара) | AR120: Авола | AS120: А-38 | AT120: Магадиев Александр Сайлаувич | AV120: У184НО | AX120: А-38 | AY120: Авола | AZ120: 1.7 | BA120: ГРК (богара) | BB120: богара | BC120: 7 | BD120: 46183 | BE120: 13430 | BF120: ГРАНД-СТАР ООО | BG120: 40-52 | BH120: Высший | BI120: 194/5 | BJ120: 52
A121: Степень зрелости | C121: =Таблица3[[#This Row],[Степень зрелости вспом]] -> 50 | D121: 195 | G121: 12890 | I121: 10816 | J121: Горошек овощной 2026 (богара) | K121: Авола | L121: А-38 | M121: Кулинич Евгений Владимирович | R121: У801СТ | T121: =VLOOKUP(Таблица3[[#This Row],[№ акта]],$AJ$1:$BJ$691,15,FALSE) -> А-38 | U121: =VLOOKUP(Таблица3[[#This Row],[№ акта]],$AJ$1:$BJ$691,16,FALSE) -> Авола | V121: =VLOOKUP(Таблица3[[#This Row],[№ акта]],$AJ$1:$BJ$691,17,FALSE) -> 1.7 | W121: =VLOOKUP(Таблица3[[#This Row],[№ акта]],$AJ$1:$BJ$691,18,FALSE) -> ГРК (богара) | X121: =VLOOKUP(Таблица3[[#This Row],[№ акта]],$AJ$1:$BJ$691,19,FALSE) -> богара | Y121: =VLOOKUP(Таблица3[[#This Row],[№ акта]],$AJ$1:$BJ$691,20,FALSE) -> 7 | Z121: =VLOOKUP(Таблица3[[#This Row],[№ акта]],$AJ$1:$BJ$691,21,FALSE) -> 46183 | AA121: =Таблица3[[#This Row],[Регистратор.Вес нетто]] -> 12890 | AB121: =IF(VLOOKUP(Таблица3[[#This Row],[№ акта]],$AJ$1:$BJ$691,23,FALSE)<>0,VLOOKUP(Таблица3[[#This Row],[№ акта]],$AJ$1:$BJ$691,23,FALSE),"-") -> ГРАНД-СТАР ООО | AC121: =IF(Таблица3[[#This Row],[Степень зрелости вспом]]=0,"нет данных",IF(Таблица3[[#This Row],[Степень зрелости вспом]]<40,"до 40",IF(Таблица3[[#This Row],[Степень зрелости вспом]]<53,"40-52",IF(Таблица3[[#This Row],[Степень зрелости вспом]]<64,"53-63",IF(Таблица3[[#This Row],[Степень зрелости вспом]]<67,"64-66",IF(Таблица3[[#This Row],[Степень зрелости вспом]]<85,"67-85",)))))) -> 40-52 | AD121: Высший | AE121: 276 | AF121: 46183 | AG121: 195/6 | AH121: =IFERROR(VLOOKUP(Таблица3[[#This Row],[№ акта]],'Степень зрелости 2026'!$H$12:$I$800,2,FALSE),) -> 50 | AJ121: 276 | AK121: 46183 | AL121: 195 | AO121: 12890 | AP121: 10816 | AQ121: Горошек овощной 2026 (богара) | AR121: Авола | AS121: А-38 | AT121: Кулинич Евгений Владимирович | AV121: У801СТ | AX121: А-38 | AY121: Авола | AZ121: 1.7 | BA121: ГРК (богара) | BB121: богара | BC121: 7 | BD121: 46183 | BE121: 12890 | BF121: ГРАНД-СТАР ООО | BG121: 40-52 | BH121: Высший | BI121: 195/6 | BJ121: 50
A122: Степень зрелости | C122: =Таблица3[[#This Row],[Степень зрелости вспом]] -> 63 | D122: 196 | G122: 4430 | I122: 4142 | J122: Горошек овощной 2026 (богара) | K122: Авола | L122: А-112 | M122: Сайко Владимир Николаевич | R122: Т919РВ | T122: =VLOOKUP(Таблица3[[#This Row],[№ акта]],$AJ$1:$BJ$691,15,FALSE) -> А-112/1 | U122: =VLOOKUP(Таблица3[[#This Row],[№ акта]],$AJ$1:$BJ$691,16,FALSE) -> Авола | V122: =VLOOKUP(Таблица3[[#This Row],[№ акта]],$AJ$1:$BJ$691,17,FALSE) -> 1 | W122: =VLOOKUP(Таблица3[[#This Row],[№ акта]],$AJ$1:$BJ$691,18,FALSE) -> ГРК (богара) | X122: =VLOOKUP(Таблица3[[#This Row],[№ акта]],$AJ$1:$BJ$691,19,FALSE) -> богара | Y122: =VLOOKUP(Таблица3[[#This Row],[№ акта]],$AJ$1:$BJ$691,20,FALSE) -> 7 | Z122: =VLOOKUP(Таблица3[[#This Row],[№ акта]],$AJ$1:$BJ$691,21,FALSE) -> 46183 | AB122: =IF(VLOOKUP(Таблица3[[#This Row],[№ акта]],$AJ$1:$BJ$691,23,FALSE)<>0,VLOOKUP(Таблица3[[#This Row],[№ акта]],$AJ$1:$BJ$691,23,FALSE),"-") -> - | AC122: =IF(Таблица3[[#This Row],[Степень зрелости вспом]]=0,"нет данных",IF(Таблица3[[#This Row],[Степень зрелости вспом]]<40,"до 40",IF(Таблица3[[#This Row],[Степень зрелости вспом]]<53,"40-52",IF(Таблица3[[#This Row],[Степень зрелости вспом]]<64,"53-63",IF(Таблица3[[#This Row],[Степень зрелости вспом]]<67,"64-66",IF(Таблица3[[#This Row],[Степень зрелости вспом]]<85,"67-85",)))))) -> 53-63 | AD122: Первый | AE122: 129 | AF122: 46183 | AG122: 115 | AH122: =IFERROR(VLOOKUP(Таблица3[[#This Row],[№ акта]],'Степень зрелости 2026'!$H$12:$I$800,2,FALSE),) -> 63 | AJ122: 129 | AK122: 46183 | AL122: 196 | AO122: 4430 | AP122: 4142 | AQ122: Горошек овощной 2026 (богара) | AR122: Авола | AS122: А-112 | AT122: Сайко Владимир Николаевич | AV122: Т919РВ | AX122: А-112/1 | AY122: Авола | AZ122: 1 | BA122: ГРК (богара) | BB122: богара | BC122: 7 | BD122: 46183 | BG122: 53-63 | BH122: Высший | BI122: 115 | BJ122: 63
A123: Степень зрелости | C123: =Таблица3[[#This Row],[Степень зрелости вспом]] -> 59 | D123: 197 | G123: 13220 | I123: 11964.1 | J123: Горошек овощной 2026 (богара) | K123: Авола | L123: А-38 | M123: Черевко Александр Владимирович | R123: А114МК | T123: =VLOOKUP(Таблица3[[#This Row],[№ акта]],$AJ$1:$BJ$691,15,FALSE) -> А-38 | U123: =VLOOKUP(Таблица3[[#This Row],[№ акта]],$AJ$1:$BJ$691,16,FALSE) -> Авола | V123: =VLOOKUP(Таблица3[[#This Row],[№ акта]],$AJ$1:$BJ$691,17,FALSE) -> 1.7 | W123: =VLOOKUP(Таблица3[[#This Row],[№ акта]],$AJ$1:$BJ$691,18,FALSE) -> ГРК (богара) | X123: =VLOOKUP(Таблица3[[#This Row],[№ акта]],$AJ$1:$BJ$691,19,FALSE) -> богара | Y123: =VLOOKUP(Таблица3[[#This Row],[№ акта]],$AJ$1:$BJ$691,20,FALSE) -> 7 | Z123: =VLOOKUP(Таблица3[[#This Row],[№ акта]],$AJ$1:$BJ$691,21,FALSE) -> 46183 | AB123: =IF(VLOOKUP(Таблица3[[#This Row],[№ акта]],$AJ$1:$BJ$691,23,FALSE)<>0,VLOOKUP(Таблица3[[#This Row],[№ акта]],$AJ$1:$BJ$691,23,FALSE),"-") -> - | AC123: =IF(Таблица3[[#This Row],[Степень зрелости вспом]]=0,"нет данных",IF(Таблица3[[#This Row],[Степень зрелости вспом]]<40,"до 40",IF(Таблица3[[#This Row],[Степень зрелости вспом]]<53,"40-52",IF(Таблица3[[#This Row],[Степень зрелости вспом]]<64,"53-63",IF(Таблица3[[#This Row],[Степень зрелости вспом]]<67,"64-66",IF(Таблица3[[#This Row],[Степень зрелости вспом]]<85,"67-85",)))))) -> 53-63 | AD123: Высший | AE123: 130 | AF123: 46183 | AG123: 116 | AH123: =IFERROR(VLOOKUP(Таблица3[[#This Row],[№ акта]],'Степень зрелости 2026'!$H$12:$I$800,2,FALSE),) -> 59 | AJ123: 130 | AK123: 46183 | AL123: 197 | AO123: 13220 | AP123: 11964.1 | AQ123: Горошек овощной 2026 (богара) | AR123: Авола | AS123: А-38 | AT123: Черевко Александр Владимирович | AV123: А114МК | AX123: А-38 | AY123: Авола | AZ123: 1.7 | BA123: ГРК (богара) | BB123: богара | BC123: 7 | BD123: 46183 | BG123: 53-63 | BH123: Высший | BI123: 116 | BJ123: 59
A124: Степень зрелости | C124: =Таблица3[[#This Row],[Степень зрелости вспом]] -> 57 | D124: 199 | G124: 6800 | I124: 5984 | J124: Горошек овощной 2026 (богара) | K124: Авола | L124: А-111/1 | M124: Чигрин Н.А. | R124: А819ЕВ | T124: =VLOOKUP(Таблица3[[#This Row],[№ акта]],$AJ$1:$BJ$691,15,FALSE) -> А-111/1 | U124: =VLOOKUP(Таблица3[[#This Row],[№ акта]],$AJ$1:$BJ$691,16,FALSE) -> Авола | V124: =VLOOKUP(Таблица3[[#This Row],[№ акта]],$AJ$1:$BJ$691,17,FALSE) -> 1.2 | W124: =VLOOKUP(Таблица3[[#This Row],[№ акта]],$AJ$1:$BJ$691,18,FALSE) -> ГРК (богара) | X124: =VLOOKUP(Таблица3[[#This Row],[№ акта]],$AJ$1:$BJ$691,19,FALSE) -> богара | Y124: =VLOOKUP(Таблица3[[#This Row],[№ акта]],$AJ$1:$BJ$691,20,FALSE) -> 7 | Z124: =VLOOKUP(Таблица3[[#This Row],[№ акта]],$AJ$1:$BJ$691,21,FALSE) -> 46183 | AB124: =IF(VLOOKUP(Таблица3[[#This Row],[№ акта]],$AJ$1:$BJ$691,23,FALSE)<>0,VLOOKUP(Таблица3[[#This Row],[№ акта]],$AJ$1:$BJ$691,23,FALSE),"-") -> - | AC124: =IF(Таблица3[[#This Row],[Степень зрелости вспом]]=0,"нет данных",IF(Таблица3[[#This Row],[Степень зрелости вспом]]<40,"до 40",IF(Таблица3[[#This Row],[Степень зрелости вспом]]<53,"40-52",IF(Таблица3[[#This Row],[Степень зрелости вспом]]<64,"53-63",IF(Таблица3[[#This Row],[Степень зрелости вспом]]<67,"64-66",IF(Таблица3[[#This Row],[Степень зрелости вспом]]<85,"67-85",)))))) -> 53-63 | AD124: Высший | AE124: 131 | AF124: 46183 | AG124: 117 | AH124: =IFERROR(VLOOKUP(Таблица3[[#This Row],[№ акта]],'Степень зрелости 2026'!$H$12:$I$800,2,FALSE),) -> 57 | AJ124: 131 | AK124: 46183 | AL124: 199 | AO124: 6800 | AP124: 5984 | AQ124: Горошек овощной 2026 (богара) | AR124: Авола | AS124: А-111/1 | AT124: Чигрин Н.А. | AV124: А819ЕВ | AX124: А-111/1 | AY124: Авола | AZ124: 1.2 | BA124: ГРК (богара) | BB124: богара | BC124: 7 | BD124: 46183 | BG124: 53-63 | BH124: Высший | BI124: 117 | BJ124: 57
A125: Степень зрелости | C125: =Таблица3[[#This Row],[Степень зрелости вспом]] -> 53 | D125: 200 | G125: 13060 | I125: 11230 | J125: Горошек овощной 2026 (богара) | K125: Авола | L125: А-38 | M125: Ревенко Андрей Вячеславович | R125: А781РР | T125: =VLOOKUP(Таблица3[[#This Row],[№ акта]],$AJ$1:$BJ$691,15,FALSE) -> А-38 | U125: =VLOOKUP(Таблица3[[#This Row],[№ акта]],$AJ$1:$BJ$691,16,FALSE) -> Авола | V125: =VLOOKUP(Таблица3[[#This Row],[№ акта]],$AJ$1:$BJ$691,17,FALSE) -> 1.7 | W125: =VLOOKUP(Таблица3[[#This Row],[№ акта]],$AJ$1:$BJ$691,18,FALSE) -> ГРК (богара) | X125: =VLOOKUP(Таблица3[[#This Row],[№ акта]],$AJ$1:$BJ$691,19,FALSE) -> богара | Y125: =VLOOKUP(Таблица3[[#This Row],[№ акта]],$AJ$1:$BJ$691,20,FALSE) -> 7 | Z125: =VLOOKUP(Таблица3[[#This Row],[№ акта]],$AJ$1:$BJ$691,21,FALSE) -> 46183 | AA125: =Таблица3[[#This Row],[Регистратор.Вес нетто]] -> 13060 | AB125: =IF(VLOOKUP(Таблица3[[#This Row],[№ акта]],$AJ$1:$BJ$691,23,FALSE)<>0,VLOOKUP(Таблица3[[#This Row],[№ акта]],$AJ$1:$BJ$691,23,FALSE),"-") -> ГРАНД-СТАР ООО | AC125: =IF(Таблица3[[#This Row],[Степень зрелости вспом]]=0,"нет данных",IF(Таблица3[[#This Row],[Степень зрелости вспом]]<40,"до 40",IF(Таблица3[[#This Row],[Степень зрелости вспом]]<53,"40-52",IF(Таблица3[[#This Row],[Степень зрелости вспом]]<64,"53-63",IF(Таблица3[[#This Row],[Степень зрелости вспом]]<67,"64-66",IF(Таблица3[[#This Row],[Степень зрелости вспом]]<85,"67-85",)))))) -> 53-63 | AD125: Высший | AE125: 280 | AF125: 46183 | AG125: 200/7 | AH125: =IFERROR(VLOOKUP(Таблица3[[#This Row],[№ акта]],'Степень зрелости 2026'!$H$12:$I$800,2,FALSE),) -> 53 | AJ125: 280 | AK125: 46183 | AL125: 200 | AO125: 13060 | AP125: 11230 | AQ125: Горошек овощной 2026 (богара) | AR125: Авола | AS125: А-38 | AT125: Ревенко Андрей Вячеславович | AV125: А781РР | AX125: А-38 | AY125: Авола | AZ125: 1.7 | BA125: ГРК (богара) | BB125: богара | BC125: 7 | BD125: 46183 | BE125: 13060 | BF125: ГРАНД-СТАР ООО | BG125: 53-63 | BH125: Высший | BI125: 200/7 | BJ125: 53
A126: Степень зрелости | C126: =Таблица3[[#This Row],[Степень зрелости вспом]] -> 60 | D126: 201 | G126: 13210 | I126: 11955.1 | J126: Горошек овощной 2026 (богара) | K126: Авола | L126: А-38 | M126: Богучарский А. И. | R126: А718ВХ | T126: =VLOOKUP(Таблица3[[#This Row],[№ акта]],$AJ$1:$BJ$691,15,FALSE) -> А-38 | U126: =VLOOKUP(Таблица3[[#This Row],[№ акта]],$AJ$1:$BJ$691,16,FALSE) -> Авола | V126: =VLOOKUP(Таблица3[[#This Row],[№ акта]],$AJ$1:$BJ$691,17,FALSE) -> 1.7 | W126: =VLOOKUP(Таблица3[[#This Row],[№ акта]],$AJ$1:$BJ$691,18,FALSE) -> ГРК (богара) | X126: =VLOOKUP(Таблица3[[#This Row],[№ акта]],$AJ$1:$BJ$691,19,FALSE) -> богара | Y126: =VLOOKUP(Таблица3[[#This Row],[№ акта]],$AJ$1:$BJ$691,20,FALSE) -> 7 | Z126: =VLOOKUP(Таблица3[[#This Row],[№ акта]],$AJ$1:$BJ$691,21,FALSE) -> 46183 | AB126: =IF(VLOOKUP(Таблица3[[#This Row],[№ акта]],$AJ$1:$BJ$691,23,FALSE)<>0,VLOOKUP(Таблица3[[#This Row],[№ акта]],$AJ$1:$BJ$691,23,FALSE),"-") -> - | AC126: =IF(Таблица3[[#This Row],[Степень зрелости вспом]]=0,"нет данных",IF(Таблица3[[#This Row],[Степень зрелости вспом]]<40,"до 40",IF(Таблица3[[#This Row],[Степень зрелости вспом]]<53,"40-52",IF(Таблица3[[#This Row],[Степень зрелости вспом]]<64,"53-63",IF(Таблица3[[#This Row],[Степень зрелости вспом]]<67,"64-66",IF(Таблица3[[#This Row],[Степень зрелости вспом]]<85,"67-85",)))))) -> 53-63 | AD126: Высший | AE126: 133 | AF126: 46183 | AG126: 118 | AH126: =IFERROR(VLOOKUP(Таблица3[[#This Row],[№ акта]],'Степень зрелости 2026'!$H$12:$I$800,2,FALSE),) -> 60 | AJ126: 133 | AK126: 46183 | AL126: 201 | AO126: 13210 | AP126: 11955.1 | AQ126: Горошек овощной 2026 (богара) | AR126: Авола | AS126: А-38 | AT126: Богучарский А. И. | AV126: А718ВХ | AX126: А-38 | AY126: Авола | AZ126: 1.7 | BA126: ГРК (богара) | BB126: богара | BC126: 7 | BD126: 46183 | BG126: 53-63 | BH126: Высший | BI126: 118 | BJ126: 60
A127: Степень зрелости | C127: =Таблица3[[#This Row],[Степень зрелости вспом]] -> 54 | D127: 202 | G127: 4620 | I127: 4204.2 | J127: Горошек овощной 2026 (богара) | K127: Авола | L127: А-111 | M127: Сайко Владимир Николаевич | R127: Т919РВ | T127: =VLOOKUP(Таблица3[[#This Row],[№ акта]],$AJ$1:$BJ$691,15,FALSE) -> А-111/1 | U127: =VLOOKUP(Таблица3[[#This Row],[№ акта]],$AJ$1:$BJ$691,16,FALSE) -> Авола | V127: =VLOOKUP(Таблица3[[#This Row],[№ акта]],$AJ$1:$BJ$691,17,FALSE) -> 0.8 | W127: =VLOOKUP(Таблица3[[#This Row],[№ акта]],$AJ$1:$BJ$691,18,FALSE) -> ГРК (богара) | X127: =VLOOKUP(Таблица3[[#This Row],[№ акта]],$AJ$1:$BJ$691,19,FALSE) -> богара | Y127: =VLOOKUP(Таблица3[[#This Row],[№ акта]],$AJ$1:$BJ$691,20,FALSE) -> 7 | Z127: =VLOOKUP(Таблица3[[#This Row],[№ акта]],$AJ$1:$BJ$691,21,FALSE) -> 46183 | AB127: =IF(VLOOKUP(Таблица3[[#This Row],[№ акта]],$AJ$1:$BJ$691,23,FALSE)<>0,VLOOKUP(Таблица3[[#This Row],[№ акта]],$AJ$1:$BJ$691,23,FALSE),"-") -> - | AC127: =IF(Таблица3[[#This Row],[Степень зрелости вспом]]=0,"нет данных",IF(Таблица3[[#This Row],[Степень зрелости вспом]]<40,"до 40",IF(Таблица3[[#This Row],[Степень зрелости вспом]]<53,"40-52",IF(Таблица3[[#This Row],[Степень зрелости вспом]]<64,"53-63",IF(Таблица3[[#This Row],[Степень зрелости вспом]]<67,"64-66",IF(Таблица3[[#This Row],[Степень зрелости вспом]]<85,"67-85",)))))) -> 53-63 | AD127: Высший | AE127: 132 | AF127: 46183 | AG127: 119 | AH127: =IFERROR(VLOOKUP(Таблица3[[#This Row],[№ акта]],'Степень зрелости 2026'!$H$12:$I$800,2,FALSE),) -> 54 | AJ127: 132 | AK127: 46183 | AL127: 202 | AO127: 4620 | AP127: 4204.2 | AQ127: Горошек овощной 2026 (богара) | AR127: Авола | AS127: А-111 | AT127: Сайко Владимир Николаевич | AV127: Т919РВ | AX127: А-111/1 | AY127: Авола | AZ127: 0.8 | BA127: ГРК (богара) | BB127: богара | BC127: 7 | BD127: 46183 | BG127: 53-63 | BH127: Высший | BI127: 119 | BJ127: 54
A128: Степень зрелости | C128: =Таблица3[[#This Row],[Степень зрелости вспом]] -> 44 | D128: 203 | G128: 12830 | I128: 11499 | J128: Горошек овощной 2026 (богара) | K128: Авола | L128: А-38 | M128: Извеков Владимир Владимирович | R128: Н378ХЕ | T128: =VLOOKUP(Таблица3[[#This Row],[№ акта]],$AJ$1:$BJ$691,15,FALSE) -> А-38 | U128: =VLOOKUP(Таблица3[[#This Row],[№ акта]],$AJ$1:$BJ$691,16,FALSE) -> Авола | V128: =VLOOKUP(Таблица3[[#This Row],[№ акта]],$AJ$1:$BJ$691,17,FALSE) -> 1.7 | W128: =VLOOKUP(Таблица3[[#This Row],[№ акта]],$AJ$1:$BJ$691,18,FALSE) -> ГРК (богара) | X128: =VLOOKUP(Таблица3[[#This Row],[№ акта]],$AJ$1:$BJ$691,19,FALSE) -> богара | Y128: =VLOOKUP(Таблица3[[#This Row],[№ акта]],$AJ$1:$BJ$691,20,FALSE) -> 7 | Z128: =VLOOKUP(Таблица3[[#This Row],[№ акта]],$AJ$1:$BJ$691,21,FALSE) -> 46183 | AA128: =Таблица3[[#This Row],[Регистратор.Вес нетто]] -> 12830 | AB128: =IF(VLOOKUP(Таблица3[[#This Row],[№ акта]],$AJ$1:$BJ$691,23,FALSE)<>0,VLOOKUP(Таблица3[[#This Row],[№ акта]],$AJ$1:$BJ$691,23,FALSE),"-") -> ГРАНД-СТАР ООО | AC128: =IF(Таблица3[[#This Row],[Степень зрелости вспом]]=0,"нет данных",IF(Таблица3[[#This Row],[Степень зрелости вспом]]<40,"до 40",IF(Таблица3[[#This Row],[Степень зрелости вспом]]<53,"40-52",IF(Таблица3[[#This Row],[Степень зрелости вспом]]<64,"53-63",IF(Таблица3[[#This Row],[Степень зрелости вспом]]<67,"64-66",IF(Таблица3[[#This Row],[Степень зрелости вспом]]<85,"67-85",)))))) -> 40-52 | AD128: Высший | AE128: 281 | AF128: 46183 | AG128: 203/8 | AH128: =IFERROR(VLOOKUP(Таблица3[[#This Row],[№ акта]],'Степень зрелости 2026'!$H$12:$I$800,2,FALSE),) -> 44 | AJ128: 281 | AK128: 46183 | AL128: 203 | AO128: 12830 | AP128: 11499 | AQ128: Горошек овощной 2026 (богара) | AR128: Авола | AS128: А-38 | AT128: Извеков Владимир Владимирович | AV128: Н378ХЕ | AX128: А-38 | AY128: Авола | AZ128: 1.7 | BA128: ГРК (богара) | BB128: богара | BC128: 7 | BD128: 46183 | BE128: 12830 | BF128: ГРАНД-СТАР ООО | BG128: 40-52 | BH128: Высший | BI128: 203/8 | BJ128: 44
A129: Степень зрелости | C129: =Таблица3[[#This Row],[Степень зрелости вспом]] -> 58 | D129: 204 | G129: 13310 | I129: 12378.3 | J129: Горошек овощной 2026 (богара) | K129: Авола | L129: А-38 | M129: Кудря Евгений | R129: А719ОО | T129: =VLOOKUP(Таблица3[[#This Row],[№ акта]],$AJ$1:$BJ$691,15,FALSE) -> А-38 | U129: =VLOOKUP(Таблица3[[#This Row],[№ акта]],$AJ$1:$BJ$691,16,FALSE) -> Авола | V129: =VLOOKUP(Таблица3[[#This Row],[№ акта]],$AJ$1:$BJ$691,17,FALSE) -> 1.7 | W129: =VLOOKUP(Таблица3[[#This Row],[№ акта]],$AJ$1:$BJ$691,18,FALSE) -> ГРК (богара) | X129: =VLOOKUP(Таблица3[[#This Row],[№ акта]],$AJ$1:$BJ$691,19,FALSE) -> богара | Y129: =VLOOKUP(Таблица3[[#This Row],[№ акта]],$AJ$1:$BJ$691,20,FALSE) -> 7 | Z129: =VLOOKUP(Таблица3[[#This Row],[№ акта]],$AJ$1:$BJ$691,21,FALSE) -> 46183 | AB129: =IF(VLOOKUP(Таблица3[[#This Row],[№ акта]],$AJ$1:$BJ$691,23,FALSE)<>0,VLOOKUP(Таблица3[[#This Row],[№ акта]],$AJ$1:$BJ$691,23,FALSE),"-") -> - | AC129: =IF(Таблица3[[#This Row],[Степень зрелости вспом]]=0,"нет данных",IF(Таблица3[[#This Row],[Степень зрелости вспом]]<40,"до 40",IF(Таблица3[[#This Row],[Степень зрелости вспом]]<53,"40-52",IF(Таблица3[[#This Row],[Степень зрелости вспом]]<64,"53-63",IF(Таблица3[[#This Row],[Степень зрелости вспом]]<67,"64-66",IF(Таблица3[[#This Row],[Степень зрелости вспом]]<85,"67-85",)))))) -> 53-63 | AD129: Высший | AE129: 134 | AF129: 46183 | AG129: 120 | AH129: =IFERROR(VLOOKUP(Таблица3[[#This Row],[№ акта]],'Степень зрелости 2026'!$H$12:$I$800,2,FALSE),) -> 58 | AJ129: 134 | AK129: 46183 | AL129: 204 | AO129: 13310 | AP129: 12378.3 | AQ129: Горошек овощной 2026 (богара) | AR129: Авола | AS129: А-38 | AT129: Кудря Евгений | AV129: А719ОО | AX129: А-38 | AY129: Авола | AZ129: 1.7 | BA129: ГРК (богара) | BB129: богара | BC129: 7 | BD129: 46183 | BG129: 53-63 | BH129: Высший | BI129: 120 | BJ129: 58
A130: Степень зрелости | C130: =Таблица3[[#This Row],[Степень зрелости вспом]] -> 48 | D130: 205 | G130: 17430 | I130: 16555 | J130: Горошек овощной 2026 (богара) | K130: Авола | L130: А-38 | M130: Мормуль А.Е. | R130: Х474КЕ | T130: =VLOOKUP(Таблица3[[#This Row],[№ акта]],$AJ$1:$BJ$691,15,FALSE) -> А-38 | U130: =VLOOKUP(Таблица3[[#This Row],[№ акта]],$AJ$1:$BJ$691,16,FALSE) -> Авола | V130: =VLOOKUP(Таблица3[[#This Row],[№ акта]],$AJ$1:$BJ$691,17,FALSE) -> 2.3 | W130: =VLOOKUP(Таблица3[[#This Row],[№ акта]],$AJ$1:$BJ$691,18,FALSE) -> ГРК (богара) | X130: =VLOOKUP(Таблица3[[#This Row],[№ акта]],$AJ$1:$BJ$691,19,FALSE) -> богара | Y130: =VLOOKUP(Таблица3[[#This Row],[№ акта]],$AJ$1:$BJ$691,20,FALSE) -> 7 | Z130: =VLOOKUP(Таблица3[[#This Row],[№ акта]],$AJ$1:$BJ$691,21,FALSE) -> 46183 | AA130: =Таблица3[[#This Row],[Регистратор.Вес нетто]] -> 17430 | AB130: =IF(VLOOKUP(Таблица3[[#This Row],[№ акта]],$AJ$1:$BJ$691,23,FALSE)<>0,VLOOKUP(Таблица3[[#This Row],[№ акта]],$AJ$1:$BJ$691,23,FALSE),"-") -> Пищевик ООО | AC130: =IF(Таблица3[[#This Row],[Степень зрелости вспом]]=0,"нет данных",IF(Таблица3[[#This Row],[Степень зрелости вспом]]<40,"до 40",IF(Таблица3[[#This Row],[Степень зрелости вспом]]<53,"40-52",IF(Таблица3[[#This Row],[Степень зрелости вспом]]<64,"53-63",IF(Таблица3[[#This Row],[Степень зрелости вспом]]<67,"64-66",IF(Таблица3[[#This Row],[Степень зрелости вспом]]<85,"67-85",)))))) -> 40-52 | AD130: Высший | AE130: 287 | AF130: 46183 | AG130: 205/9 | AH130: =IFERROR(VLOOKUP(Таблица3[[#This Row],[№ акта]],'Степень зрелости 2026'!$H$12:$I$800,2,FALSE),) -> 48 | AJ130: 287 | AK130: 46183 | AL130: 205 | AO130: 17430 | AP130: 16555 | AQ130: Горошек овощной 2026 (богара) | AR130: Авола | AS130: А-38 | AT130: Мормуль А.Е. | AV130: Х474КЕ | AX130: А-38 | AY130: Авола | AZ130: 2.3 | BA130: ГРК (богара) | BB130: богара | BC130: 7 | BD130: 46183 | BE130: 17430 | BF130: Пищевик ООО | BG130: 40-52 | BH130: Высший | BI130: 205/9 | BJ130: 48
A131: Степень зрелости | C131: =Таблица3[[#This Row],[Степень зрелости вспом]] -> 61 | D131: 206 | G131: 13330 | I131: 11730.4 | J131: Горошек овощной 2026 (богара) | K131: Авола | L131: А-38 | M131: Черевко Александр Владимирович | R131: А114МК | T131: =VLOOKUP(Таблица3[[#This Row],[№ акта]],$AJ$1:$BJ$691,15,FALSE) -> А-38 | U131: =VLOOKUP(Таблица3[[#This Row],[№ акта]],$AJ$1:$BJ$691,16,FALSE) -> Авола | V131: =VLOOKUP(Таблица3[[#This Row],[№ акта]],$AJ$1:$BJ$691,17,FALSE) -> 1.7 | W131: =VLOOKUP(Таблица3[[#This Row],[№ акта]],$AJ$1:$BJ$691,18,FALSE) -> ГРК (богара) | X131: =VLOOKUP(Таблица3[[#This Row],[№ акта]],$AJ$1:$BJ$691,19,FALSE) -> богара | Y131: =VLOOKUP(Таблица3[[#This Row],[№ акта]],$AJ$1:$BJ$691,20,FALSE) -> 7 | Z131: =VLOOKUP(Таблица3[[#This Row],[№ акта]],$AJ$1:$BJ$691,21,FALSE) -> 46183 | AB131: =IF(VLOOKUP(Таблица3[[#This Row],[№ акта]],$AJ$1:$BJ$691,23,FALSE)<>0,VLOOKUP(Таблица3[[#This Row],[№ акта]],$AJ$1:$BJ$691,23,FALSE),"-") -> - | AC131: =IF(Таблица3[[#This Row],[Степень зрелости вспом]]=0,"нет данных",IF(Таблица3[[#This Row],[Степень зрелости вспом]]<40,"до 40",IF(Таблица3[[#This Row],[Степень зрелости вспом]]<53,"40-52",IF(Таблица3[[#This Row],[Степень зрелости вспом]]<64,"53-63",IF(Таблица3[[#This Row],[Степень зрелости вспом]]<67,"64-66",IF(Таблица3[[#This Row],[Степень зрелости вспом]]<85,"67-85",)))))) -> 53-63 | AD131: Высший | AE131: 135 | AF131: 46183 | AG131: 121 | AH131: =IFERROR(VLOOKUP(Таблица3[[#This Row],[№ акта]],'Степень зрелости 2026'!$H$12:$I$800,2,FALSE),) -> 61 | AJ131: 135 | AK131: 46183 | AL131: 206 | AO131: 13330 | AP131: 11730.4 | AQ131: Горошек овощной 2026 (богара) | AR131: Авола | AS131: А-38 | AT131: Черевко Александр Владимирович | AV131: А114МК | AX131: А-38 | AY131: Авола | AZ131: 1.7 | BA131: ГРК (богара) | BB131: богара | BC131: 7 | BD131: 46183 | BG131: 53-63 | BH131: Высший | BI131: 121 | BJ131: 61
A132: Степень зрелости | C132: =Таблица3[[#This Row],[Степень зрелости вспом]] -> 53 | D132: 207 | G132: 13060 | I132: 11667 | J132: Горошек овощной 2026 (богара) | K132: Авола | L132: А-5 | M132: Магадиев Александр Сайлаувич | R132: У184НО | T132: =VLOOKUP(Таблица3[[#This Row],[№ акта]],$AJ$1:$BJ$691,15,FALSE) -> А-38 | U132: =VLOOKUP(Таблица3[[#This Row],[№ акта]],$AJ$1:$BJ$691,16,FALSE) -> Авола | V132: =VLOOKUP(Таблица3[[#This Row],[№ акта]],$AJ$1:$BJ$691,17,FALSE) -> 1.6 | W132: =VLOOKUP(Таблица3[[#This Row],[№ акта]],$AJ$1:$BJ$691,18,FALSE) -> ГРК (богара) | X132: =VLOOKUP(Таблица3[[#This Row],[№ акта]],$AJ$1:$BJ$691,19,FALSE) -> богара | Y132: =VLOOKUP(Таблица3[[#This Row],[№ акта]],$AJ$1:$BJ$691,20,FALSE) -> 7 | Z132: =VLOOKUP(Таблица3[[#This Row],[№ акта]],$AJ$1:$BJ$691,21,FALSE) -> 46183 | AA132: =Таблица3[[#This Row],[Регистратор.Вес нетто]] -> 13060 | AB132: =IF(VLOOKUP(Таблица3[[#This Row],[№ акта]],$AJ$1:$BJ$691,23,FALSE)<>0,VLOOKUP(Таблица3[[#This Row],[№ акта]],$AJ$1:$BJ$691,23,FALSE),"-") -> ГРАНД-СТАР ООО | AC132: =IF(Таблица3[[#This Row],[Степень зрелости вспом]]=0,"нет данных",IF(Таблица3[[#This Row],[Степень зрелости вспом]]<40,"до 40",IF(Таблица3[[#This Row],[Степень зрелости вспом]]<53,"40-52",IF(Таблица3[[#This Row],[Степень зрелости вспом]]<64,"53-63",IF(Таблица3[[#This Row],[Степень зрелости вспом]]<67,"64-66",IF(Таблица3[[#This Row],[Степень зрелости вспом]]<85,"67-85",)))))) -> 53-63 | AD132: Высший | AE132: 282 | AF132: 46183 | AG132: 207/13 | AH132: =IFERROR(VLOOKUP(Таблица3[[#This Row],[№ акта]],'Степень зрелости 2026'!$H$12:$I$800,2,FALSE),) -> 53 | AJ132: 282 | AK132: 46183 | AL132: 207 | AO132: 13060 | AP132: 11667 | AQ132: Горошек овощной 2026 (богара) | AR132: Авола | AS132: А-5 | AT132: Магадиев Александр Сайлаувич | AV132: У184НО | AX132: А-38 | AY132: Авола | AZ132: 1.6 | BA132: ГРК (богара) | BB132: богара | BC132: 7 | BD132: 46183 | BE132: 13060 | BF132: ГРАНД-СТАР ООО | BG132: 53-63 | BH132: Высший | BI132: 207/13 | BJ132: 53
A133: Степень зрелости | C133: =Таблица3[[#This Row],[Степень зрелости вспом]] -> 55 | D133: 208 | G133: 13700 | I133: 11987.5 | J133: Горошек овощной 2026 (богара) | K133: Авола | L133: А-38 | M133: Чигрин Н.А. | R133: А819ЕВ | T133: =VLOOKUP(Таблица3[[#This Row],[№ акта]],$AJ$1:$BJ$691,15,FALSE) -> А-38 | U133: =VLOOKUP(Таблица3[[#This Row],[№ акта]],$AJ$1:$BJ$691,16,FALSE) -> Авола | V133: =VLOOKUP(Таблица3[[#This Row],[№ акта]],$AJ$1:$BJ$691,17,FALSE) -> 1.8 | W133: =VLOOKUP(Таблица3[[#This Row],[№ акта]],$AJ$1:$BJ$691,18,FALSE) -> ГРК (богара) | X133: =VLOOKUP(Таблица3[[#This Row],[№ акта]],$AJ$1:$BJ$691,19,FALSE) -> богара | Y133: =VLOOKUP(Таблица3[[#This Row],[№ акта]],$AJ$1:$BJ$691,20,FALSE) -> 7 | Z133: =VLOOKUP(Таблица3[[#This Row],[№ акта]],$AJ$1:$BJ$691,21,FALSE) -> 46183 | AB133: =IF(VLOOKUP(Таблица3[[#This Row],[№ акта]],$AJ$1:$BJ$691,23,FALSE)<>0,VLOOKUP(Таблица3[[#This Row],[№ акта]],$AJ$1:$BJ$691,23,FALSE),"-") -> - | AC133: =IF(Таблица3[[#This Row],[Степень зрелости вспом]]=0,"нет данных",IF(Таблица3[[#This Row],[Степень зрелости вспом]]<40,"до 40",IF(Таблица3[[#This Row],[Степень зрелости вспом]]<53,"40-52",IF(Таблица3[[#This Row],[Степень зрелости вспом]]<64,"53-63",IF(Таблица3[[#This Row],[Степень зрелости вспом]]<67,"64-66",IF(Таблица3[[#This Row],[Степень зрелости вспом]]<85,"67-85",)))))) -> 53-63 | AD133: Высший | AE133: 136 | AF133: 46183 | AG133: 122 | AH133: =IFERROR(VLOOKUP(Таблица3[[#This Row],[№ акта]],'Степень зрелости 2026'!$H$12:$I$800,2,FALSE),) -> 55 | AJ133: 136 | AK133: 46183 | AL133: 208 | AO133: 13700 | AP133: 11987.5 | AQ133: Горошек овощной 2026 (богара) | AR133: Авола | AS133: А-38 | AT133: Чигрин Н.А. | AV133: А819ЕВ | AX133: А-38 | AY133: Авола | AZ133: 1.8 | BA133: ГРК (богара) | BB133: богара | BC133: 7 | BD133: 46183 | BG133: 53-63 | BH133: Высший | BI133: 122 | BJ133: 55
A134: Степень зрелости | C134: =Таблица3[[#This Row],[Степень зрелости вспом]] -> 59 | D134: 209 | G134: 13040 | I134: 11670.8 | J134: Горошек овощной 2026 (богара) | K134: Авола | L134: А-38 | M134: Богучарский А. И. | R134: А718ВХ | T134: =VLOOKUP(Таблица3[[#This Row],[№ акта]],$AJ$1:$BJ$691,15,FALSE) -> А-38 | U134: =VLOOKUP(Таблица3[[#This Row],[№ акта]],$AJ$1:$BJ$691,16,FALSE) -> Авола | V134: =VLOOKUP(Таблица3[[#This Row],[№ акта]],$AJ$1:$BJ$691,17,FALSE) -> 1.7 | W134: =VLOOKUP(Таблица3[[#This Row],[№ акта]],$AJ$1:$BJ$691,18,FALSE) -> ГРК (богара) | X134: =VLOOKUP(Таблица3[[#This Row],[№ акта]],$AJ$1:$BJ$691,19,FALSE) -> богара | Y134: =VLOOKUP(Таблица3[[#This Row],[№ акта]],$AJ$1:$BJ$691,20,FALSE) -> 7 | Z134: =VLOOKUP(Таблица3[[#This Row],[№ акта]],$AJ$1:$BJ$691,21,FALSE) -> 46183 | AB134: =IF(VLOOKUP(Таблица3[[#This Row],[№ акта]],$AJ$1:$BJ$691,23,FALSE)<>0,VLOOKUP(Таблица3[[#This Row],[№ акта]],$AJ$1:$BJ$691,23,FALSE),"-") -> - | AC134: =IF(Таблица3[[#This Row],[Степень зрелости вспом]]=0,"нет данных",IF(Таблица3[[#This Row],[Степень зрелости вспом]]<40,"до 40",IF(Таблица3[[#This Row],[Степень зрелости вспом]]<53,"40-52",IF(Таблица3[[#This Row],[Степень зрелости вспом]]<64,"53-63",IF(Таблица3[[#This Row],[Степень зрелости вспом]]<67,"64-66",IF(Таблица3[[#This Row],[Степень зрелости вспом]]<85,"67-85",)))))) -> 53-63 | AD134: Высший | AE134: 137 | AF134: 46183 | AG134: 118 | AH134: =IFERROR(VLOOKUP(Таблица3[[#This Row],[№ акта]],'Степень зрелости 2026'!$H$12:$I$800,2,FALSE),) -> 59 | AJ134: 137 | AK134: 46183 | AL134: 209 | AO134: 13040 | AP134: 11670.8 | AQ134: Горошек овощной 2026 (богара) | AR134: Авола | AS134: А-38 | AT134: Богучарский А. И. | AV134: А718ВХ | AX134: А-38 | AY134: Авола | AZ134: 1.7 | BA134: ГРК (богара) | BB134: богара | BC134: 7 | BD134: 46183 | BG134: 53-63 | BH134: Высший | BI134: 118 | BJ134: 59
A135: Степень зрелости | C135: =Таблица3[[#This Row],[Степень зрелости вспом]] -> 57 | D135: 210 | G135: 4400 | I135: 3894 | J135: Горошек овощной 2026 (богара) | K135: Авола | L135: А-38 | M135: Сайко Владимир Николаевич | R135: Т919РВ | T135: =VLOOKUP(Таблица3[[#This Row],[№ акта]],$AJ$1:$BJ$691,15,FALSE) -> А-38 | U135: =VLOOKUP(Таблица3[[#This Row],[№ акта]],$AJ$1:$BJ$691,16,FALSE) -> Авола | V135: =VLOOKUP(Таблица3[[#This Row],[№ акта]],$AJ$1:$BJ$691,17,FALSE) -> 0.6 | W135: =VLOOKUP(Таблица3[[#This Row],[№ акта]],$AJ$1:$BJ$691,18,FALSE) -> ГРК (богара) | X135: =VLOOKUP(Таблица3[[#This Row],[№ акта]],$AJ$1:$BJ$691,19,FALSE) -> богара | Y135: =VLOOKUP(Таблица3[[#This Row],[№ акта]],$AJ$1:$BJ$691,20,FALSE) -> 7 | Z135: =VLOOKUP(Таблица3[[#This Row],[№ акта]],$AJ$1:$BJ$691,21,FALSE) -> 46183 | AB135: =IF(VLOOKUP(Таблица3[[#This Row],[№ акта]],$AJ$1:$BJ$691,23,FALSE)<>0,VLOOKUP(Таблица3[[#This Row],[№ акта]],$AJ$1:$BJ$691,23,FALSE),"-") -> - | AC135: =IF(Таблица3[[#This Row],[Степень зрелости вспом]]=0,"нет данных",IF(Таблица3[[#This Row],[Степень зрелости вспом]]<40,"до 40",IF(Таблица3[[#This Row],[Степень зрелости вспом]]<53,"40-52",IF(Таблица3[[#This Row],[Степень зрелости вспом]]<64,"53-63",IF(Таблица3[[#This Row],[Степень зрелости вспом]]<67,"64-66",IF(Таблица3[[#This Row],[Степень зрелости вспом]]<85,"67-85",)))))) -> 53-63 | AD135: Высший | AE135: 138 | AF135: 46183 | AG135: 124 | AH135: =IFERROR(VLOOKUP(Таблица3[[#This Row],[№ акта]],'Степень зрелости 2026'!$H$12:$I$800,2,FALSE),) -> 57 | AJ135: 138 | AK135: 46183 | AL135: 210 | AO135: 4400 | AP135: 3894 | AQ135: Горошек овощной 2026 (богара) | AR135: Авола | AS135: А-38 | AT135: Сайко Владимир Николаевич | AV135: Т919РВ | AX135: А-38 | AY135: Авола | AZ135: 0.6 | BA135: ГРК (богара) | BB135: богара | BC135: 7 | BD135: 46183 | BG135: 53-63 | BH135: Высший | BI135: 124 | BJ135: 57
